Workbook

Sheet Calculation
A1: Capital Walk- On Notice of Offer of Possession | B1: Column1
A2: Business Unit | B2: =_xlfn.IFNA(VLOOKUP($B$3,[1]Final!$B:$AF,3,0),0) -> M3M Capital Walk in M3M Capital Phase-1
A3: Unit No | B3: R1 165
A4: Collection RM | B4: =VLOOKUP($B$3,'OOP Cases'!$A:$BZ,77,0) -> Priya Anand
A5: Frontend RM | B5: =VLOOKUP($B$3,'OOP Cases'!$A:$BZ,78,0) -> Sabhyata Kapoor
A6: Customer Name | B6: =_xlfn.IFNA(VLOOKUP($B$3,'OOP Cases'!$A:$BW,5,0),0) -> Mr. SHUBHAM SINGH
A7: Schedule | B7: On Notice of Offer of Possession
A8: Invoice Date | B8: =_xlfn.IFNA(VLOOKUP($B$3,'OOP Cases'!$A:$BW,59,0),0) -> 46176
A9: Due Date | B9: =_xlfn.IFNA(VLOOKUP($B$3,'OOP Cases'!$A:$BW,60,0),0) -> 46206
A10: OLD Basic Sales Price | B10: =_xlfn.IFNA(VLOOKUP($B$3,'OOP Cases'!$A:$BW,19,0),0) -> 4870725
A11: New Basic Sales Price | B11: =_xlfn.IFNA(VLOOKUP($B$3,'OOP Cases'!$A:$BW,26,0),0) -> 4870725
A12: Old Area | B12: =_xlfn.IFNA(VLOOKUP($B$3,'OOP Cases'!$A:$BW,10,0),0) -> 649.43
A13: New Area | B13: =_xlfn.IFNA(VLOOKUP($B$3,'OOP Cases'!$A:$BW,11,0),0) -> 649.43
A14: Difference In Area | B14: =_xlfn.IFNA(VLOOKUP($B$3,'OOP Cases'!$A:$BW,12,0),0) -> 0
A15: Discount/Credit Note (Already applied) | B15: =_xlfn.IFNA(VLOOKUP($B$3,'OOP Cases'!$A:$BW,27,0)+VLOOKUP($B$3,'OOP Cases'!$A:$BW,28,0),0) -> 0
A16: PBIC after Increase or Decrease Area | B16: =_xlfn.IFNA(VLOOKUP($B$3,'OOP Cases'!$A:$BW,35,0),0) -> 77985
A17: Total BSP & PBIC | B17: =_xlfn.IFNA(VLOOKUP($B$3,'OOP Cases'!$A:$BW,39,0),0) -> 4948710
A18: Total GST on BSP/ PBIC | B18: =_xlfn.IFNA(VLOOKUP($B$3,'OOP Cases'!$A:$BW,40,0),0) -> 257574
A19: IFMS Amount after Change Area | B19: =_xlfn.IFNA(VLOOKUP($B$3,'OOP Cases'!$A:$BW,38,0),0) -> 77985
A20: Total Amount | B20: =_xlfn.IFNA(VLOOKUP($B$3,'OOP Cases'!$A:$BW,42,0),0) -> 5284269
A21: Total Received | B21: =_xlfn.IFNA(VLOOKUP($B$3,'OOP Cases'!$A:$BW,43,0),0) -> 4653102
A22: Total Payable Without Interest | B22: =B20-B21-B23 -> 631167
A23: Interest Due | B23: =_xlfn.IFNA(VLOOKUP($B$3,'OOP Cases'!$A:$BW,44,0),0) -> 0
A24: Total Accumulation (Subject to Payment demand received within Due Date) | B24: =_xlfn.IFNA(VLOOKUP($B$3,'OOP Cases'!$A:$BX,76,0),0) -> 0
A25: Payable With Interest | B25: =_xlfn.IFNA(VLOOKUP($B$3,'OOP Cases'!$A:$BW,45,0),0) -> 631167
A26: Net Amount Payable With Interest | B26: =B25-B24 -> 631167
A27: * 1% To avoid penal consequences under the Income Tax Act 1961, you are required to comply with provisions of Section 194 IA
A28: (effective from 01st June 2013), by deducting TDS @ 1% from each instalment/payment. Please submit with us TDS certificate/Challan
A29: showing proof of deposition of the same within 7 days from the date of tax so deposited so that the appropriate credit may be allowed in your account
A30: * Stamp Duty Charges is payable extra

Sheet OOP Cases
A1: Unit No | B1: Business Unit | C1: Booking No | D1: Application No | E1: Customer Name | F1: Booking Date | G1: Block | H1: Floor | I1: Hierarchy Level 4 | J1: Suer Area (Sq. ft.) | K1: New Super Area (Sq. ft.) | L1: Diff in Super Area | M1: Carpet Area (Sq. ft.) | N1: New Carpet Area (Sq. ft.) | O1: Diff in Carpet Area Area | P1: Super Area Rate (Booking Rate) | Q1: Carpet Area Rate (Booking Rate) | R1: Current Rate | S1: BSP | T1: GST on BSP as per Old Area | U1: GST%age | V1: Increase/Decrease Area cost | W1: GST% on Increase/Decrease Area cost | X1: Increased Unit Cost due to Excess Discount_Basic | Y1: Increased Unit Cost due to Excess Discount_Tax | Z1: BASIC after Increase or Decrease Area | AA1: Discount/Credit Note (Already applied) | AB1: GST on Credit Note | AC1: Basic Sale Price after discount & Adjustment | AD1: PBIC Rate Carpet Area | AE1: PBIC | AF1: Tax on PBIC | AG1: PBIC on Increase or Decrease Area | AH1: Tax on Diff PBIC | AI1: PBIC after Increase or Decrease Area | AJ1: Tax on PBIC after Increase or Decrease Area | AK1: IFMS Amount | AL1: IFMS Amount after Change Area | AM1: Total BSP & PBIC | AN1: Total GST on BSP/ PBIC | AO1: Total GST+IFMS and Interest | AP1: Grand Total | AQ1: Total Received Till Date | AR1: Interest | AS1: Net Payable with Interest | AT1: ATS Value | AU1: Circle Rate | AV1: Value as per Circle rate | AW1: Stamp Duty Calculation on | AX1: Ceiling up to 1000 of Stamp Duty Calculation Value | AY1: Stamp Duty Percentage | AZ1: stamp duty | BA1: actual stamp duty Ceiling up to Rs. 100 | BB1: Final Total Payable | BC1: Area Variation Super % | BD1: Area Variation Carpet % | BE1: Final Super Area (in sq. mt.) | BF1: Final Carpet Area (in sq. mt.) | BG1: Invocie Date | BH1: Due Date | BI1: Stampduty % for mail merge | BM1: Payment in Favour of | BN1: Account Number | BO1: IFSC Code | BP1: Name of Bank | BQ1: Address of Bank Branch | BR1: Name of Builder | BS1: PAN of the Builder | BT1: Address of the builder | BU1: Address of the Unit/Apartment | BV1: Email ID | BW1: Mobile Number | BX1: Accumulation Amount | BY1: Collection RM | BZ1: Frontend RM
A2: R1 165 | B2: M3M Capital Walk in M3M Capital Phase-1 | C2: WPBOOKING/00001/23-24 | D2: WPFLAP/00016/22-23 | E2: Mr. SHUBHAM SINGH | F2: 45026 | G2: BLOCK-01 | H2: FLOOR 1 | I2: Anchor Units | J2: 649.43 | K2: 649.43 | L2: =K2-J2 -> 0 | M2: 259.95 | N2: 259.95 | O2: =N2-M2 -> 0 | P2: 7500 | Q2: 18737.161 | R2: 22000 | S2: 4870725 | T2: 243536 | U2: =T2/S2 -> 0.049999949 | V2: =L2*P2 -> 0 | W2: =V2*U2 -> 0 | Z2: =S2+V2+X2 -> 4870725 | AC2: =Z2-AA2 -> 4870725 | AD2: =AE2/M2 -> 300 | AE2: 77985 | AF2: 14038 | AG2: =(AD2*O2) -> 0 | AH2: =AG2*18% -> 0 | AI2: =AD2*N2 -> 77985 | AJ2: =ROUNDUP(AI2*18%,0) -> 14038 | AK2: 77985 | AL2: =N2*300 -> 77985 | AM2: =ROUND(AI2+AC2,0) -> 4948710 | AN2: =ROUNDUP(AJ2+W2+T2+Y2-AB2,0) -> 257574 | AO2: =AN2+AL2+AR2 -> 335559 | AP2: =AM2+AO2 -> 5284269 | AQ2: 4653102 | AR2: 0 | AS2: =ROUND(AP2-AQ2,0) -> 631167 | AT2: 0 | AU2: 8800 | AV2: =AU2*N2 -> 2287560 | AW2: =MAX(AM2,AT2,AV2) -> 4948710 | AX2: =CEILING((AW2),1000) -> 4949000 | AY2: 0.07 | AZ2: =AY2*AX2 -> 346430 | BA2: =CEILING(AZ2,100) -> 346500 | BB2: =BA2+AS2 -> 977667 | BC2: =L2/J2% -> 0 | BD2: =O2/M2% -> 0 | BE2: 60.33 | BF2: 24.15 | BG2: 46176 | BH2: =BG2+30 -> 46206 | BI2: 7 | BM2: UBPL M3M CAPITAL MASTER ACCOUNT | BN2: 777705001441 | BO2: ICIC0000399 | BP2: ICICI Bank | BQ2: Shop No - 19, 20, 21, Vipul Orchid Plaza, Suncity, Sector 54, Gurgaon, Haryana -122002 | BR2: Union Buildmart Private Limited | BS2: AABCU4843M | BT2: 41st Floor, Tower-1, M3M International Financial center, sector- 66,Gurugram, Haryana, India 122101 | BU2: (……………..)Village Chauma, Sector – 113, Gurugram, Manesar Urban Complex, GURGAON, HARYANA, INDIA PIN Code: 122017 | BV2: Feedback@m3mindia.com | BW2: 8068970077 | BX2: 0 | BY2: Priya Anand | BZ2: Sabhyata Kapoor
A3: R1 259 | B3: M3M Capital Walk in M3M Capital Phase-1 | C3: WPBOOKING/00009/23-24 | D3: WPFLAP/00005/23-24 | E3: Ms. RACHNA MAHALWALA | F3: 45120 | G3: BLOCK-01 | H3: FLOOR 2 | I3: Anchor Units | J3: 662.58 | K3: 662.58 | L3: =K3-J3 -> 0 | M3: 270.18 | N3: 270.18 | O3: =N3-M3 -> 0 | P3: 7283.0028 | Q3: 17860.582 | R3: 20000 | S3: 4825572 | T3: 241280 | U3: =T3/S3 -> 0.05000029 | V3: =L3*P3 -> 0 | W3: =V3*U3 -> 0 | Z3: =S3+V3+X3 -> 4825572 | AC3: =Z3-AA3 -> 4825572 | AD3: =AE3/M3 -> 300 | AE3: 81054 | AF3: 14590 | AG3: =(AD3*O3) -> 0 | AH3: =AG3*18% -> 0 | AI3: =AD3*N3 -> 81054 | AJ3: =ROUNDUP(AI3*18%,0) -> 14590 | AK3: 81054 | AL3: =N3*300 -> 81054 | AM3: =ROUND(AI3+AC3,0) -> 4906626 | AN3: =ROUNDUP(AJ3+W3+T3+Y3-AB3,0) -> 255870 | AO3: =AN3+AL3+AR3 -> 336924 | AP3: =AM3+AO3 -> 5243550 | AQ3: 3983645 | AR3: 0 | AS3: =ROUND(AP3-AQ3,0) -> 1259905 | AT3: 0 | AU3: 8800 | AV3: =AU3*N3 -> 2377584 | AW3: =MAX(AM3,AT3,AV3) -> 4906626 | AX3: =CEILING((AW3),1000) -> 4907000 | AY3: 0.05 | AZ3: =AY3*AX3 -> 245350 | BA3: =CEILING(AZ3,100) -> 245400 | BB3: =BA3+AS3 -> 1505305 | BC3: =L3/J3% -> 0 | BD3: =O3/M3% -> 0 | BE3: 61.56 | BF3: 25.1 | BG3: 46176 | BH3: =BG3+30 -> 46206 | BI3: 5 | BM3: UBPL M3M CAPITAL MASTER ACCOUNT | BN3: 777705001441 | BO3: ICIC0000399 | BP3: ICICI Bank | BQ3: Shop No - 19, 20, 21, Vipul Orchid Plaza, Suncity, Sector 54, Gurgaon, Haryana -122002 | BR3: Union Buildmart Private Limited | BS3: AABCU4843M | BT3: 41st Floor, Tower-1, M3M International Financial center, sector- 66,Gurugram, Haryana, India 122101 | BU3: (……………..)Village Chauma, Sector – 113, Gurugram, Manesar Urban Complex, GURGAON, HARYANA, INDIA PIN Code: 122017 | BV3: Feedback@m3mindia.com | BW3: 8068970077 | BX3: 0 | BY3: Ritika Singh | BZ3: Sabhyata Kapoor
A4: R2 214 | B4: M3M Capital Walk in M3M Capital Phase-1 | C4: WPBOOKING/00005/24-25 | D4: WPFLAP/00024/23-24 | E4: Ms. Madhulika Nath | F4: 45398 | G4: BLOCK-02 | H4: FLOOR 2 | I4: Retail | J4: 900 | K4: 900 | L4: =K4-J4 -> 0 | M4: 396 | N4: 396 | O4: =N4-M4 -> 0 | P4: 11576.339 | Q4: 26309.861 | R4: 20000 | S4: 10418705 | T4: 520936 | U4: =T4/S4 -> 0.050000072 | V4: =L4*P4 -> 0 | W4: =V4*U4 -> 0 | Z4: =S4+V4+X4 -> 10418705 | AC4: =Z4-AA4 -> 10418705 | AD4: =AE4/M4 -> 300 | AE4: 118800 | AF4: 21384 | AG4: =(AD4*O4) -> 0 | AH4: =AG4*18% -> 0 | AI4: =AD4*N4 -> 118800 | AJ4: =ROUNDUP(AI4*18%,0) -> 21384 | AK4: 118800 | AL4: =N4*300 -> 118800 | AM4: =ROUND(AI4+AC4,0) -> 10537505 | AN4: =ROUNDUP(AJ4+W4+T4+Y4-AB4,0) -> 542320 | AO4: =AN4+AL4+AR4 -> 661120 | AP4: =AM4+AO4 -> 11198625 | AQ4: 9845677.1 | AR4: 0 | AS4: =ROUND(AP4-AQ4,0) -> 1352948 | AT4: 0 | AU4: 8800 | AV4: =AU4*N4 -> 3484800 | AW4: =MAX(AM4,AT4,AV4) -> 10537505 | AX4: =CEILING((AW4),1000) -> 10538000 | AY4: 0.05 | AZ4: =AY4*AX4 -> 526900 | BA4: =CEILING(AZ4,100) -> 526900 | BB4: =BA4+AS4 -> 1879848 | BC4: =L4/J4% -> 0 | BD4: =O4/M4% -> 0 | BE4: 83.61 | BF4: 36.79 | BG4: 46176 | BH4: =BG4+30 -> 46206 | BI4: 5 | BM4: UBPL M3M CAPITAL MASTER ACCOUNT | BN4: 777705001441 | BO4: ICIC0000399 | BP4: ICICI Bank | BQ4: Shop No - 19, 20, 21, Vipul Orchid Plaza, Suncity, Sector 54, Gurgaon, Haryana -122002 | BR4: Union Buildmart Private Limited | BS4: AABCU4843M | BT4: 41st Floor, Tower-1, M3M International Financial center, sector- 66,Gurugram, Haryana, India 122101 | BU4: (……………..)Village Chauma, Sector – 113, Gurugram, Manesar Urban Complex, GURGAON, HARYANA, INDIA PIN Code: 122017 | BV4: Feedback@m3mindia.com | BW4: 8068970077 | BX4: 0 | BY4: Darshan Lal | BZ4: Shubra
A5: R2 215 | B5: M3M Capital Walk in M3M Capital Phase-1 | C5: WPBOOKING/00009/22-23 | D5: WPFLAP/00006/22-23 | E5: Ms. SHASHI | F5: 44897 | G5: BLOCK-02 | H5: FLOOR 2 | I5: Retail | J5: 372.86 | K5: 372.86 | L5: =K5-J5 -> 0 | M5: 158.23 | N5: 158.23 | O5: =N5-M5 -> 0 | P5: 16165 | Q5: 38091.904 | R5: 20000 | S5: 6027282 | T5: 301364 | U5: =T5/S5 -> 0.049999983 | V5: =L5*P5 -> 0 | W5: =V5*U5 -> 0 | Z5: =S5+V5+X5 -> 6027282 | AC5: =Z5-AA5 -> 6027282 | AD5: =AE5/M5 -> 300 | AE5: 47469 | AF5: 8544 | AG5: =(AD5*O5) -> 0 | AH5: =AG5*18% -> 0 | AI5: =AD5*N5 -> 47469 | AJ5: =ROUNDUP(AI5*18%,0) -> 8545 | AK5: 47469 | AL5: =N5*300 -> 47469 | AM5: =ROUND(AI5+AC5,0) -> 6074751 | AN5: =ROUNDUP(AJ5+W5+T5+Y5-AB5,0) -> 309909 | AO5: =AN5+AL5+AR5 -> 357378 | AP5: =AM5+AO5 -> 6432129 | AQ5: 5695781 | AR5: 0 | AS5: =ROUND(AP5-AQ5,0) -> 736348 | AT5: 0 | AU5: 8800 | AV5: =AU5*N5 -> 1392424 | AW5: =MAX(AM5,AT5,AV5) -> 6074751 | AX5: =CEILING((AW5),1000) -> 6075000 | AY5: 0.05 | AZ5: =AY5*AX5 -> 303750 | BA5: =CEILING(AZ5,100) -> 303800 | BB5: =BA5+AS5 -> 1040148 | BC5: =L5/J5% -> 0 | BD5: =O5/M5% -> 0 | BE5: 34.64 | BF5: 14.7 | BG5: 46176 | BH5: =BG5+30 -> 46206 | BI5: 5 | BM5: UBPL M3M CAPITAL MASTER ACCOUNT | BN5: 777705001441 | BO5: ICIC0000399 | BP5: ICICI Bank | BQ5: Shop No - 19, 20, 21, Vipul Orchid Plaza, Suncity, Sector 54, Gurgaon, Haryana -122002 | BR5: Union Buildmart Private Limited | BS5: AABCU4843M | BT5: 41st Floor, Tower-1, M3M International Financial center, sector- 66,Gurugram, Haryana, India 122101 | BU5: (……………..)Village Chauma, Sector – 113, Gurugram, Manesar Urban Complex, GURGAON, HARYANA, INDIA PIN Code: 122017 | BV5: Feedback@m3mindia.com | BW5: 8068970077 | BX5: 0 | BY5: Priya Anand | BZ5: Shubra
A6: R2 LG 22 | B6: M3M Capital Walk in M3M Capital Phase-1 | C6: WPBOOKING/00006/22-23 | D6: WPFLAP/00003/22-23 | E6: Ms. SUMITI KHURANA | F6: 44893 | G6: BLOCK-02 | H6: BASEMENT 2 | I6: Retail | J6: 450.37 | K6: 450.37 | L6: =K6-J6 -> 0 | M6: 193.75 | N6: 193.75 | O6: =N6-M6 -> 0 | P6: 21619 | Q6: 50253.156 | R6: 40000 | S6: 9736549 | T6: 486826 | U6: =T6/S6 -> 0.049999851 | V6: =L6*P6 -> 0 | W6: =V6*U6 -> 0 | Z6: =S6+V6+X6 -> 9736549 | AA6: 1063188 | AB6: 53160 | AC6: =Z6-AA6 -> 8673361 | AD6: =AE6/M6 -> 300 | AE6: 58125 | AF6: 10462 | AG6: =(AD6*O6) -> 0 | AH6: =AG6*18% -> 0 | AI6: =AD6*N6 -> 58125 | AJ6: =ROUNDUP(AI6*18%,0) -> 10463 | AK6: 58125 | AL6: =N6*300 -> 58125 | AM6: =ROUND(AI6+AC6,0) -> 8731486 | AN6: =ROUNDUP(AJ6+W6+T6+Y6-AB6,0) -> 444129 | AO6: =AN6+AL6+AR6 -> 502254 | AP6: =AM6+AO6 -> 9233740 | AQ6: 8084691 | AR6: 0 | AS6: =ROUND(AP6-AQ6,0) -> 1149049 | AT6: 0 | AU6: 8800 | AV6: =AU6*N6 -> 1705000 | AW6: =MAX(AM6,AT6,AV6) -> 8731486 | AX6: =CEILING((AW6),1000) -> 8732000 | AY6: 0.06 | AZ6: =AY6*AX6 -> 523920 | BA6: =CEILING(AZ6,100) -> 524000 | BB6: =BA6+AS6 -> 1673049 | BC6: =L6/J6% -> 0 | BD6: =O6/M6% -> 0 | BE6: 41.84 | BF6: 18 | BG6: 46176 | BH6: =BG6+30 -> 46206 | BI6: 6 | BM6: UBPL M3M CAPITAL MASTER ACCOUNT | BN6: 777705001441 | BO6: ICIC0000399 | BP6: ICICI Bank | BQ6: Shop No - 19, 20, 21, Vipul Orchid Plaza, Suncity, Sector 54, Gurgaon, Haryana -122002 | BR6: Union Buildmart Private Limited | BS6: AABCU4843M | BT6: 41st Floor, Tower-1, M3M International Financial center, sector- 66,Gurugram, Haryana, India 122101 | BU6: (……………..)Village Chauma, Sector – 113, Gurugram, Manesar Urban Complex, GURGAON, HARYANA, INDIA PIN Code: 122017 | BV6: Feedback@m3mindia.com | BW6: 8068970077 | BX6: 0 | BY6: Darshan Lal | BZ6: Shubra
A7: R2 UG 23 | B7: M3M Capital Walk in M3M Capital Phase-1 | C7: WPBOOKING/00013/22-23 | D7: WPFLAP/00009/22-23 | E7: Ms. SHYAMA GOYAL | F7: 44978 | G7: BLOCK-02 | H7: BASEMENT 1 | I7: Retail | J7: 685.67 | K7: 725.28 | L7: =K7-J7 -> 39.61 | M7: 288.8 | N7: 320 | O7: =N7-M7 -> 31.2 | P7: 21094 | Q7: 50081.451 | R7: 28000 | S7: 14463523 | T7: 723178 | U7: =T7/S7 -> 0.050000128 | V7: =L7*R7 -> 1109080 | W7: =V7*U7 -> 55454.142 | Z7: =S7+V7+X7 -> 15572603 | AA7: 899069 | AB7: 44954 | AC7: =Z7-AA7 -> 14673534 | AD7: =AE7/M7 -> 300 | AE7: 86640 | AF7: 15596 | AG7: =(AD7*O7) -> 9360 | AH7: =AG7*18% -> 1684.8 | AI7: =AD7*N7 -> 96000 | AJ7: =ROUNDUP(AI7*18%,0) -> 17280 | AK7: 86640 | AL7: =N7*300 -> 96000 | AM7: =ROUND(AI7+AC7,0) -> 14769534 | AN7: =ROUNDUP(AJ7+W7+T7+Y7-AB7,0) -> 750959 | AO7: =AN7+AL7+AR7 -> 846959 | AP7: =AM7+AO7 -> 15616493 | AQ7: 12724457 | AR7: 0 | AS7: =ROUND(AP7-AQ7,0) -> 2892036 | AT7: 0 | AU7: 8800 | AV7: =AU7*N7 -> 2816000 | AW7: =MAX(AM7,AT7,AV7) -> 14769534 | AX7: =CEILING((AW7),1000) -> 14770000 | AY7: 0.05 | AZ7: =AY7*AX7 -> 738500 | BA7: =CEILING(AZ7,100) -> 738500 | BB7: =BA7+AS7 -> 3630536 | BC7: =L7/J7% -> 5.7768314 | BD7: =O7/M7% -> 10.803324 | BE7: 67.38 | BF7: 29.73 | BG7: 46176 | BH7: =BG7+30 -> 46206 | BI7: 5 | BM7: UBPL M3M CAPITAL MASTER ACCOUNT | BN7: 777705001441 | BO7: ICIC0000399 | BP7: ICICI Bank | BQ7: Shop No - 19, 20, 21, Vipul Orchid Plaza, Suncity, Sector 54, Gurgaon, Haryana -122002 | BR7: Union Buildmart Private Limited | BS7: AABCU4843M | BT7: 41st Floor, Tower-1, M3M International Financial center, sector- 66,Gurugram, Haryana, India 122101 | BU7: (……………..)Village Chauma, Sector – 113, Gurugram, Manesar Urban Complex, GURGAON, HARYANA, INDIA PIN Code: 122017 | BV7: Feedback@m3mindia.com | BW7: 8068970077 | BX7: 0 | BY7: Manish Kumar | BZ7: Shubra
A8: R2 212 | B8: M3M Capital Walk in M3M Capital Phase-1 | C8: WPBOOKING/00014/22-23 | D8: WPFLAP/00010/22-23 | E8: Mr. AJAY KUMAR SHARMA | F8: 44995 | G8: BLOCK-02 | H8: FLOOR 2 | I8: Retail | J8: 1202.34 | K8: 1202.34 | L8: =K8-J8 -> 0 | M8: 535.51 | N8: 535.51 | O8: =N8-M8 -> 0 | P8: 6500 | Q8: 14593.957 | R8: 20000 | S8: 7815210 | T8: 390760 | U8: =T8/S8 -> 0.049999936 | V8: =L8*P8 -> 0 | W8: =V8*U8 -> 0 | Z8: =S8+V8+X8 -> 7815210 | AC8: =Z8-AA8 -> 7815210 | AD8: =AE8/M8 -> 300 | AE8: 160653 | AF8: 28918 | AG8: =(AD8*O8) -> 0 | AH8: =AG8*18% -> 0 | AI8: =AD8*N8 -> 160653 | AJ8: =ROUNDUP(AI8*18%,0) -> 28918 | AK8: 160653 | AL8: =N8*300 -> 160653 | AM8: =ROUND(AI8+AC8,0) -> 7975863 | AN8: =ROUNDUP(AJ8+W8+T8+Y8-AB8,0) -> 419678 | AO8: =AN8+AL8+AR8 -> 580333.48 | AP8: =AM8+AO8 -> 8556196.5 | AQ8: 6975075 | AR8: 2.48 | AS8: =ROUND(AP8-AQ8,0) -> 1581121 | AT8: 0 | AU8: 8800 | AV8: =AU8*N8 -> 4712488 | AW8: =MAX(AM8,AT8,AV8) -> 7975863 | AX8: =CEILING((AW8),1000) -> 7976000 | AY8: 0.06 | AZ8: =AY8*AX8 -> 478560 | BA8: =CEILING(AZ8,100) -> 478600 | BB8: =BA8+AS8 -> 2059721 | BC8: =L8/J8% -> 0 | BD8: =O8/M8% -> 0 | BE8: 111.7 | BF8: 49.75 | BG8: 46176 | BH8: =BG8+30 -> 46206 | BI8: 6 | BM8: UBPL M3M CAPITAL MASTER ACCOUNT | BN8: 777705001441 | BO8: ICIC0000399 | BP8: ICICI Bank | BQ8: Shop No - 19, 20, 21, Vipul Orchid Plaza, Suncity, Sector 54, Gurgaon, Haryana -122002 | BR8: Union Buildmart Private Limited | BS8: AABCU4843M | BT8: 41st Floor, Tower-1, M3M International Financial center, sector- 66,Gurugram, Haryana, India 122101 | BU8: (……………..)Village Chauma, Sector – 113, Gurugram, Manesar Urban Complex, GURGAON, HARYANA, INDIA PIN Code: 122017 | BV8: Feedback@m3mindia.com | BW8: 8068970077 | BX8: 0 | BY8: Vidhi Singh | BZ8: Shubra
A9: R2 115 | B9: M3M Capital Walk in M3M Capital Phase-1 | C9: WPBOOKING/00003/22-23 | D9: WPFLAP/00002/22-23 | E9: Mr. SATYA VRAT | F9: 44868 | G9: BLOCK-02 | H9: FLOOR 1 | I9: Retail | J9: 372.86 | K9: 372.86 | L9: =K9-J9 -> 0 | M9: 158.23 | N9: 158.23 | O9: =N9-M9 -> 0 | P9: 15782.999 | Q9: 37191.74 | R9: 22000 | S9: 5884849 | T9: 294242 | U9: =T9/S9 -> 0.049999924 | V9: =L9*P9 -> 0 | W9: =V9*U9 -> 0 | Z9: =S9+V9+X9 -> 5884849 | AA9: 728980 | AB9: 36450 | AC9: =Z9-AA9 -> 5155869 | AD9: =AE9/M9 -> 300 | AE9: 47469 | AF9: 8544 | AG9: =(AD9*O9) -> 0 | AH9: =AG9*18% -> 0 | AI9: =AD9*N9 -> 47469 | AJ9: =ROUNDUP(AI9*18%,0) -> 8545 | AK9: 47469 | AL9: =N9*300 -> 47469 | AM9: =ROUND(AI9+AC9,0) -> 5203338 | AN9: =ROUNDUP(AJ9+W9+T9+Y9-AB9,0) -> 266337 | AO9: =AN9+AL9+AR9 -> 313806 | AP9: =AM9+AO9 -> 5517144 | AQ9: 4795753 | AR9: 0 | AS9: =ROUND(AP9-AQ9,0) -> 721391 | AT9: 0 | AU9: 8800 | AV9: =AU9*N9 -> 1392424 | AW9: =MAX(AM9,AT9,AV9) -> 5203338 | AX9: =CEILING((AW9),1000) -> 5204000 | AY9: 0.06 | AZ9: =AY9*AX9 -> 312240 | BA9: =CEILING(AZ9,100) -> 312300 | BB9: =BA9+AS9 -> 1033691 | BC9: =L9/J9% -> 0 | BD9: =O9/M9% -> 0 | BE9: 34.64 | BF9: 14.7 | BG9: 46176 | BH9: =BG9+30 -> 46206 | BI9: 6 | BM9: UBPL M3M CAPITAL MASTER ACCOUNT | BN9: 777705001441 | BO9: ICIC0000399 | BP9: ICICI Bank | BQ9: Shop No - 19, 20, 21, Vipul Orchid Plaza, Suncity, Sector 54, Gurgaon, Haryana -122002 | BR9: Union Buildmart Private Limited | BS9: AABCU4843M | BT9: 41st Floor, Tower-1, M3M International Financial center, sector- 66,Gurugram, Haryana, India 122101 | BU9: (……………..)Village Chauma, Sector – 113, Gurugram, Manesar Urban Complex, GURGAON, HARYANA, INDIA PIN Code: 122017 | BV9: Feedback@m3mindia.com | BW9: 8068970077 | BX9: 0 | BY9: Priya Anand | BZ9: Shubra
A10: R2 112A | B10: M3M Capital Walk in M3M Capital Phase-1 | C10: WPBOOKING/00017/22-23 | D10: WPFLAP/00012/22-23 | E10: Ms. SAVITA TANWAR | F10: 45001 | G10: BLOCK-02 | H10: FLOOR 1 | I10: Retail | J10: 761.88 | K10: 780 | L10: =K10-J10 -> 18.12 | M10: 330.45 | N10: 348 | O10: =N10-M10 -> 17.55 | P10: 12377.222 | Q10: 28536.717 | R10: 22000 | S10: 9429958 | T10: 471500 | U10: =T10/S10 -> 0.050000223 | V10: =L10*R10 -> 398640 | W10: =V10*U10 -> 19932.089 | Z10: =S10+V10+X10 -> 9828598 | AC10: =Z10-AA10 -> 9828598 | AD10: =AE10/M10 -> 300 | AE10: 99135 | AF10: 17844 | AG10: =(AD10*O10) -> 5265 | AH10: =AG10*18% -> 947.7 | AI10: =AD10*N10 -> 104400 | AJ10: =ROUNDUP(AI10*18%,0) -> 18792 | AK10: 99135 | AL10: =N10*300 -> 104400 | AM10: =ROUND(AI10+AC10,0) -> 9932998 | AN10: =ROUNDUP(AJ10+W10+T10+Y10-AB10,0) -> 510225 | AO10: =AN10+AL10+AR10 -> 614627.1 | AP10: =AM10+AO10 -> 10547625 | AQ10: 8882188.4 | AR10: 2.1 | AS10: =ROUND(AP10-AQ10,0) -> 1665437 | AT10: 0 | AU10: 8800 | AV10: =AU10*N10 -> 3062400 | AW10: =MAX(AM10,AT10,AV10) -> 9932998 | AX10: =CEILING((AW10),1000) -> 9933000 | AY10: 0.05 | AZ10: =AY10*AX10 -> 496650 | BA10: =CEILING(AZ10,100) -> 496700 | BB10: =BA10+AS10 -> 2162137 | BC10: =L10/J10% -> 2.3783273 | BD10: =O10/M10% -> 5.3109396 | BE10: 72.46 | BF10: 32.33 | BG10: 46176 | BH10: =BG10+30 -> 46206 | BI10: 5 | BM10: UBPL M3M CAPITAL MASTER ACCOUNT | BN10: 777705001441 | BO10: ICIC0000399 | BP10: ICICI Bank | BQ10: Shop No - 19, 20, 21, Vipul Orchid Plaza, Suncity, Sector 54, Gurgaon, Haryana -122002 | BR10: Union Buildmart Private Limited | BS10: AABCU4843M | BT10: 41st Floor, Tower-1, M3M International Financial center, sector- 66,Gurugram, Haryana, India 122101 | BU10: (……………..)Village Chauma, Sector – 113, Gurugram, Manesar Urban Complex, GURGAON, HARYANA, INDIA PIN Code: 122017 | BV10: Feedback@m3mindia.com | BW10: 8068970077 | BX10: 0 | BY10: Manish Kumar | BZ10: Shubra
A11: R1 162 | B11: M3M Capital Walk in M3M Capital Phase-1 | C11: WPBOOKING/00004/24-25 | D11: WPFLAP/00025/23-24 | E11: Mr. Ram Niwas Gupta | F11: 45383 | G11: BLOCK-01 | H11: FLOOR 1 | I11: Anchor Units | J11: 662.58 | K11: 662.58 | L11: =K11-J11 -> 0 | M11: 270.18 | N11: 270.18 | O11: =N11-M11 -> 0 | P11: 14400.002 | Q11: 35314.061 | R11: 22000 | S11: 9541153 | T11: 477058 | U11: =T11/S11 -> 0.050000037 | V11: =L11*P11 -> 0 | W11: =V11*U11 -> 0 | Z11: =S11+V11+X11 -> 9541153 | AC11: =Z11-AA11 -> 9541153 | AD11: =AE11/M11 -> 300 | AE11: 81054 | AF11: 14590 | AG11: =(AD11*O11) -> 0 | AH11: =AG11*18% -> 0 | AI11: =AD11*N11 -> 81054 | AJ11: =ROUNDUP(AI11*18%,0) -> 14590 | AK11: 81054 | AL11: =N11*300 -> 81054 | AM11: =ROUND(AI11+AC11,0) -> 9622207 | AN11: =ROUNDUP(AJ11+W11+T11+Y11-AB11,0) -> 491648 | AO11: =AN11+AL11+AR11 -> 572981.66 | AP11: =AM11+AO11 -> 10195189 | AQ11: 8956359.6 | AR11: 279.66 | AS11: =ROUND(AP11-AQ11,0) -> 1238829 | AT11: 0 | AU11: 8800 | AV11: =AU11*N11 -> 2377584 | AW11: =MAX(AM11,AT11,AV11) -> 9622207 | AX11: =CEILING((AW11),1000) -> 9623000 | AY11: 0.07 | AZ11: =AY11*AX11 -> 673610 | BA11: =CEILING(AZ11,100) -> 673700 | BB11: =BA11+AS11 -> 1912529 | BC11: =L11/J11% -> 0 | BD11: =O11/M11% -> 0 | BE11: 61.56 | BF11: 25.1 | BG11: 46176 | BH11: =BG11+30 -> 46206 | BI11: 7 | BM11: UBPL M3M CAPITAL MASTER ACCOUNT | BN11: 777705001441 | BO11: ICIC0000399 | BP11: ICICI Bank | BQ11: Shop No - 19, 20, 21, Vipul Orchid Plaza, Suncity, Sector 54, Gurgaon, Haryana -122002 | BR11: Union Buildmart Private Limited | BS11: AABCU4843M | BT11: 41st Floor, Tower-1, M3M International Financial center, sector- 66,Gurugram, Haryana, India 122101 | BU11: (……………..)Village Chauma, Sector – 113, Gurugram, Manesar Urban Complex, GURGAON, HARYANA, INDIA PIN Code: 122017 | BV11: Feedback@m3mindia.com | BW11: 8068970077 | BX11: 0 | BY11: Ritika Singh | BZ11: Sabhyata Kapoor
A12: R2 216 | B12: M3M Capital Walk in M3M Capital Phase-1 | C12: WPBOOKING/00011/22-23 | D12: WPFLAP/00007/22-23 | E12: Ms. Runa Singh | F12: 44958 | G12: BLOCK-02 | H12: FLOOR 2 | I12: Retail | J12: 684.59 | K12: 725 | L12: =K12-J12 -> 40.41 | M12: 288.48 | N12: 319 | O12: =N12-M12 -> 30.52 | P12: 12349.999 | Q12: 29307.702 | R12: 20000 | S12: 8454686 | T12: 422736 | U12: =T12/S12 -> 0.050000201 | V12: =L12*R12 -> 808200 | W12: =V12*U12 -> 40410.163 | Z12: =S12+V12+X12 -> 9262886 | AC12: =Z12-AA12 -> 9262886 | AD12: =AE12/M12 -> 300 | AE12: 86544 | AF12: 15578 | AG12: =(AD12*O12) -> 9156 | AH12: =AG12*18% -> 1648.08 | AI12: =AD12*N12 -> 95700 | AJ12: =ROUNDUP(AI12*18%,0) -> 17226 | AK12: 86544 | AL12: =N12*300 -> 95700 | AM12: =ROUND(AI12+AC12,0) -> 9358586 | AN12: =ROUNDUP(AJ12+W12+T12+Y12-AB12,0) -> 480373 | AO12: =AN12+AL12+AR12 -> 576444.86 | AP12: =AM12+AO12 -> 9935030.9 | AQ12: 7909741 | AR12: 371.86 | AS12: =ROUND(AP12-AQ12,0) -> 2025290 | AT12: 9584260 | AU12: 8800 | AV12: =AU12*N12 -> 2807200 | AW12: =MAX(AM12,AT12,AV12) -> 9584260 | AX12: =CEILING((AW12),1000) -> 9585000 | AY12: 0.05 | AZ12: =AY12*AX12 -> 479250 | BA12: =CEILING(AZ12,100) -> 479300 | BB12: =BA12+AS12 -> 2504590 | BC12: =L12/J12% -> 5.9028031 | BD12: =O12/M12% -> 10.57959 | BE12: 67.35 | BF12: 29.64 | BG12: 46176 | BH12: =BG12+30 -> 46206 | BI12: 5 | BM12: UBPL M3M CAPITAL MASTER ACCOUNT | BN12: 777705001441 | BO12: ICIC0000399 | BP12: ICICI Bank | BQ12: Shop No - 19, 20, 21, Vipul Orchid Plaza, Suncity, Sector 54, Gurgaon, Haryana -122002 | BR12: Union Buildmart Private Limited | BS12: AABCU4843M | BT12: 41st Floor, Tower-1, M3M International Financial center, sector- 66,Gurugram, Haryana, India 122101 | BU12: (……………..)Village Chauma, Sector – 113, Gurugram, Manesar Urban Complex, GURGAON, HARYANA, INDIA PIN Code: 122017 | BV12: Feedback@m3mindia.com | BW12: 8068970077 | BX12: 0 | BY12: Manish Kumar | BZ12: Shubra
A13: R2 UG 19 | B13: M3M Capital Walk in M3M Capital Phase-1 | C13: WPBOOKING/00004/23-24 | D13: WPFLAP/00003/23-24 | E13: Ms. KAVYA RAI | F13: 45055 | G13: BLOCK-02 | H13: BASEMENT 1 | I13: Retail | J13: 1204.49 | K13: 1204.49 | L13: =K13-J13 -> 0 | M13: 537.55 | N13: 552 | O13: =N13-M13 -> 14.45 | P13: 9000 | Q13: 20166.329 | R13: 28000 | S13: 10840410 | T13: 542022 | U13: =T13/S13 -> 0.050000138 | V13: =L13*P13 -> 0 | W13: =V13*U13 -> 0 | Z13: =S13+V13+X13 -> 10840410 | AA13: 96841 | AB13: 4842 | AC13: =Z13-AA13 -> 10743569 | AD13: =AE13/M13 -> 300 | AE13: 161265 | AF13: 29028 | AG13: =(AD13*O13) -> 4335 | AH13: =AG13*18% -> 780.3 | AI13: =AD13*N13 -> 165600 | AJ13: =ROUNDUP(AI13*18%,0) -> 29808 | AK13: 161265 | AL13: =N13*300 -> 165600 | AM13: =ROUND(AI13+AC13,0) -> 10909169 | AN13: =ROUNDUP(AJ13+W13+T13+Y13-AB13,0) -> 566988 | AO13: =AN13+AL13+AR13 -> 733043 | AP13: =AM13+AO13 -> 11642212 | AQ13: 10044942 | AR13: 455 | AS13: =ROUND(AP13-AQ13,0) -> 1597270 | AT13: 0 | AU13: 8800 | AV13: =AU13*N13 -> 4857600 | AW13: =MAX(AM13,AT13,AV13) -> 10909169 | AX13: =CEILING((AW13),1000) -> 10910000 | AY13: 0.05 | AZ13: =AY13*AX13 -> 545500 | BA13: =CEILING(AZ13,100) -> 545500 | BB13: =BA13+AS13 -> 2142770 | BC13: =L13/J13% -> 0 | BD13: =O13/M13% -> 2.688122 | BE13: 111.9 | BF13: 51.28 | BG13: 46176 | BH13: =BG13+30 -> 46206 | BI13: 5 | BM13: UBPL M3M CAPITAL MASTER ACCOUNT | BN13: 777705001441 | BO13: ICIC0000399 | BP13: ICICI Bank | BQ13: Shop No - 19, 20, 21, Vipul Orchid Plaza, Suncity, Sector 54, Gurgaon, Haryana -122002 | BR13: Union Buildmart Private Limited | BS13: AABCU4843M | BT13: 41st Floor, Tower-1, M3M International Financial center, sector- 66,Gurugram, Haryana, India 122101 | BU13: (……………..)Village Chauma, Sector – 113, Gurugram, Manesar Urban Complex, GURGAON, HARYANA, INDIA PIN Code: 122017 | BV13: Feedback@m3mindia.com | BW13: 8068970077 | BX13: 0 | BY13: Manish Kumar | BZ13: Shubra
A14: R2 217 | B14: M3M Capital Walk in M3M Capital Phase-1 | C14: WPBOOKING/00019/22-23 | D14: WPFLAP/00014/22-23 | E14: Mr. MANMEET VINOD SEHGAL | F14: 45008 | G14: BLOCK-02 | H14: FLOOR 2 | I14: Retail | J14: 1194.8 | K14: 1194.8 | L14: =K14-J14 -> 0 | M14: 529.59 | N14: 529.59 | O14: =N14-M14 -> 0 | P14: 10063 | Q14: 22702.982 | R14: 20000 | S14: 12023272 | T14: 601164 | U14: =T14/S14 -> 0.050000033 | V14: =L14*P14 -> 0 | W14: =V14*U14 -> 0 | Z14: =S14+V14+X14 -> 12023272 | AC14: =Z14-AA14 -> 12023272 | AD14: =AE14/M14 -> 300 | AE14: 158877 | AF14: 28598 | AG14: =(AD14*O14) -> 0 | AH14: =AG14*18% -> 0 | AI14: =AD14*N14 -> 158877 | AJ14: =ROUNDUP(AI14*18%,0) -> 28598 | AK14: 158877 | AL14: =N14*300 -> 158877 | AM14: =ROUND(AI14+AC14,0) -> 12182149 | AN14: =ROUNDUP(AJ14+W14+T14+Y14-AB14,0) -> 629762 | AO14: =AN14+AL14+AR14 -> 789148.16 | AP14: =AM14+AO14 -> 12971297 | AQ14: 11285496 | AR14: 509.16 | AS14: =ROUND(AP14-AQ14,0) -> 1685801 | AT14: 0 | AU14: 8800 | AV14: =AU14*N14 -> 4660392 | AW14: =MAX(AM14,AT14,AV14) -> 12182149 | AX14: =CEILING((AW14),1000) -> 12183000 | AY14: 0.06 | AZ14: =AY14*AX14 -> 730980 | BA14: =CEILING(AZ14,100) -> 731000 | BB14: =BA14+AS14 -> 2416801 | BC14: =L14/J14% -> 0 | BD14: =O14/M14% -> 0 | BE14: 111 | BF14: 49.2 | BG14: 46176 | BH14: =BG14+30 -> 46206 | BI14: 6 | BM14: UBPL M3M CAPITAL MASTER ACCOUNT | BN14: 777705001441 | BO14: ICIC0000399 | BP14: ICICI Bank | BQ14: Shop No - 19, 20, 21, Vipul Orchid Plaza, Suncity, Sector 54, Gurgaon, Haryana -122002 | BR14: Union Buildmart Private Limited | BS14: AABCU4843M | BT14: 41st Floor, Tower-1, M3M International Financial center, sector- 66,Gurugram, Haryana, India 122101 | BU14: (……………..)Village Chauma, Sector – 113, Gurugram, Manesar Urban Complex, GURGAON, HARYANA, INDIA PIN Code: 122017 | BV14: Feedback@m3mindia.com | BW14: 8068970077 | BX14: 0 | BY14: Darshan Lal | BZ14: Shubra
A15: R2 LG 23 | B15: M3M Capital Walk in M3M Capital Phase-1 | C15: WPBOOKING/00014/23-24 | D15: WPFLAP/00020/23-24 | E15: Mr. Balraj Singh | F15: 45239 | G15: BLOCK-02 | H15: BASEMENT 2 | I15: Retail | J15: 618.93 | K15: 618.93 | L15: =K15-J15 -> 0 | M15: 273.94 | N15: 273.94 | O15: =N15-M15 -> 0 | P15: 31676.999 | Q15: 71569.851 | R15: 40000 | S15: 19605845 | T15: 980292 | U15: =T15/S15 -> 0.049999987 | V15: =L15*P15 -> 0 | W15: =V15*U15 -> 0 | Z15: =S15+V15+X15 -> 19605845 | AC15: =Z15-AA15 -> 19605845 | AD15: =AE15/M15 -> 300 | AE15: 82182 | AF15: 14792 | AG15: =(AD15*O15) -> 0 | AH15: =AG15*18% -> 0 | AI15: =AD15*N15 -> 82182 | AJ15: =ROUNDUP(AI15*18%,0) -> 14793 | AK15: 82182 | AL15: =N15*300 -> 82182 | AM15: =ROUND(AI15+AC15,0) -> 19688027 | AN15: =ROUNDUP(AJ15+W15+T15+Y15-AB15,0) -> 995085 | AO15: =AN15+AL15+AR15 -> 1077887 | AP15: =AM15+AO15 -> 20765914 | AQ15: 20452956 | AR15: 620 | AS15: =ROUND(AP15-AQ15,0) -> 312958 | AT15: 0 | AU15: 8800 | AV15: =AU15*N15 -> 2410672 | AW15: =MAX(AM15,AT15,AV15) -> 19688027 | AX15: =CEILING((AW15),1000) -> 19689000 | AY15: 0.07 | AZ15: =AY15*AX15 -> 1378230 | BA15: =CEILING(AZ15,100) -> 1378300 | BB15: =BA15+AS15 -> 1691258 | BC15: =L15/J15% -> 0 | BD15: =O15/M15% -> 0 | BE15: 57.5 | BF15: 25.45 | BG15: 46176 | BH15: =BG15+30 -> 46206 | BI15: 7 | BM15: UBPL M3M CAPITAL MASTER ACCOUNT | BN15: 777705001441 | BO15: ICIC0000399 | BP15: ICICI Bank | BQ15: Shop No - 19, 20, 21, Vipul Orchid Plaza, Suncity, Sector 54, Gurgaon, Haryana -122002 | BR15: Union Buildmart Private Limited | BS15: AABCU4843M | BT15: 41st Floor, Tower-1, M3M International Financial center, sector- 66,Gurugram, Haryana, India 122101 | BU15: (……………..)Village Chauma, Sector – 113, Gurugram, Manesar Urban Complex, GURGAON, HARYANA, INDIA PIN Code: 122017 | BV15: Feedback@m3mindia.com | BW15: 8068970077 | BX15: 0 | BY15: Chandrima | BZ15: Shubra
A16: R1 260 | B16: M3M Capital Walk in M3M Capital Phase-1 | C16: WPBOOKING/00006/23-24 | D16: WPFLAP/00017/22-23 | E16: Ms. SHIKHA WARIKOO | F16: 45089 | G16: BLOCK-01 | H16: FLOOR 2 | I16: Anchor Units | J16: 662.58 | K16: 662.58 | L16: =K16-J16 -> 0 | M16: 270.18 | N16: 270.18 | O16: =N16-M16 -> 0 | P16: 6925.7282 | Q16: 16984.414 | R16: 20000 | S16: 4588849 | T16: 229444 | U16: =T16/S16 -> 0.050000338 | V16: =L16*P16 -> 0 | W16: =V16*U16 -> 0 | Z16: =S16+V16+X16 -> 4588849 | AC16: =Z16-AA16 -> 4588849 | AD16: =AE16/M16 -> 300 | AE16: 81054 | AF16: 14590 | AG16: =(AD16*O16) -> 0 | AH16: =AG16*18% -> 0 | AI16: =AD16*N16 -> 81054 | AJ16: =ROUNDUP(AI16*18%,0) -> 14590 | AK16: 81054 | AL16: =N16*300 -> 81054 | AM16: =ROUND(AI16+AC16,0) -> 4669903 | AN16: =ROUNDUP(AJ16+W16+T16+Y16-AB16,0) -> 244034 | AO16: =AN16+AL16+AR16 -> 325768 | AP16: =AM16+AO16 -> 4995671 | AQ16: 3819866 | AR16: 680 | AS16: =ROUND(AP16-AQ16,0) -> 1175805 | AT16: 0 | AU16: 8800 | AV16: =AU16*N16 -> 2377584 | AW16: =MAX(AM16,AT16,AV16) -> 4669903 | AX16: =CEILING((AW16),1000) -> 4670000 | AY16: 0.05 | AZ16: =AY16*AX16 -> 233500 | BA16: =CEILING(AZ16,100) -> 233500 | BB16: =BA16+AS16 -> 1409305 | BC16: =L16/J16% -> 0 | BD16: =O16/M16% -> 0 | BE16: 61.56 | BF16: 25.1 | BG16: 46176 | BH16: =BG16+30 -> 46206 | BI16: 5 | BM16: UBPL M3M CAPITAL MASTER ACCOUNT | BN16: 777705001441 | BO16: ICIC0000399 | BP16: ICICI Bank | BQ16: Shop No - 19, 20, 21, Vipul Orchid Plaza, Suncity, Sector 54, Gurgaon, Haryana -122002 | BR16: Union Buildmart Private Limited | BS16: AABCU4843M | BT16: 41st Floor, Tower-1, M3M International Financial center, sector- 66,Gurugram, Haryana, India 122101 | BU16: (……………..)Village Chauma, Sector – 113, Gurugram, Manesar Urban Complex, GURGAON, HARYANA, INDIA PIN Code: 122017 | BV16: Feedback@m3mindia.com | BW16: 8068970077 | BX16: 0 | BY16: Ritika Singh | BZ16: Sabhyata Kapoor
A17: R2 212a | B17: M3M Capital Walk in M3M Capital Phase-1 | C17: WPBOOKING/00012/22-23 | D17: WPFLAP/00008/22-23 | E17: Mr. RAVI MADAAN | F17: 44967 | G17: BLOCK-02 | H17: FLOOR 2 | I17: Retail | J17: 761.88 | K17: 780 | L17: =K17-J17 -> 18.12 | M17: 330.45 | N17: 348 | O17: =N17-M17 -> 17.55 | P17: 10600 | Q17: 24439.183 | R17: 20000 | S17: 8075928 | T17: 403798 | U17: =T17/S17 -> 0.050000198 | V17: =L17*R17 -> 362400 | W17: =V17*U17 -> 18120.072 | Z17: =S17+V17+X17 -> 8438328 | AC17: =Z17-AA17 -> 8438328 | AD17: =AE17/M17 -> 300 | AE17: 99135 | AF17: 17844 | AG17: =(AD17*O17) -> 5265 | AH17: =AG17*18% -> 947.7 | AI17: =AD17*N17 -> 104400 | AJ17: =ROUNDUP(AI17*18%,0) -> 18792 | AK17: 99135 | AL17: =N17*300 -> 104400 | AM17: =ROUND(AI17+AC17,0) -> 8542728 | AN17: =ROUNDUP(AJ17+W17+T17+Y17-AB17,0) -> 440711 | AO17: =AN17+AL17+AR17 -> 548282.26 | AP17: =AM17+AO17 -> 9091010.3 | AQ17: 7591331.7 | AR17: 3171.26 | AS17: =ROUND(AP17-AQ17,0) -> 1499679 | AT17: 0 | AU17: 8800 | AV17: =AU17*N17 -> 3062400 | AW17: =MAX(AM17,AT17,AV17) -> 8542728 | AX17: =CEILING((AW17),1000) -> 8543000 | AY17: 0.07 | AZ17: =AY17*AX17 -> 598010 | BA17: =CEILING(AZ17,100) -> 598100 | BB17: =BA17+AS17 -> 2097779 | BC17: =L17/J17% -> 2.3783273 | BD17: =O17/M17% -> 5.3109396 | BE17: 72.46 | BF17: 32.33 | BG17: 46176 | BH17: =BG17+30 -> 46206 | BI17: 7 | BM17: UBPL M3M CAPITAL MASTER ACCOUNT | BN17: 777705001441 | BO17: ICIC0000399 | BP17: ICICI Bank | BQ17: Shop No - 19, 20, 21, Vipul Orchid Plaza, Suncity, Sector 54, Gurgaon, Haryana -122002 | BR17: Union Buildmart Private Limited | BS17: AABCU4843M | BT17: 41st Floor, Tower-1, M3M International Financial center, sector- 66,Gurugram, Haryana, India 122101 | BU17: (……………..)Village Chauma, Sector – 113, Gurugram, Manesar Urban Complex, GURGAON, HARYANA, INDIA PIN Code: 122017 | BV17: Feedback@m3mindia.com | BW17: 8068970077 | BX17: 0 | BY17: Manish Kumar | BZ17: Shubra
A18: R2 116 | B18: M3M Capital Walk in M3M Capital Phase-1 | C18: WPBOOKING/00018/22-23 | D18: WPFLAP/00013/22-23 | E18: Mr. HEMANT AGGARWAL | F18: 45005 | G18: BLOCK-02 | H18: FLOOR 1 | I18: Retail | J18: 684.59 | K18: 725 | L18: =K18-J18 -> 40.41 | M18: 288.48 | N18: 319 | O18: =N18-M18 -> 30.52 | P18: 12598.91 | Q18: 29898.392 | R18: 22000 | S18: 8625088 | T18: 431256 | U18: =T18/S18 -> 0.050000186 | V18: =L18*R18 -> 889020 | W18: =V18*U18 -> 44451.165 | Z18: =S18+V18+X18 -> 9514108 | AC18: =Z18-AA18 -> 9514108 | AD18: =AE18/M18 -> 300 | AE18: 86544 | AF18: 15578 | AG18: =(AD18*O18) -> 9156 | AH18: =AG18*18% -> 1648.08 | AI18: =AD18*N18 -> 95700 | AJ18: =ROUNDUP(AI18*18%,0) -> 17226 | AK18: 86544 | AL18: =N18*300 -> 95700 | AM18: =ROUND(AI18+AC18,0) -> 9609808 | AN18: =ROUNDUP(AJ18+W18+T18+Y18-AB18,0) -> 492934 | AO18: =AN18+AL18+AR18 -> 593917 | AP18: =AM18+AO18 -> 10203725 | AQ18: 8150709.8 | AR18: 5283 | AS18: =ROUND(AP18-AQ18,0) -> 2053015 | AT18: 0 | AU18: 8800 | AV18: =AU18*N18 -> 2807200 | AW18: =MAX(AM18,AT18,AV18) -> 9609808 | AX18: =CEILING((AW18),1000) -> 9610000 | AY18: 0.07 | AZ18: =AY18*AX18 -> 672700 | BA18: =CEILING(AZ18,100) -> 672700 | BB18: =BA18+AS18 -> 2725715 | BC18: =L18/J18% -> 5.9028031 | BD18: =O18/M18% -> 10.57959 | BE18: 67.35 | BF18: 29.64 | BG18: 46176 | BH18: =BG18+30 -> 46206 | BI18: 7 | BM18: UBPL M3M CAPITAL MASTER ACCOUNT | BN18: 777705001441 | BO18: ICIC0000399 | BP18: ICICI Bank | BQ18: Shop No - 19, 20, 21, Vipul Orchid Plaza, Suncity, Sector 54, Gurgaon, Haryana -122002 | BR18: Union Buildmart Private Limited | BS18: AABCU4843M | BT18: 41st Floor, Tower-1, M3M International Financial center, sector- 66,Gurugram, Haryana, India 122101 | BU18: (……………..)Village Chauma, Sector – 113, Gurugram, Manesar Urban Complex, GURGAON, HARYANA, INDIA PIN Code: 122017 | BV18: Feedback@m3mindia.com | BW18: 8068970077 | BX18: 0 | BY18: Ritika Singh | BZ18: Shubra
A19: R2 UG 22 | B19: M3M Capital Walk in M3M Capital Phase-1 | C19: WPBOOKING/00001/22-23 | D19: CW1FLAP/00001/22-23 | E19: Ms. SARLA ARYA | F19: 44861 | G19: BLOCK-02 | H19: BASEMENT 1 | I19: Retail | J19: 380.18 | K19: 380.18 | L19: =K19-J19 -> 0 | M19: 160.17 | N19: 160.17 | O19: =N19-M19 -> 0 | P19: 14550 | Q19: 34535.924 | R19: 28000 | S19: 5531619 | T19: 276580 | U19: =T19/S19 -> 0.049999828 | V19: =L19*P19 -> 0 | W19: =V19*U19 -> 0 | Z19: =S19+V19+X19 -> 5531619 | AA19: 1936066 | AB19: 96804 | AC19: =Z19-AA19 -> 3595553 | AD19: =AE19/M19 -> 300 | AE19: 48051 | AF19: 8650 | AG19: =(AD19*O19) -> 0 | AH19: =AG19*18% -> 0 | AI19: =AD19*N19 -> 48051 | AJ19: =ROUNDUP(AI19*18%,0) -> 8650 | AK19: 48051 | AL19: =N19*300 -> 48051 | AM19: =ROUND(AI19+AC19,0) -> 3643604 | AN19: =ROUNDUP(AJ19+W19+T19+Y19-AB19,0) -> 188426 | AO19: =AN19+AL19+AR19 -> 237124 | AP19: =AM19+AO19 -> 3880728 | AQ19: 3055784 | AR19: 647 | AS19: =ROUND(AP19-AQ19,0) -> 824944 | AT19: 0 | AU19: 8800 | AV19: =AU19*N19 -> 1409496 | AW19: =MAX(AM19,AT19,AV19) -> 3643604 | AX19: =CEILING((AW19),1000) -> 3644000 | AY19: 0.05 | AZ19: =AY19*AX19 -> 182200 | BA19: =CEILING(AZ19,100) -> 182200 | BB19: =BA19+AS19 -> 1007144 | BC19: =L19/J19% -> 0 | BD19: =O19/M19% -> 0 | BE19: 35.32 | BF19: 14.88 | BG19: 46176 | BH19: =BG19+30 -> 46206 | BI19: 5 | BM19: UBPL M3M CAPITAL MASTER ACCOUNT | BN19: 777705001441 | BO19: ICIC0000399 | BP19: ICICI Bank | BQ19: Shop No - 19, 20, 21, Vipul Orchid Plaza, Suncity, Sector 54, Gurgaon, Haryana -122002 | BR19: Union Buildmart Private Limited | BS19: AABCU4843M | BT19: 41st Floor, Tower-1, M3M International Financial center, sector- 66,Gurugram, Haryana, India 122101 | BU19: (……………..)Village Chauma, Sector – 113, Gurugram, Manesar Urban Complex, GURGAON, HARYANA, INDIA PIN Code: 122017 | BV19: Feedback@m3mindia.com | BW19: 8068970077 | BX19: 0 | BY19: Preeti Chauhan | BZ19: Shubra
A20: R1 147 | B20: M3M Capital Walk in M3M Capital Phase-1 | C20: WPBOOKING/00002/23-24 | D20: WPFLAP/00018/22-23 | E20: Mr. VIKRAM RAJ JAISWAL | F20: 45040 | G20: BLOCK-01 | H20: FLOOR 1 | I20: Anchor Units | J20: 391.09 | K20: 391.09 | L20: =K20-J20 -> 0 | M20: 156.08 | N20: 156.08 | O20: =N20-M20 -> 0 | P20: 22000 | Q20: 55125.448 | R20: 22000 | S20: 8603980 | T20: 430200 | U20: =T20/S20 -> 0.050000116 | V20: =L20*P20 -> 0 | W20: =V20*U20 -> 0 | Z20: =S20+V20+X20 -> 8603980 | AC20: =Z20-AA20 -> 8603980 | AD20: =AE20/M20 -> 300 | AE20: 46824 | AF20: 8428 | AG20: =(AD20*O20) -> 0 | AH20: =AG20*18% -> 0 | AI20: =AD20*N20 -> 46824 | AJ20: =ROUNDUP(AI20*18%,0) -> 8429 | AK20: 46824 | AL20: =N20*300 -> 46824 | AM20: =ROUND(AI20+AC20,0) -> 8650804 | AN20: =ROUNDUP(AJ20+W20+T20+Y20-AB20,0) -> 438629 | AO20: =AN20+AL20+AR20 -> 505543 | AP20: =AM20+AO20 -> 9156347 | AQ20: 3820187 | AR20: 20090 | AS20: =ROUND(AP20-AQ20,0) -> 5336160 | AT20: 0 | AU20: 8800 | AV20: =AU20*N20 -> 1373504 | AW20: =MAX(AM20,AT20,AV20) -> 8650804 | AX20: =CEILING((AW20),1000) -> 8651000 | AY20: 0.07 | AZ20: =AY20*AX20 -> 605570 | BA20: =CEILING(AZ20,100) -> 605600 | BB20: =BA20+AS20 -> 5941760 | BC20: =L20/J20% -> 0 | BD20: =O20/M20% -> 0 | BE20: 36.33 | BF20: 14.5 | BG20: 46176 | BH20: =BG20+30 -> 46206 | BI20: 7 | BM20: UBPL M3M CAPITAL MASTER ACCOUNT | BN20: 777705001441 | BO20: ICIC0000399 | BP20: ICICI Bank | BQ20: Shop No - 19, 20, 21, Vipul Orchid Plaza, Suncity, Sector 54, Gurgaon, Haryana -122002 | BR20: Union Buildmart Private Limited | BS20: AABCU4843M | BT20: 41st Floor, Tower-1, M3M International Financial center, sector- 66,Gurugram, Haryana, India 122101 | BU20: (……………..)Village Chauma, Sector – 113, Gurugram, Manesar Urban Complex, GURGAON, HARYANA, INDIA PIN Code: 122017 | BV20: Feedback@m3mindia.com | BW20: 8068970077 | BX20: 0 | BY20: Ritika Singh | BZ20: Sabhyata Kapoor
A21: R1 UG 27 | B21: M3M Capital Walk in M3M Capital Phase-1 | C21: WPBOOKING/00012/23-24 | D21: WPFLAP/00018/23-24 | E21: Mr. Amar Chand Gupta | F21: 45183 | G21: BLOCK-01 | H21: BASEMENT 1 | I21: Anchor Units | J21: 391.09 | K21: 391.09 | L21: =K21-J21 -> 0 | M21: 156.08 | N21: 156.08 | O21: =N21-M21 -> 0 | P21: 22435 | Q21: 56215.428 | R21: 28000 | S21: 8774104 | T21: 438706 | U21: =T21/S21 -> 0.050000091 | V21: =L21*P21 -> 0 | W21: =V21*U21 -> 0 | Z21: =S21+V21+X21 -> 8774104 | AC21: =Z21-AA21 -> 8774104 | AD21: =AE21/M21 -> 300 | AE21: 46824 | AF21: 8428 | AG21: =(AD21*O21) -> 0 | AH21: =AG21*18% -> 0 | AI21: =AD21*N21 -> 46824 | AJ21: =ROUNDUP(AI21*18%,0) -> 8429 | AK21: 46824 | AL21: =N21*300 -> 46824 | AM21: =ROUND(AI21+AC21,0) -> 8820928 | AN21: =ROUNDUP(AJ21+W21+T21+Y21-AB21,0) -> 447135 | AO21: =AN21+AL21+AR21 -> 515242 | AP21: =AM21+AO21 -> 9336170 | AQ21: 3724724 | AR21: 21283 | AS21: =ROUND(AP21-AQ21,0) -> 5611446 | AT21: 0 | AU21: 8800 | AV21: =AU21*N21 -> 1373504 | AW21: =MAX(AM21,AT21,AV21) -> 8820928 | AX21: =CEILING((AW21),1000) -> 8821000 | AY21: 0.06 | AZ21: =AY21*AX21 -> 529260 | BA21: =CEILING(AZ21,100) -> 529300 | BB21: =BA21+AS21 -> 6140746 | BC21: =L21/J21% -> 0 | BD21: =O21/M21% -> 0 | BE21: 36.33 | BF21: 14.5 | BG21: 46176 | BH21: =BG21+30 -> 46206 | BI21: 6 | BM21: UBPL M3M CAPITAL MASTER ACCOUNT | BN21: 777705001441 | BO21: ICIC0000399 | BP21: ICICI Bank | BQ21: Shop No - 19, 20, 21, Vipul Orchid Plaza, Suncity, Sector 54, Gurgaon, Haryana -122002 | BR21: Union Buildmart Private Limited | BS21: AABCU4843M | BT21: 41st Floor, Tower-1, M3M International Financial center, sector- 66,Gurugram, Haryana, India 122101 | BU21: (……………..)Village Chauma, Sector – 113, Gurugram, Manesar Urban Complex, GURGAON, HARYANA, INDIA PIN Code: 122017 | BV21: Feedback@m3mindia.com | BW21: 8068970077 | BX21: 0 | BY21: Vidhi Singh | BZ21: Sabhyata Kapoor
A22: R1 248 | B22: M3M Capital Walk in M3M Capital Phase-1 | C22: WPBOOKING/00002/22-23 | D22: WPFLAP/00001/22-23 | E22: Mr. NARESH KUMAR | F22: 44868 | G22: BLOCK-01 | H22: FLOOR 2 | I22: Anchor Units | J22: 477.44 | K22: 477.44 | L22: =K22-J22 -> 0 | M22: 196.98 | N22: 196.98 | O22: =N22-M22 -> 0 | P22: 12962.95 | Q22: 31419.591 | R22: 20000 | S22: 6189031 | T22: 309454 | U22: =T22/S22 -> 0.050000396 | V22: =L22*P22 -> 0 | W22: =V22*U22 -> 0 | Z22: =S22+V22+X22 -> 6189031 | AC22: =Z22-AA22 -> 6189031 | AD22: =AE22/M22 -> 300 | AE22: 59094 | AF22: 10636 | AG22: =(AD22*O22) -> 0 | AH22: =AG22*18% -> 0 | AI22: =AD22*N22 -> 59094 | AJ22: =ROUNDUP(AI22*18%,0) -> 10637 | AK22: 59094 | AL22: =N22*300 -> 59094 | AM22: =ROUND(AI22+AC22,0) -> 6248125 | AN22: =ROUNDUP(AJ22+W22+T22+Y22-AB22,0) -> 320091 | AO22: =AN22+AL22+AR22 -> 398600 | AP22: =AM22+AO22 -> 6646725 | AQ22: 2927888 | AR22: 19415 | AS22: =ROUND(AP22-AQ22,0) -> 3718837 | AT22: 0 | AU22: 8800 | AV22: =AU22*N22 -> 1733424 | AW22: =MAX(AM22,AT22,AV22) -> 6248125 | AX22: =CEILING((AW22),1000) -> 6249000 | AY22: 0.07 | AZ22: =AY22*AX22 -> 437430 | BA22: =CEILING(AZ22,100) -> 437500 | BB22: =BA22+AS22 -> 4156337 | BC22: =L22/J22% -> 0 | BD22: =O22/M22% -> 0 | BE22: 44.36 | BF22: 18.3 | BG22: 46176 | BH22: =BG22+30 -> 46206 | BI22: 7 | BM22: UBPL M3M CAPITAL MASTER ACCOUNT | BN22: 777705001441 | BO22: ICIC0000399 | BP22: ICICI Bank | BQ22: Shop No - 19, 20, 21, Vipul Orchid Plaza, Suncity, Sector 54, Gurgaon, Haryana -122002 | BR22: Union Buildmart Private Limited | BS22: AABCU4843M | BT22: 41st Floor, Tower-1, M3M International Financial center, sector- 66,Gurugram, Haryana, India 122101 | BU22: (……………..)Village Chauma, Sector – 113, Gurugram, Manesar Urban Complex, GURGAON, HARYANA, INDIA PIN Code: 122017 | BV22: Feedback@m3mindia.com | BW22: 8068970077 | BX22: 0 | BY22: Vidhi Singh | BZ22: Sabhyata Kapoor
A23: R2 211 | B23: M3M Capital Walk in M3M Capital Phase-1 | C23: WPBOOKING/00005/23-24 | D23: WPFLAP/00004/23-24 | E23: Ms. RUCHI | F23: 45058 | G23: BLOCK-02 | H23: FLOOR 2 | I23: Retail | J23: 1173.28 | K23: 1190 | L23: =K23-J23 -> 16.72 | M23: 496.22 | N23: 538 | O23: =N23-M23 -> 41.78 | P23: 8972.2402 | Q23: 21214.28 | R23: 20000 | S23: 10526950 | T23: 526348 | U23: =T23/S23 -> 0.050000047 | V23: =L23*R23 -> 334400 | W23: =V23*U23 -> 16720.016 | Z23: =S23+V23+X23 -> 10861350 | AC23: =Z23-AA23 -> 10861350 | AD23: =AE23/M23 -> 300 | AE23: 148866 | AF23: 26796 | AG23: =(AD23*O23) -> 12534 | AH23: =AG23*18% -> 2256.12 | AI23: =AD23*N23 -> 161400 | AJ23: =ROUNDUP(AI23*18%,0) -> 29052 | AK23: 148866 | AL23: =N23*300 -> 161400 | AM23: =ROUND(AI23+AC23,0) -> 11022750 | AN23: =ROUNDUP(AJ23+W23+T23+Y23-AB23,0) -> 572121 | AO23: =AN23+AL23+AR23 -> 756437 | AP23: =AM23+AO23 -> 11779187 | AQ23: 4060786 | AR23: 22916 | AS23: =ROUND(AP23-AQ23,0) -> 7718401 | AT23: 0 | AU23: 8800 | AV23: =AU23*N23 -> 4734400 | AW23: =MAX(AM23,AT23,AV23) -> 11022750 | AX23: =CEILING((AW23),1000) -> 11023000 | AY23: 0.05 | AZ23: =AY23*AX23 -> 551150 | BA23: =CEILING(AZ23,100) -> 551200 | BB23: =BA23+AS23 -> 8269601 | BC23: =L23/J23% -> 1.4250648 | BD23: =O23/M23% -> 8.4196526 | BE23: 110.55 | BF23: 49.98 | BG23: 46176 | BH23: =BG23+30 -> 46206 | BI23: 5 | BM23: UBPL M3M CAPITAL MASTER ACCOUNT | BN23: 777705001441 | BO23: ICIC0000399 | BP23: ICICI Bank | BQ23: Shop No - 19, 20, 21, Vipul Orchid Plaza, Suncity, Sector 54, Gurgaon, Haryana -122002 | BR23: Union Buildmart Private Limited | BS23: AABCU4843M | BT23: 41st Floor, Tower-1, M3M International Financial center, sector- 66,Gurugram, Haryana, India 122101 | BU23: (……………..)Village Chauma, Sector – 113, Gurugram, Manesar Urban Complex, GURGAON, HARYANA, INDIA PIN Code: 122017 | BV23: Feedback@m3mindia.com | BW23: 8068970077 | BX23: 0 | BY23: Ritika Singh | BZ23: Shubra
A24: R2 114 | B24: M3M Capital Walk in M3M Capital Phase-1 | C24: WPBOOKING/00010/23-24 | D24: WPFLAP/00009/23-24 | E24: Mrs. SUKHWINDER DEVI | F24: 45128 | G24: BLOCK-02 | H24: FLOOR 1 | I24: Retail | J24: 847.77 | K24: 900 | L24: =K24-J24 -> 52.23 | M24: 349.83 | N24: 396 | O24: =N24-M24 -> 46.17 | P24: 11790.002 | Q24: 28571.621 | R24: 22000 | S24: 9995210 | T24: 499760 | U24: =T24/S24 -> 0.04999995 | V24: =L24*R24 -> 1149060 | W24: =V24*U24 -> 57452.943 | Z24: =S24+V24+X24 -> 11144270 | AC24: =Z24-AA24 -> 11144270 | AD24: =AE24/M24 -> 300 | AE24: 104949 | AF24: 18890 | AG24: =(AD24*O24) -> 13851 | AH24: =AG24*18% -> 2493.18 | AI24: =AD24*N24 -> 118800 | AJ24: =ROUNDUP(AI24*18%,0) -> 21384 | AK24: 104949 | AL24: =N24*300 -> 118800 | AM24: =ROUND(AI24+AC24,0) -> 11263070 | AN24: =ROUNDUP(AJ24+W24+T24+Y24-AB24,0) -> 578597 | AO24: =AN24+AL24+AR24 -> 728366 | AP24: =AM24+AO24 -> 11991436 | AQ24: 2800000 | AR24: 30969 | AS24: =ROUND(AP24-AQ24,0) -> 9191436 | AT24: 2475000 | AU24: 8800 | AV24: =AU24*N24 -> 3484800 | AW24: =MAX(AM24,AT24,AV24) -> 11263070 | AX24: =CEILING((AW24),1000) -> 11264000 | AY24: 0.05 | AZ24: =AY24*AX24 -> 563200 | BA24: =CEILING(AZ24,100) -> 563200 | BB24: =BA24+AS24 -> 9754636 | BC24: =L24/J24% -> 6.1608691 | BD24: =O24/M24% -> 13.197839 | BE24: 83.61 | BF24: 36.79 | BG24: 46176 | BH24: =BG24+30 -> 46206 | BI24: 5 | BM24: UBPL M3M CAPITAL MASTER ACCOUNT | BN24: 777705001441 | BO24: ICIC0000399 | BP24: ICICI Bank | BQ24: Shop No - 19, 20, 21, Vipul Orchid Plaza, Suncity, Sector 54, Gurgaon, Haryana -122002 | BR24: Union Buildmart Private Limited | BS24: AABCU4843M | BT24: 41st Floor, Tower-1, M3M International Financial center, sector- 66,Gurugram, Haryana, India 122101 | BU24: (……………..)Village Chauma, Sector – 113, Gurugram, Manesar Urban Complex, GURGAON, HARYANA, INDIA PIN Code: 122017 | BV24: Feedback@m3mindia.com | BW24: 8068970077 | BX24: 0 | BY24: Ritika Singh | BZ24: Shubra
A25: R2 UG 20 | B25: M3M Capital Walk in M3M Capital Phase-1 | C25: WPBOOKING/00007/22-23 | D25: WPFLAP/00005/22-23 | E25: Mr. GULAB CHAND CHAURASIA | F25: 44902 | G25: BLOCK-02 | H25: BASEMENT 1 | I25: Retail | J25: 764.24 | K25: 764.24 | L25: =K25-J25 -> 0 | M25: 333.68 | N25: 342 | O25: =N25-M25 -> 8.32 | P25: 17635.84 | Q25: 40392.034 | R25: 28000 | S25: 13478014 | T25: 673900 | U25: =T25/S25 -> 0.049999948 | V25: =L25*P25 -> 0 | W25: =V25*U25 -> 0 | Z25: =S25+V25+X25 -> 13478014 | AC25: =Z25-AA25 -> 13478014 | AD25: =AE25/M25 -> 300 | AE25: 100104 | AF25: 18018 | AG25: =(AD25*O25) -> 2496 | AH25: =AG25*18% -> 449.28 | AI25: =AD25*N25 -> 102600 | AJ25: =ROUNDUP(AI25*18%,0) -> 18468 | AK25: 100104 | AL25: =N25*300 -> 102600 | AM25: =ROUND(AI25+AC25,0) -> 13580614 | AN25: =ROUNDUP(AJ25+W25+T25+Y25-AB25,0) -> 692368 | AO25: =AN25+AL25+AR25 -> 836211.6 | AP25: =AM25+AO25 -> 14416826 | AQ25: 2824279.9 | AR25: 41243.6 | AS25: =ROUND(AP25-AQ25,0) -> 11592546 | AT25: 0 | AU25: 8800 | AV25: =AU25*N25 -> 3009600 | AW25: =MAX(AM25,AT25,AV25) -> 13580614 | AX25: =CEILING((AW25),1000) -> 13581000 | AY25: 0.07 | AZ25: =AY25*AX25 -> 950670 | BA25: =CEILING(AZ25,100) -> 950700 | BB25: =BA25+AS25 -> 12543246 | BC25: =L25/J25% -> 0 | BD25: =O25/M25% -> 2.4934069 | BE25: 71 | BF25: 31.77 | BG25: 46176 | BH25: =BG25+30 -> 46206 | BI25: 7 | BM25: UBPL M3M CAPITAL MASTER ACCOUNT | BN25: 777705001441 | BO25: ICIC0000399 | BP25: ICICI Bank | BQ25: Shop No - 19, 20, 21, Vipul Orchid Plaza, Suncity, Sector 54, Gurgaon, Haryana -122002 | BR25: Union Buildmart Private Limited | BS25: AABCU4843M | BT25: 41st Floor, Tower-1, M3M International Financial center, sector- 66,Gurugram, Haryana, India 122101 | BU25: (……………..)Village Chauma, Sector – 113, Gurugram, Manesar Urban Complex, GURGAON, HARYANA, INDIA PIN Code: 122017 | BV25: Feedback@m3mindia.com | BW25: 8068970077 | BX25: 0 | BY25: Manish Kumar | BZ25: Shubra
A26: R1 261 | B26: M3M Capital Walk in M3M Capital Phase-1 | C26: WPBOOKING/00013/23-24 | D26: WPFLAP/00019/23-24 | E26: Ms. Nirmala Prasad | F26: 45183 | G26: BLOCK-01 | H26: FLOOR 2 | I26: Anchor Units | J26: 2078.65 | K26: 2055 | L26: =K26-J26 -> -23.65 | M26: 785.77 | N26: 833 | O26: =N26-M26 -> 47.23 | P26: 8000.0014 | Q26: 21162.94 | R26: 20000 | S26: 16629203 | T26: 831460 | U26: =T26/S26 -> 0.049999991 | V26: =L26*P26 -> -189200.03 | W26: =V26*U26 -> -9460 | Z26: =S26+V26+X26 -> 16440003 | AC26: =Z26-AA26 -> 16440003 | AD26: =AE26/M26 -> 300 | AE26: 235731 | AF26: 42432 | AG26: =(AD26*O26) -> 14169 | AH26: =AG26*18% -> 2550.42 | AI26: =AD26*N26 -> 249900 | AJ26: =ROUNDUP(AI26*18%,0) -> 44982 | AK26: 235731 | AL26: =N26*300 -> 249900 | AM26: =ROUND(AI26+AC26,0) -> 16689903 | AN26: =ROUNDUP(AJ26+W26+T26+Y26-AB26,0) -> 866982 | AO26: =AN26+AL26+AR26 -> 1154917.3 | AP26: =AM26+AO26 -> 17844820 | AQ26: 9338022.5 | AR26: 38035.26 | AS26: =ROUND(AP26-AQ26,0) -> 8506798 | AT26: 0 | AU26: 8800 | AV26: =AU26*N26 -> 7330400 | AW26: =MAX(AM26,AT26,AV26) -> 16689903 | AX26: =CEILING((AW26),1000) -> 16690000 | AY26: 0.05 | AZ26: =AY26*AX26 -> 834500 | BA26: =CEILING(AZ26,100) -> 834500 | BB26: =BA26+AS26 -> 9341298 | BC26: =L26/J26% -> -1.1377577 | BD26: =O26/M26% -> 6.0106647 | BE26: 190.91 | BF26: 77.39 | BG26: 46176 | BH26: =BG26+30 -> 46206 | BI26: 5 | BM26: UBPL M3M CAPITAL MASTER ACCOUNT | BN26: 777705001441 | BO26: ICIC0000399 | BP26: ICICI Bank | BQ26: Shop No - 19, 20, 21, Vipul Orchid Plaza, Suncity, Sector 54, Gurgaon, Haryana -122002 | BR26: Union Buildmart Private Limited | BS26: AABCU4843M | BT26: 41st Floor, Tower-1, M3M International Financial center, sector- 66,Gurugram, Haryana, India 122101 | BU26: (……………..)Village Chauma, Sector – 113, Gurugram, Manesar Urban Complex, GURGAON, HARYANA, INDIA PIN Code: 122017 | BV26: Feedback@m3mindia.com | BW26: 8068970077 | BX26: 0 | BY26: Manish Kumar | BZ26: Sabhyata Kapoor
A27: R1 247 | B27: M3M Capital Walk in M3M Capital Phase-1 | C27: WPBOOKING/00005/22-23 | D27: WPFLAP/00004/22-23 | E27: Ms. SUMAN KUMARI | F27: 44874 | G27: BLOCK-01 | H27: FLOOR 2 | I27: Anchor Units | J27: 391.09 | K27: 391.09 | L27: =K27-J27 -> 0 | M27: 156.08 | N27: 156.08 | O27: =N27-M27 -> 0 | P27: 13369.999 | Q27: 33501.237 | R27: 20000 | S27: 5228873 | T27: 261444 | U27: =T27/S27 -> 0.050000067 | V27: =L27*P27 -> 0 | W27: =V27*U27 -> 0 | Z27: =S27+V27+X27 -> 5228873 | AC27: =Z27-AA27 -> 5228873 | AD27: =AE27/M27 -> 300 | AE27: 46824 | AF27: 8428 | AG27: =(AD27*O27) -> 0 | AH27: =AG27*18% -> 0 | AI27: =AD27*N27 -> 46824 | AJ27: =ROUNDUP(AI27*18%,0) -> 8429 | AK27: 46824 | AL27: =N27*300 -> 46824 | AM27: =ROUND(AI27+AC27,0) -> 5275697 | AN27: =ROUNDUP(AJ27+W27+T27+Y27-AB27,0) -> 269873 | AO27: =AN27+AL27+AR27 -> 348249 | AP27: =AM27+AO27 -> 5623946 | AQ27: 4941285 | AR27: 31552 | AS27: =ROUND(AP27-AQ27,0) -> 682661 | AT27: 0 | AU27: 8800 | AV27: =AU27*N27 -> 1373504 | AW27: =MAX(AM27,AT27,AV27) -> 5275697 | AX27: =CEILING((AW27),1000) -> 5276000 | AY27: 0.06 | AZ27: =AY27*AX27 -> 316560 | BA27: =CEILING(AZ27,100) -> 316600 | BB27: =BA27+AS27 -> 999261 | BC27: =L27/J27% -> 0 | BD27: =O27/M27% -> 0 | BE27: 36.33 | BF27: 14.5 | BG27: 46176 | BH27: =BG27+30 -> 46206 | BI27: 6 | BM27: UBPL M3M CAPITAL MASTER ACCOUNT | BN27: 777705001441 | BO27: ICIC0000399 | BP27: ICICI Bank | BQ27: Shop No - 19, 20, 21, Vipul Orchid Plaza, Suncity, Sector 54, Gurgaon, Haryana -122002 | BR27: Union Buildmart Private Limited | BS27: AABCU4843M | BT27: 41st Floor, Tower-1, M3M International Financial center, sector- 66,Gurugram, Haryana, India 122101 | BU27: (……………..)Village Chauma, Sector – 113, Gurugram, Manesar Urban Complex, GURGAON, HARYANA, INDIA PIN Code: 122017 | BV27: Feedback@m3mindia.com | BW27: 8068970077 | BX27: 0 | BY27: Priya Anand | BZ27: Sabhyata Kapoor
A28: R2 LG 20 | B28: M3M Capital Walk in M3M Capital Phase-1 | C28: WPBOOKING/00003/24-25 | D28: WPFLAP/00023/23-24 | E28: Mr. Santosh Kumar Aggarwal | F28: 45383 | G28: BLOCK-02 | H28: BASEMENT 2 | I28: Retail | J28: 861 | K28: 861 | L28: =K28-J28 -> 0 | M28: 381 | N28: 381 | O28: =N28-M28 -> 0 | P28: 14730 | Q28: 33287.48 | R28: 40000 | S28: 12682530 | T28: 634128 | U28: =T28/S28 -> 0.050000118 | V28: =L28*P28 -> 0 | W28: =V28*U28 -> 0 | Z28: =S28+V28+X28 -> 12682530 | AC28: =Z28-AA28 -> 12682530 | AD28: =AE28/M28 -> 300 | AE28: 114300 | AF28: 20574 | AG28: =(AD28*O28) -> 0 | AH28: =AG28*18% -> 0 | AI28: =AD28*N28 -> 114300 | AJ28: =ROUNDUP(AI28*18%,0) -> 20574 | AK28: 114300 | AL28: =N28*300 -> 114300 | AM28: =ROUND(AI28+AC28,0) -> 12796830 | AN28: =ROUNDUP(AJ28+W28+T28+Y28-AB28,0) -> 654702 | AO28: =AN28+AL28+AR28 -> 817928 | AP28: =AM28+AO28 -> 13614758 | AQ28: 1485787 | AR28: 48926 | AS28: =ROUND(AP28-AQ28,0) -> 12128971 | AT28: 0 | AU28: 8800 | AV28: =AU28*N28 -> 3352800 | AW28: =MAX(AM28,AT28,AV28) -> 12796830 | AX28: =CEILING((AW28),1000) -> 12797000 | AY28: 0.07 | AZ28: =AY28*AX28 -> 895790 | BA28: =CEILING(AZ28,100) -> 895800 | BB28: =BA28+AS28 -> 13024771 | BC28: =L28/J28% -> 0 | BD28: =O28/M28% -> 0 | BE28: 79.99 | BF28: 35.4 | BG28: 46176 | BH28: =BG28+30 -> 46206 | BI28: 7 | BM28: UBPL M3M CAPITAL MASTER ACCOUNT | BN28: 777705001441 | BO28: ICIC0000399 | BP28: ICICI Bank | BQ28: Shop No - 19, 20, 21, Vipul Orchid Plaza, Suncity, Sector 54, Gurgaon, Haryana -122002 | BR28: Union Buildmart Private Limited | BS28: AABCU4843M | BT28: 41st Floor, Tower-1, M3M International Financial center, sector- 66,Gurugram, Haryana, India 122101 | BU28: (……………..)Village Chauma, Sector – 113, Gurugram, Manesar Urban Complex, GURGAON, HARYANA, INDIA PIN Code: 122017 | BV28: Feedback@m3mindia.com | BW28: 8068970077 | BX28: 0 | BY28: Sudhanshu Gurjar | BZ28: Shubra
A29: R2 LG 18 | B29: M3M Capital Walk in M3M Capital Phase-1 | C29: WPBOOKING/00003/23-24 | D29: WPFLAP/00002/23-24 | E29: Ms. SAROJ BALA | F29: 45055 | G29: BLOCK-02 | H29: BASEMENT 2 | I29: Retail | J29: 955.84 | K29: 1184 | L29: =K29-J29 -> 228.16 | M29: 410.11 | N29: 521 | O29: =N29-M29 -> 110.89 | P29: 21042.566 | Q29: 49043.735 | R29: 40000 | S29: 20113326 | T29: 1005668 | U29: =T29/S29 -> 0.050000085 | V29: =L29*R29 -> 9126400 | W29: =V29*U29 -> 456320.77 | Z29: =S29+V29+X29 -> 29239726 | AC29: =Z29-AA29 -> 29239726 | AD29: =AE29/M29 -> 300 | AE29: 123033 | AF29: 22146 | AG29: =(AD29*O29) -> 33267 | AH29: =AG29*18% -> 5988.06 | AI29: =AD29*N29 -> 156300 | AJ29: =ROUNDUP(AI29*18%,0) -> 28134 | AK29: 123033 | AL29: =N29*300 -> 156300 | AM29: =ROUND(AI29+AC29,0) -> 29396026 | AN29: =ROUNDUP(AJ29+W29+T29+Y29-AB29,0) -> 1490123 | AO29: =AN29+AL29+AR29 -> 1823724.8 | AP29: =AM29+AO29 -> 31219751 | AQ29: 16740764 | AR29: 177301.76 | AS29: =ROUND(AP29-AQ29,0) -> 14478987 | AT29: 0 | AU29: 8800 | AV29: =AU29*N29 -> 4584800 | AW29: =MAX(AM29,AT29,AV29) -> 29396026 | AX29: =CEILING((AW29),1000) -> 29397000 | AY29: 0.05 | AZ29: =AY29*AX29 -> 1469850 | BA29: =CEILING(AZ29,100) -> 1469900 | BB29: =BA29+AS29 -> 15948887 | BC29: =L29/J29% -> 23.870104 | BD29: =O29/M29% -> 27.039087 | BE29: 110 | BF29: 48.4 | BG29: 46176 | BH29: =BG29+30 -> 46206 | BI29: 5 | BM29: UBPL M3M CAPITAL MASTER ACCOUNT | BN29: 777705001441 | BO29: ICIC0000399 | BP29: ICICI Bank | BQ29: Shop No - 19, 20, 21, Vipul Orchid Plaza, Suncity, Sector 54, Gurgaon, Haryana -122002 | BR29: Union Buildmart Private Limited | BS29: AABCU4843M | BT29: 41st Floor, Tower-1, M3M International Financial center, sector- 66,Gurugram, Haryana, India 122101 | BU29: (……………..)Village Chauma, Sector – 113, Gurugram, Manesar Urban Complex, GURGAON, HARYANA, INDIA PIN Code: 122017 | BV29: Feedback@m3mindia.com | BW29: 8068970077 | BX29: 0 | BY29: Manish Kumar | BZ29: Shubra
A30: R1 205 | B30: M3M Capital Walk in M3M Capital Phase-2 | C30: cwBOOKING/00135/22-23 | D30: cwFLAP/00069/22-23 | E30: Mr. KULDEEP KUMAR SHARMA | F30: 44880 | G30: BLOCK-01 | H30: FLOOR 2 | I30: Retail | J30: 369.21 | K30: 369.21 | L30: =K30-J30 -> 0 | M30: 160.38 | N30: 160.38 | O30: =N30-M30 -> 0 | P30: 9040.9604 | Q30: 20813.15 | R30: 20000 | S30: 3338013 | T30: 400562 | U30: =T30/S30 -> 0.12000013 | V30: =L30*P30 -> 0 | W30: =V30*U30 -> 0 | Z30: =S30+V30+X30 -> 3338013 | AA30: 156873 | AB30: 18824 | AC30: =Z30-AA30 -> 3181140 | AD30: =AE30/M30 -> 300 | AE30: 48114 | AF30: 8660 | AG30: =(AD30*O30) -> 0 | AH30: =AG30*18% -> 0 | AI30: =AD30*N30 -> 48114 | AJ30: =ROUNDUP(AI30*18%,0) -> 8661 | AK30: 48114 | AL30: =N30*300 -> 48114 | AM30: =ROUND(AI30+AC30,0) -> 3229254 | AN30: =ROUNDUP(AJ30+W30+T30+Y30-AB30,0) -> 390399 | AO30: =AN30+AL30+AR30 -> 438513 | AP30: =AM30+AO30 -> 3667767 | AQ30: 3188980 | AR30: 0 | AS30: =ROUND(AP30-AQ30,0) -> 478787 | AT30: 0 | AU30: 8800 | AV30: =AU30*N30 -> 1411344 | AW30: =MAX(AM30,AT30,AV30) -> 3229254 | AX30: =CEILING((AW30),1000) -> 3230000 | AY30: 0.07 | AZ30: =AY30*AX30 -> 226100 | BA30: =CEILING(AZ30,100) -> 226100 | BB30: =BA30+AS30 -> 704887 | BC30: =L30/J30% -> 0 | BD30: =O30/M30% -> 0 | BE30: 34.3 | BF30: 14.9 | BG30: 46176 | BH30: =BG30+30 -> 46206 | BI30: 7 | BL30: =VLOOKUP(A30,[2]Sheet1!$D$2:$H$933,5,0) -> 0 | BM30: UBPL M3M CAPITAL PHASE 2 MASTER ACCOUNT | BN30: 777705551661 | BO30: ICIC0000399 | BP30: ICICI Bank | BQ30: Shop No - 19, 20, Vipul Orchid Plaza, Suncity, Sector 54, Gurgaon, Haryana -122002 | BR30: Union Buildmart Private Limited | BS30: AABCU4843M | BT30: 41st Floor, Tower-1, M3M International Financial center, sector- 66,Gurugram, Haryana, India 122101 | BU30: (……………..)Village Chauma, Sector – 113, Gurugram, Manesar Urban Complex, GURGAON, HARYANA, INDIA PIN Code: 122017 | BV30: Feedback@m3mindia.com | BW30: 8068970077 | BX30: 0 | BY30: Sonia Gupta | BZ30: Sabhyata Kapoor
A31: R1 G 01 | B31: M3M Capital Walk in M3M Capital Phase-2 | C31: cwBOOKING/00177/23-24 | D31: cwFLAP/00147/22-23 | E31: M/S. INVESTOR HOME SOLUTIONS PVT. LTD. | F31: 45110 | G31: BLOCK-01 | H31: GROUND | I31: Retail | J31: 1763.14 | K31: 1763.14 | L31: =K31-J31 -> 0 | M31: 825.38 | N31: 825.38 | O31: =N31-M31 -> 0 | P31: 17473.049 | Q31: 37325.15 | R31: 60000 | S31: 30807432 | T31: 3696892 | U31: =T31/S31 -> 0.12000001 | V31: =L31*P31 -> 0 | W31: =V31*U31 -> 0 | Z31: =S31+V31+X31 -> 30807432 | AA31: 8810428 | AB31: 1057252 | AC31: =Z31-AA31 -> 21997004 | AD31: =AE31/M31 -> 300 | AE31: 247614 | AF31: 44570 | AG31: =(AD31*O31) -> 0 | AH31: =AG31*18% -> 0 | AI31: =AD31*N31 -> 247614 | AJ31: =ROUNDUP(AI31*18%,0) -> 44571 | AK31: 247614 | AL31: =N31*300 -> 247614 | AM31: =ROUND(AI31+AC31,0) -> 22244618 | AN31: =ROUNDUP(AJ31+W31+T31+Y31-AB31,0) -> 2684211 | AO31: =AN31+AL31+AR31 -> 2931825 | AP31: =AM31+AO31 -> 25176443 | AQ31: 2700000 | AR31: 0 | AS31: =ROUND(AP31-AQ31,0) -> 22476443 | AT31: 0 | AU31: 8800 | AV31: =AU31*N31 -> 7263344 | AW31: =MAX(AM31,AT31,AV31) -> 22244618 | AX31: =CEILING((AW31),1000) -> 22245000 | AY31: 0.07 | AZ31: =AY31*AX31 -> 1557150 | BA31: =CEILING(AZ31,100) -> 1557200 | BB31: =BA31+AS31 -> 24033643 | BC31: =L31/J31% -> 0 | BD31: =O31/M31% -> 0 | BE31: 163.8 | BF31: 76.68 | BG31: 46176 | BH31: =BG31+30 -> 46206 | BI31: 7 | BL31: =VLOOKUP(A31,[2]Sheet1!$D$2:$H$933,5,0) -> 0 | BM31: UBPL M3M CAPITAL PHASE 2 MASTER ACCOUNT | BN31: 777705551661 | BO31: ICIC0000399 | BP31: ICICI Bank | BQ31: Shop No - 19, 20, Vipul Orchid Plaza, Suncity, Sector 54, Gurgaon, Haryana -122002 | BR31: Union Buildmart Private Limited | BS31: AABCU4843M | BT31: 41st Floor, Tower-1, M3M International Financial center, sector- 66,Gurugram, Haryana, India 122101 | BU31: (……………..)Village Chauma, Sector – 113, Gurugram, Manesar Urban Complex, GURGAON, HARYANA, INDIA PIN Code: 122017 | BV31: Feedback@m3mindia.com | BW31: 8068970077 | BX31: 0 | BY31: Vidhi Singh | BZ31: Sabhyata Kapoor
A32: R1 G 02 | B32: M3M Capital Walk in M3M Capital Phase-2 | C32: cwBOOKING/00179/23-24 | D32: cwFLAP/00145/22-23 | E32: M/S. INVESTOR HOME SOLUTIONS PVT. LTD. | F32: 45110 | G32: BLOCK-01 | H32: GROUND | I32: Retail | J32: 1154.98 | K32: 1154.98 | L32: =K32-J32 -> 0 | M32: 538.42 | N32: 538.42 | O32: =N32-M32 -> 0 | P32: 17474.227 | Q32: 37484.46 | R32: 60000 | S32: 20182383 | T32: 2421888 | U32: =T32/S32 -> 0.1200001 | V32: =L32*P32 -> 0 | W32: =V32*U32 -> 0 | Z32: =S32+V32+X32 -> 20182383 | AA32: 5601347 | AB32: 672162 | AC32: =Z32-AA32 -> 14581036 | AD32: =AE32/M32 -> 300 | AE32: 161526 | AF32: 29074 | AG32: =(AD32*O32) -> 0 | AH32: =AG32*18% -> 0 | AI32: =AD32*N32 -> 161526 | AJ32: =ROUNDUP(AI32*18%,0) -> 29075 | AK32: 161526 | AL32: =N32*300 -> 161526 | AM32: =ROUND(AI32+AC32,0) -> 14742562 | AN32: =ROUNDUP(AJ32+W32+T32+Y32-AB32,0) -> 1778801 | AO32: =AN32+AL32+AR32 -> 1940327 | AP32: =AM32+AO32 -> 16682889 | AQ32: 2500000 | AR32: 0 | AS32: =ROUND(AP32-AQ32,0) -> 14182889 | AT32: 0 | AU32: 8800 | AV32: =AU32*N32 -> 4738096 | AW32: =MAX(AM32,AT32,AV32) -> 14742562 | AX32: =CEILING((AW32),1000) -> 14743000 | AY32: 0.07 | AZ32: =AY32*AX32 -> 1032010 | BA32: =CEILING(AZ32,100) -> 1032100 | BB32: =BA32+AS32 -> 15214989 | BC32: =L32/J32% -> 0 | BD32: =O32/M32% -> 0 | BE32: 107.3 | BF32: 50.02 | BG32: 46176 | BH32: =BG32+30 -> 46206 | BI32: 7 | BL32: =VLOOKUP(A32,[2]Sheet1!$D$2:$H$933,5,0) -> 0 | BM32: UBPL M3M CAPITAL PHASE 2 MASTER ACCOUNT | BN32: 777705551661 | BO32: ICIC0000399 | BP32: ICICI Bank | BQ32: Shop No - 19, 20, Vipul Orchid Plaza, Suncity, Sector 54, Gurgaon, Haryana -122002 | BR32: Union Buildmart Private Limited | BS32: AABCU4843M | BT32: 41st Floor, Tower-1, M3M International Financial center, sector- 66,Gurugram, Haryana, India 122101 | BU32: (……………..)Village Chauma, Sector – 113, Gurugram, Manesar Urban Complex, GURGAON, HARYANA, INDIA PIN Code: 122017 | BV32: Feedback@m3mindia.com | BW32: 8068970077 | BX32: 0 | BY32: Vidhi Singh | BZ32: Sabhyata Kapoor
A33: R1 G 03 | B33: M3M Capital Walk in M3M Capital Phase-2 | C33: cwBOOKING/00176/23-24 | D33: cwFLAP/00146/22-23 | E33: M/S. INVESTOR HOME SOLUTIONS PVT. LTD. | F33: 45110 | G33: BLOCK-01 | H33: GROUND | I33: Retail | J33: 1154.98 | K33: 1154.98 | L33: =K33-J33 -> 0 | M33: 538.42 | N33: 538.42 | O33: =N33-M33 -> 0 | P33: 18949.295 | Q33: 40648.67 | R33: 60000 | S33: 21886057 | T33: 2626326 | U33: =T33/S33 -> 0.11999996 | V33: =L33*P33 -> 0 | W33: =V33*U33 -> 0 | Z33: =S33+V33+X33 -> 21886057 | AA33: 4552740 | AB33: 546328 | AC33: =Z33-AA33 -> 17333317 | AD33: =AE33/M33 -> 300 | AE33: 161526 | AF33: 29074 | AG33: =(AD33*O33) -> 0 | AH33: =AG33*18% -> 0 | AI33: =AD33*N33 -> 161526 | AJ33: =ROUNDUP(AI33*18%,0) -> 29075 | AK33: 161526 | AL33: =N33*300 -> 161526 | AM33: =ROUND(AI33+AC33,0) -> 17494843 | AN33: =ROUNDUP(AJ33+W33+T33+Y33-AB33,0) -> 2109073 | AO33: =AN33+AL33+AR33 -> 2270599 | AP33: =AM33+AO33 -> 19765442 | AQ33: 1500000 | AR33: 0 | AS33: =ROUND(AP33-AQ33,0) -> 18265442 | AT33: 0 | AU33: 8800 | AV33: =AU33*N33 -> 4738096 | AW33: =MAX(AM33,AT33,AV33) -> 17494843 | AX33: =CEILING((AW33),1000) -> 17495000 | AY33: 0.07 | AZ33: =AY33*AX33 -> 1224650 | BA33: =CEILING(AZ33,100) -> 1224700 | BB33: =BA33+AS33 -> 19490142 | BC33: =L33/J33% -> 0 | BD33: =O33/M33% -> 0 | BE33: 107.3 | BF33: 50.02 | BG33: 46176 | BH33: =BG33+30 -> 46206 | BI33: 7 | BL33: =VLOOKUP(A33,[2]Sheet1!$D$2:$H$933,5,0) -> 0 | BM33: UBPL M3M CAPITAL PHASE 2 MASTER ACCOUNT | BN33: 777705551661 | BO33: ICIC0000399 | BP33: ICICI Bank | BQ33: Shop No - 19, 20, Vipul Orchid Plaza, Suncity, Sector 54, Gurgaon, Haryana -122002 | BR33: Union Buildmart Private Limited | BS33: AABCU4843M | BT33: 41st Floor, Tower-1, M3M International Financial center, sector- 66,Gurugram, Haryana, India 122101 | BU33: (……………..)Village Chauma, Sector – 113, Gurugram, Manesar Urban Complex, GURGAON, HARYANA, INDIA PIN Code: 122017 | BV33: Feedback@m3mindia.com | BW33: 8068970077 | BX33: 0 | BY33: Vidhi Singh | BZ33: Sabhyata Kapoor
A34: R1 G 04 | B34: M3M Capital Walk in M3M Capital Phase-2 | C34: cwBOOKING/00180/23-24 | D34: cwFLAP/00152/22-23 | E34: M/S. INVESTOR HOME SOLUTIONS PVT. LTD. | F34: 45110 | G34: BLOCK-01 | H34: GROUND | I34: Retail | J34: 1236.78 | K34: 1236.78 | L34: =K34-J34 -> 0 | M34: 532.82 | N34: 532.82 | O34: =N34-M34 -> 0 | P34: 18970.512 | Q34: 44034.289 | R34: 60000 | S34: 23462350 | T34: 2815482 | U34: =T34/S34 -> 0.12 | V34: =L34*P34 -> 0 | W34: =V34*U34 -> 0 | Z34: =S34+V34+X34 -> 23462350 | AA34: 5076621 | AB34: 609194 | AC34: =Z34-AA34 -> 18385729 | AD34: =AE34/M34 -> 300 | AE34: 159846 | AF34: 28772 | AG34: =(AD34*O34) -> 0 | AH34: =AG34*18% -> 0 | AI34: =AD34*N34 -> 159846 | AJ34: =ROUNDUP(AI34*18%,0) -> 28773 | AK34: 159846 | AL34: =N34*300 -> 159846 | AM34: =ROUND(AI34+AC34,0) -> 18545575 | AN34: =ROUNDUP(AJ34+W34+T34+Y34-AB34,0) -> 2235061 | AO34: =AN34+AL34+AR34 -> 2394907 | AP34: =AM34+AO34 -> 20940482 | AQ34: 2500000 | AR34: 0 | AS34: =ROUND(AP34-AQ34,0) -> 18440482 | AT34: 0 | AU34: 8800 | AV34: =AU34*N34 -> 4688816 | AW34: =MAX(AM34,AT34,AV34) -> 18545575 | AX34: =CEILING((AW34),1000) -> 18546000 | AY34: 0.07 | AZ34: =AY34*AX34 -> 1298220 | BA34: =CEILING(AZ34,100) -> 1298300 | BB34: =BA34+AS34 -> 19738782 | BC34: =L34/J34% -> 0 | BD34: =O34/M34% -> 0 | BE34: 114.9 | BF34: 49.5 | BG34: 46176 | BH34: =BG34+30 -> 46206 | BI34: 7 | BL34: =VLOOKUP(A34,[2]Sheet1!$D$2:$H$933,5,0) -> 0 | BM34: UBPL M3M CAPITAL PHASE 2 MASTER ACCOUNT | BN34: 777705551661 | BO34: ICIC0000399 | BP34: ICICI Bank | BQ34: Shop No - 19, 20, Vipul Orchid Plaza, Suncity, Sector 54, Gurgaon, Haryana -122002 | BR34: Union Buildmart Private Limited | BS34: AABCU4843M | BT34: 41st Floor, Tower-1, M3M International Financial center, sector- 66,Gurugram, Haryana, India 122101 | BU34: (……………..)Village Chauma, Sector – 113, Gurugram, Manesar Urban Complex, GURGAON, HARYANA, INDIA PIN Code: 122017 | BV34: Feedback@m3mindia.com | BW34: 8068970077 | BX34: 0 | BY34: Vidhi Singh | BZ34: Sabhyata Kapoor
A35: R1 104 | B35: M3M Capital Walk in M3M Capital Phase-2 | C35: cwBOOKING/00285/22-23 | D35: cwFLAP/00309/22-23 | E35: Mr. SHAILENDRA KUMAR PANDEY | F35: 44896 | G35: BLOCK-01 | H35: FLOOR 1 | I35: Retail | J35: 489.76 | K35: 489.76 | L35: =K35-J35 -> 0 | M35: 219.59 | N35: 219.59 | O35: =N35-M35 -> 0 | P35: 13180.983 | Q35: 29398.051 | R35: 22000 | S35: 6455518 | T35: 774662 | U35: =T35/S35 -> 0.11999998 | V35: =L35*P35 -> 0 | W35: =V35*U35 -> 0 | Z35: =S35+V35+X35 -> 6455518 | AC35: =Z35-AA35 -> 6455518 | AD35: =AE35/M35 -> 300 | AE35: 65877 | AF35: 11858 | AG35: =(AD35*O35) -> 0 | AH35: =AG35*18% -> 0 | AI35: =AD35*N35 -> 65877 | AJ35: =ROUNDUP(AI35*18%,0) -> 11858 | AK35: 65877 | AL35: =N35*300 -> 65877 | AM35: =ROUND(AI35+AC35,0) -> 6521395 | AN35: =ROUNDUP(AJ35+W35+T35+Y35-AB35,0) -> 786520 | AO35: =AN35+AL35+AR35 -> 852397 | AP35: =AM35+AO35 -> 7373792 | AQ35: 6491868 | AR35: 0 | AS35: =ROUND(AP35-AQ35,0) -> 881924 | AT35: 0 | AU35: 8800 | AV35: =AU35*N35 -> 1932392 | AW35: =MAX(AM35,AT35,AV35) -> 6521395 | AX35: =CEILING((AW35),1000) -> 6522000 | AY35: 0.06 | AZ35: =AY35*AX35 -> 391320 | BA35: =CEILING(AZ35,100) -> 391400 | BB35: =BA35+AS35 -> 1273324 | BC35: =L35/J35% -> 0 | BD35: =O35/M35% -> 0 | BE35: 45.5 | BF35: 20.4 | BG35: 46176 | BH35: =BG35+30 -> 46206 | BI35: 6 | BL35: =VLOOKUP(A35,[2]Sheet1!$D$2:$H$933,5,0) -> 0 | BM35: UBPL M3M CAPITAL PHASE 2 MASTER ACCOUNT | BN35: 777705551661 | BO35: ICIC0000399 | BP35: ICICI Bank | BQ35: Shop No - 19, 20, Vipul Orchid Plaza, Suncity, Sector 54, Gurgaon, Haryana -122002 | BR35: Union Buildmart Private Limited | BS35: AABCU4843M | BT35: 41st Floor, Tower-1, M3M International Financial center, sector- 66,Gurugram, Haryana, India 122101 | BU35: (……………..)Village Chauma, Sector – 113, Gurugram, Manesar Urban Complex, GURGAON, HARYANA, INDIA PIN Code: 122017 | BV35: Feedback@m3mindia.com | BW35: 8068970077 | BX35: 0 | BY35: Preeti Chauhan | BZ35: Sabhyata Kapoor
A36: R1 112A | B36: M3M Capital Walk in M3M Capital Phase-2 | C36: cwBOOKING/00507/22-23 | D36: cwFLAP/00583/22-23 | E36: Ms. RAJ BALA | F36: 44987 | G36: BLOCK-01 | H36: FLOOR 1 | I36: Retail | J36: 553.48 | K36: 553.48 | L36: =K36-J36 -> 0 | M36: 256.83 | N36: 256.83 | O36: =N36-M36 -> 0 | P36: 10227.999 | Q36: 22041.79 | R36: 22000 | S36: 5660993 | T36: 679320 | U36: =T36/S36 -> 0.12000015 | V36: =L36*P36 -> 0 | W36: =V36*U36 -> 0 | Z36: =S36+V36+X36 -> 5660993 | AA36: 107241 | AB36: 12869 | AC36: =Z36-AA36 -> 5553752 | AD36: =AE36/M36 -> 300 | AE36: 77049 | AF36: 13868 | AG36: =(AD36*O36) -> 0 | AH36: =AG36*18% -> 0 | AI36: =AD36*N36 -> 77049 | AJ36: =ROUNDUP(AI36*18%,0) -> 13869 | AK36: 77049 | AL36: =N36*300 -> 77049 | AM36: =ROUND(AI36+AC36,0) -> 5630801 | AN36: =ROUNDUP(AJ36+W36+T36+Y36-AB36,0) -> 680320 | AO36: =AN36+AL36+AR36 -> 757369 | AP36: =AM36+AO36 -> 6388170 | AQ36: 5915256 | AR36: 0 | AS36: =ROUND(AP36-AQ36,0) -> 472914 | AT36: 0 | AU36: 8800 | AV36: =AU36*N36 -> 2260104 | AW36: =MAX(AM36,AT36,AV36) -> 5630801 | AX36: =CEILING((AW36),1000) -> 5631000 | AY36: 0.05 | AZ36: =AY36*AX36 -> 281550 | BA36: =CEILING(AZ36,100) -> 281600 | BB36: =BA36+AS36 -> 754514 | BC36: =L36/J36% -> 0 | BD36: =O36/M36% -> 0 | BE36: 51.42 | BF36: 23.86 | BG36: 46176 | BH36: =BG36+30 -> 46206 | BI36: 5 | BJ36: Pre Payment | BL36: =VLOOKUP(A36,[2]Sheet1!$D$2:$H$933,5,0) -> 0 | BM36: UBPL M3M CAPITAL PHASE 2 MASTER ACCOUNT | BN36: 777705551661 | BO36: ICIC0000399 | BP36: ICICI Bank | BQ36: Shop No - 19, 20, Vipul Orchid Plaza, Suncity, Sector 54, Gurgaon, Haryana -122002 | BR36: Union Buildmart Private Limited | BS36: AABCU4843M | BT36: 41st Floor, Tower-1, M3M International Financial center, sector- 66,Gurugram, Haryana, India 122101 | BU36: (……………..)Village Chauma, Sector – 113, Gurugram, Manesar Urban Complex, GURGAON, HARYANA, INDIA PIN Code: 122017 | BV36: Feedback@m3mindia.com | BW36: 8068970077 | BY36: Preeti Chauhan | BZ36: Sabhyata Kapoor
A37: R1 125 | B37: M3M Capital Walk in M3M Capital Phase-2 | C37: cwBOOKING/00506/22-23 | D37: cwFLAP/00684/22-23 | E37: Ms. ELEAROSE FRANCO CHOUDHURY | F37: 44986 | G37: BLOCK-01 | H37: FLOOR 1 | I37: Retail | J37: 795.46 | K37: 795.46 | L37: =K37-J37 -> 0 | M37: 372.43 | N37: 372.43 | O37: =N37-M37 -> 0 | P37: 9449.995 | Q37: 20183.908 | R37: 22000 | S37: 7517093 | T37: 902052 | U37: =T37/S37 -> 0.12000011 | V37: =L37*P37 -> 0 | W37: =V37*U37 -> 0 | Z37: =S37+V37+X37 -> 7517093 | AC37: =Z37-AA37 -> 7517093 | AD37: =AE37/M37 -> 300 | AE37: 111729 | AF37: 20112 | AG37: =(AD37*O37) -> 0 | AH37: =AG37*18% -> 0 | AI37: =AD37*N37 -> 111729 | AJ37: =ROUNDUP(AI37*18%,0) -> 20112 | AK37: 111729 | AL37: =N37*300 -> 111729 | AM37: =ROUND(AI37+AC37,0) -> 7628822 | AN37: =ROUNDUP(AJ37+W37+T37+Y37-AB37,0) -> 922164 | AO37: =AN37+AL37+AR37 -> 1033893 | AP37: =AM37+AO37 -> 8662715 | AQ37: 7577234 | AR37: 0 | AS37: =ROUND(AP37-AQ37,0) -> 1085481 | AT37: 0 | AU37: 8800 | AV37: =AU37*N37 -> 3277384 | AW37: =MAX(AM37,AT37,AV37) -> 7628822 | AX37: =CEILING((AW37),1000) -> 7629000 | AY37: 0.06 | AZ37: =AY37*AX37 -> 457740 | BA37: =CEILING(AZ37,100) -> 457800 | BB37: =BA37+AS37 -> 1543281 | BC37: =L37/J37% -> 0 | BD37: =O37/M37% -> 0 | BE37: 73.9 | BF37: 34.6 | BG37: 46176 | BH37: =BG37+30 -> 46206 | BI37: 6 | BL37: =VLOOKUP(A37,[2]Sheet1!$D$2:$H$933,5,0) -> 0 | BM37: UBPL M3M CAPITAL PHASE 2 MASTER ACCOUNT | BN37: 777705551661 | BO37: ICIC0000399 | BP37: ICICI Bank | BQ37: Shop No - 19, 20, Vipul Orchid Plaza, Suncity, Sector 54, Gurgaon, Haryana -122002 | BR37: Union Buildmart Private Limited | BS37: AABCU4843M | BT37: 41st Floor, Tower-1, M3M International Financial center, sector- 66,Gurugram, Haryana, India 122101 | BU37: (……………..)Village Chauma, Sector – 113, Gurugram, Manesar Urban Complex, GURGAON, HARYANA, INDIA PIN Code: 122017 | BV37: Feedback@m3mindia.com | BW37: 8068970077 | BX37: 0 | BY37: Deepak chaubey | BZ37: Sabhyata Kapoor
A38: R1 136 | B38: M3M Capital Walk in M3M Capital Phase-2 | C38: cwBOOKING/00508/22-23 | D38: cwFLAP/00712/22-23 | E38: Ms. SUNITA DEVI | F38: 44987 | G38: BLOCK-01 | H38: FLOOR 1 | I38: Retail | J38: 669.52 | K38: 669.52 | L38: =K38-J38 -> 0 | M38: 312.16 | N38: 312.16 | O38: =N38-M38 -> 0 | P38: 10150 | Q38: 21769.695 | R38: 22000 | S38: 6795628 | T38: 815476 | U38: =T38/S38 -> 0.12000009 | V38: =L38*P38 -> 0 | W38: =V38*U38 -> 0 | Z38: =S38+V38+X38 -> 6795628 | AC38: =Z38-AA38 -> 6795628 | AD38: =AE38/M38 -> 300 | AE38: 93648 | AF38: 16856 | AG38: =(AD38*O38) -> 0 | AH38: =AG38*18% -> 0 | AI38: =AD38*N38 -> 93648 | AJ38: =ROUNDUP(AI38*18%,0) -> 16857 | AK38: 93648 | AL38: =N38*300 -> 93648 | AM38: =ROUND(AI38+AC38,0) -> 6889276 | AN38: =ROUNDUP(AJ38+W38+T38+Y38-AB38,0) -> 832333 | AO38: =AN38+AL38+AR38 -> 925981 | AP38: =AM38+AO38 -> 7815257 | AQ38: 6850004 | AR38: 0 | AS38: =ROUND(AP38-AQ38,0) -> 965253 | AT38: 0 | AU38: 8800 | AV38: =AU38*N38 -> 2747008 | AW38: =MAX(AM38,AT38,AV38) -> 6889276 | AX38: =CEILING((AW38),1000) -> 6890000 | AY38: 0.05 | AZ38: =AY38*AX38 -> 344500 | BA38: =CEILING(AZ38,100) -> 344500 | BB38: =BA38+AS38 -> 1309753 | BC38: =L38/J38% -> 0 | BD38: =O38/M38% -> 0 | BE38: 62.2 | BF38: 29 | BG38: 46176 | BH38: =BG38+30 -> 46206 | BI38: 5 | BL38: =VLOOKUP(A38,[2]Sheet1!$D$2:$H$933,5,0) -> 0 | BM38: UBPL M3M CAPITAL PHASE 2 MASTER ACCOUNT | BN38: 777705551661 | BO38: ICIC0000399 | BP38: ICICI Bank | BQ38: Shop No - 19, 20, Vipul Orchid Plaza, Suncity, Sector 54, Gurgaon, Haryana -122002 | BR38: Union Buildmart Private Limited | BS38: AABCU4843M | BT38: 41st Floor, Tower-1, M3M International Financial center, sector- 66,Gurugram, Haryana, India 122101 | BU38: (……………..)Village Chauma, Sector – 113, Gurugram, Manesar Urban Complex, GURGAON, HARYANA, INDIA PIN Code: 122017 | BV38: Feedback@m3mindia.com | BW38: 8068970077 | BX38: 0 | BY38: Preeti Chauhan | BZ38: Sabhyata Kapoor
A39: R1 138 | B39: M3M Capital Walk in M3M Capital Phase-2 | C39: cwBOOKING/00680/22-23 | D39: cwFLAP/00641/22-23 | E39: Mr. TEJ PAL | F39: 45000 | G39: BLOCK-01 | H39: FLOOR 1 | I39: Retail | J39: 1062.41 | K39: 1062.41 | L39: =K39-J39 -> 0 | M39: 489.76 | N39: 489.76 | O39: =N39-M39 -> 0 | P39: 15200 | Q39: 32972.542 | R39: 22000 | S39: 16148632 | T39: 1937836 | U39: =T39/S39 -> 0.12000001 | V39: =L39*P39 -> 0 | W39: =V39*U39 -> 0 | Z39: =S39+V39+X39 -> 16148632 | AC39: =Z39-AA39 -> 16148632 | AD39: =AE39/M39 -> 300 | AE39: 146928 | AF39: 26448 | AG39: =(AD39*O39) -> 0 | AH39: =AG39*18% -> 0 | AI39: =AD39*N39 -> 146928 | AJ39: =ROUNDUP(AI39*18%,0) -> 26448 | AK39: 146928 | AL39: =N39*300 -> 146928 | AM39: =ROUND(AI39+AC39,0) -> 16295560 | AN39: =ROUNDUP(AJ39+W39+T39+Y39-AB39,0) -> 1964284 | AO39: =AN39+AL39+AR39 -> 2111212 | AP39: =AM39+AO39 -> 18406772 | AQ39: 16277822 | AR39: 0 | AS39: =ROUND(AP39-AQ39,0) -> 2128950 | AT39: 0 | AU39: 8800 | AV39: =AU39*N39 -> 4309888 | AW39: =MAX(AM39,AT39,AV39) -> 16295560 | AX39: =CEILING((AW39),1000) -> 16296000 | AY39: 0.06 | AZ39: =AY39*AX39 -> 977760 | BA39: =CEILING(AZ39,100) -> 977800 | BB39: =BA39+AS39 -> 3106750 | BC39: =L39/J39% -> 0 | BD39: =O39/M39% -> 0 | BE39: 98.7 | BF39: 45.5 | BG39: 46176 | BH39: =BG39+30 -> 46206 | BI39: 6 | BL39: =VLOOKUP(A39,[2]Sheet1!$D$2:$H$933,5,0) -> 0 | BM39: UBPL M3M CAPITAL PHASE 2 MASTER ACCOUNT | BN39: 777705551661 | BO39: ICIC0000399 | BP39: ICICI Bank | BQ39: Shop No - 19, 20, Vipul Orchid Plaza, Suncity, Sector 54, Gurgaon, Haryana -122002 | BR39: Union Buildmart Private Limited | BS39: AABCU4843M | BT39: 41st Floor, Tower-1, M3M International Financial center, sector- 66,Gurugram, Haryana, India 122101 | BU39: (……………..)Village Chauma, Sector – 113, Gurugram, Manesar Urban Complex, GURGAON, HARYANA, INDIA PIN Code: 122017 | BV39: Feedback@m3mindia.com | BW39: 8068970077 | BX39: 0 | BY39: Deepak chaubey | BZ39: Sabhyata Kapoor
A40: R1 141 | B40: M3M Capital Walk in M3M Capital Phase-2 | C40: cwBOOKING/00612/22-23 | D40: cwFLAP/00514/22-23 | E40: Ms. ANITA RANA | F40: 44996 | G40: BLOCK-01 | H40: FLOOR 1 | I40: Retail | J40: 521.84 | K40: 521.84 | L40: =K40-J40 -> 0 | M40: 231.43 | N40: 231.43 | O40: =N40-M40 -> 0 | P40: 12000 | Q40: 27058.203 | R40: 22000 | S40: 6262080 | T40: 751450 | U40: =T40/S40 -> 0.12000006 | V40: =L40*P40 -> 0 | W40: =V40*U40 -> 0 | Z40: =S40+V40+X40 -> 6262080 | AC40: =Z40-AA40 -> 6262080 | AD40: =AE40/M40 -> 300 | AE40: 69429 | AF40: 12498 | AG40: =(AD40*O40) -> 0 | AH40: =AG40*18% -> 0 | AI40: =AD40*N40 -> 69429 | AJ40: =ROUNDUP(AI40*18%,0) -> 12498 | AK40: 69429 | AL40: =N40*300 -> 69429 | AM40: =ROUND(AI40+AC40,0) -> 6331509 | AN40: =ROUNDUP(AJ40+W40+T40+Y40-AB40,0) -> 763948 | AO40: =AN40+AL40+AR40 -> 833377 | AP40: =AM40+AO40 -> 7164886 | AQ40: 6312178 | AR40: 0 | AS40: =ROUND(AP40-AQ40,0) -> 852708 | AT40: 0 | AU40: 8800 | AV40: =AU40*N40 -> 2036584 | AW40: =MAX(AM40,AT40,AV40) -> 6331509 | AX40: =CEILING((AW40),1000) -> 6332000 | AY40: 0.05 | AZ40: =AY40*AX40 -> 316600 | BA40: =CEILING(AZ40,100) -> 316600 | BB40: =BA40+AS40 -> 1169308 | BC40: =L40/J40% -> 0 | BD40: =O40/M40% -> 0 | BE40: 48.48 | BF40: 21.5 | BG40: 46176 | BH40: =BG40+30 -> 46206 | BI40: 5 | BL40: =VLOOKUP(A40,[2]Sheet1!$D$2:$H$933,5,0) -> 0 | BM40: UBPL M3M CAPITAL PHASE 2 MASTER ACCOUNT | BN40: 777705551661 | BO40: ICIC0000399 | BP40: ICICI Bank | BQ40: Shop No - 19, 20, Vipul Orchid Plaza, Suncity, Sector 54, Gurgaon, Haryana -122002 | BR40: Union Buildmart Private Limited | BS40: AABCU4843M | BT40: 41st Floor, Tower-1, M3M International Financial center, sector- 66,Gurugram, Haryana, India 122101 | BU40: (……………..)Village Chauma, Sector – 113, Gurugram, Manesar Urban Complex, GURGAON, HARYANA, INDIA PIN Code: 122017 | BV40: Feedback@m3mindia.com | BW40: 8068970077 | BX40: 0 | BY40: Deepak chaubey | BZ40: Sabhyata Kapoor
A41: R1 142 | B41: M3M Capital Walk in M3M Capital Phase-2 | C41: cwBOOKING/00006/23-24 | D41: cwFLAP/01015/22-23 | E41: Ms. DISHA AGGARWAL | F41: 45019 | G41: BLOCK-01 | H41: FLOOR 1 | I41: Retail | J41: 1184.04 | K41: 1184.04 | L41: =K41-J41 -> 0 | M41: 548.96 | N41: 548.96 | O41: =N41-M41 -> 0 | P41: 7221.8202 | Q41: 15576.588 | R41: 22000 | S41: 8550924 | T41: 1026112 | U41: =T41/S41 -> 0.12000013 | V41: =L41*P41 -> 0 | W41: =V41*U41 -> 0 | Z41: =S41+V41+X41 -> 8550924 | AC41: =Z41-AA41 -> 8550924 | AD41: =AE41/M41 -> 300 | AE41: 164688 | AF41: 29644 | AG41: =(AD41*O41) -> 0 | AH41: =AG41*18% -> 0 | AI41: =AD41*N41 -> 164688 | AJ41: =ROUNDUP(AI41*18%,0) -> 29644 | AK41: 164688 | AL41: =N41*300 -> 164688 | AM41: =ROUND(AI41+AC41,0) -> 8715612 | AN41: =ROUNDUP(AJ41+W41+T41+Y41-AB41,0) -> 1055756 | AO41: =AN41+AL41+AR41 -> 1220444 | AP41: =AM41+AO41 -> 9936056 | AQ41: 1650000 | AR41: 0 | AS41: =ROUND(AP41-AQ41,0) -> 8286056 | AT41: 0 | AU41: 8800 | AV41: =AU41*N41 -> 4830848 | AW41: =MAX(AM41,AT41,AV41) -> 8715612 | AX41: =CEILING((AW41),1000) -> 8716000 | AY41: 0.05 | AZ41: =AY41*AX41 -> 435800 | BA41: =CEILING(AZ41,100) -> 435800 | BB41: =BA41+AS41 -> 8721856 | BC41: =L41/J41% -> 0 | BD41: =O41/M41% -> 0 | BE41: 110 | BF41: 51 | BG41: 46176 | BH41: =BG41+30 -> 46206 | BI41: 5 | BL41: =VLOOKUP(A41,[2]Sheet1!$D$2:$H$933,5,0) -> 0 | BM41: UBPL M3M CAPITAL PHASE 2 MASTER ACCOUNT | BN41: 777705551661 | BO41: ICIC0000399 | BP41: ICICI Bank | BQ41: Shop No - 19, 20, Vipul Orchid Plaza, Suncity, Sector 54, Gurgaon, Haryana -122002 | BR41: Union Buildmart Private Limited | BS41: AABCU4843M | BT41: 41st Floor, Tower-1, M3M International Financial center, sector- 66,Gurugram, Haryana, India 122101 | BU41: (……………..)Village Chauma, Sector – 113, Gurugram, Manesar Urban Complex, GURGAON, HARYANA, INDIA PIN Code: 122017 | BV41: Feedback@m3mindia.com | BW41: 8068970077 | BX41: 1126022 | BY41: Manish Kumar | BZ41: Sabhyata Kapoor
A42: R1 153 | B42: M3M Capital Walk in M3M Capital Phase-2 | C42: cwBOOKING/00302/23-24 | D42: cwFLAP/00188/23-24 | E42: Mr. Parveen Kumar | F42: 45266 | G42: BLOCK-01 | H42: FLOOR 1 | I42: Anchor Units | J42: 484.38 | K42: 484.38 | L42: =K42-J42 -> 0 | M42: 201.83 | N42: 201.83 | O42: =N42-M42 -> 0 | P42: 11519.999 | Q42: 27647.312 | R42: 22000 | S42: 5580057 | T42: 669606 | U42: =T42/S42 -> 0.11999985 | V42: =L42*P42 -> 0 | W42: =V42*U42 -> 0 | Z42: =S42+V42+X42 -> 5580057 | AC42: =Z42-AA42 -> 5580057 | AD42: =AE42/M42 -> 300 | AE42: 60549 | AF42: 10898 | AG42: =(AD42*O42) -> 0 | AH42: =AG42*18% -> 0 | AI42: =AD42*N42 -> 60549 | AJ42: =ROUNDUP(AI42*18%,0) -> 10899 | AK42: 60549 | AL42: =N42*300 -> 60549 | AM42: =ROUND(AI42+AC42,0) -> 5640606 | AN42: =ROUNDUP(AJ42+W42+T42+Y42-AB42,0) -> 680505 | AO42: =AN42+AL42+AR42 -> 741054 | AP42: =AM42+AO42 -> 6381660 | AQ42: 5624698 | AR42: 0 | AS42: =ROUND(AP42-AQ42,0) -> 756962 | AT42: 0 | AU42: 8800 | AV42: =AU42*N42 -> 1776104 | AW42: =MAX(AM42,AT42,AV42) -> 5640606 | AX42: =CEILING((AW42),1000) -> 5641000 | AY42: 0.07 | AZ42: =AY42*AX42 -> 394870 | BA42: =CEILING(AZ42,100) -> 394900 | BB42: =BA42+AS42 -> 1151862 | BC42: =L42/J42% -> 0 | BD42: =O42/M42% -> 0 | BE42: 45 | BF42: 18.75 | BG42: 46176 | BH42: =BG42+30 -> 46206 | BI42: 7 | BL42: =VLOOKUP(A42,[2]Sheet1!$D$2:$H$933,5,0) -> 0 | BM42: UBPL M3M CAPITAL PHASE 2 MASTER ACCOUNT | BN42: 777705551661 | BO42: ICIC0000399 | BP42: ICICI Bank | BQ42: Shop No - 19, 20, Vipul Orchid Plaza, Suncity, Sector 54, Gurgaon, Haryana -122002 | BR42: Union Buildmart Private Limited | BS42: AABCU4843M | BT42: 41st Floor, Tower-1, M3M International Financial center, sector- 66,Gurugram, Haryana, India 122101 | BU42: (……………..)Village Chauma, Sector – 113, Gurugram, Manesar Urban Complex, GURGAON, HARYANA, INDIA PIN Code: 122017 | BV42: Feedback@m3mindia.com | BW42: 8068970077 | BX42: 0 | BY42: Priya Anand | BZ42: Sabhyata Kapoor
A43: R1 158 | B43: M3M Capital Walk in M3M Capital Phase-2 | C43: cwBOOKING/00036/23-24 | D43: cwFLAP/01050/22-23 | E43: Ms. SUGANDHA AGGARWAL | F43: 45030 | G43: BLOCK-01 | H43: FLOOR 1 | I43: Anchor Units | J43: 571.69 | K43: 571.69 | L43: =K43-J43 -> 0 | M43: 234.66 | N43: 234.66 | O43: =N43-M43 -> 0 | P43: 12927.999 | Q43: 31495.815 | R43: 22000 | S43: 7390808 | T43: 886898 | U43: =T43/S43 -> 0.12000014 | V43: =L43*P43 -> 0 | W43: =V43*U43 -> 0 | Z43: =S43+V43+X43 -> 7390808 | AC43: =Z43-AA43 -> 7390808 | AD43: =AE43/M43 -> 300 | AE43: 70398 | AF43: 12672 | AG43: =(AD43*O43) -> 0 | AH43: =AG43*18% -> 0 | AI43: =AD43*N43 -> 70398 | AJ43: =ROUNDUP(AI43*18%,0) -> 12672 | AK43: 70398 | AL43: =N43*300 -> 70398 | AM43: =ROUND(AI43+AC43,0) -> 7461206 | AN43: =ROUNDUP(AJ43+W43+T43+Y43-AB43,0) -> 899570 | AO43: =AN43+AL43+AR43 -> 969968 | AP43: =AM43+AO43 -> 8431174 | AQ43: 7449985 | AR43: 0 | AS43: =ROUND(AP43-AQ43,0) -> 981189 | AT43: 0 | AU43: 8800 | AV43: =AU43*N43 -> 2065008 | AW43: =MAX(AM43,AT43,AV43) -> 7461206 | AX43: =CEILING((AW43),1000) -> 7462000 | AY43: 0.05 | AZ43: =AY43*AX43 -> 373100 | BA43: =CEILING(AZ43,100) -> 373100 | BB43: =BA43+AS43 -> 1354289 | BC43: =L43/J43% -> 0 | BD43: =O43/M43% -> 0 | BE43: 53.11 | BF43: 21.8 | BG43: 46176 | BH43: =BG43+30 -> 46206 | BI43: 5 | BL43: =VLOOKUP(A43,[2]Sheet1!$D$2:$H$933,5,0) -> 0 | BM43: UBPL M3M CAPITAL PHASE 2 MASTER ACCOUNT | BN43: 777705551661 | BO43: ICIC0000399 | BP43: ICICI Bank | BQ43: Shop No - 19, 20, Vipul Orchid Plaza, Suncity, Sector 54, Gurgaon, Haryana -122002 | BR43: Union Buildmart Private Limited | BS43: AABCU4843M | BT43: 41st Floor, Tower-1, M3M International Financial center, sector- 66,Gurugram, Haryana, India 122101 | BU43: (……………..)Village Chauma, Sector – 113, Gurugram, Manesar Urban Complex, GURGAON, HARYANA, INDIA PIN Code: 122017 | BV43: Feedback@m3mindia.com | BW43: 8068970077 | BX43: 0 | BY43: Preeti Chauhan | BZ43: Sabhyata Kapoor
A44: R1 206 | B44: M3M Capital Walk in M3M Capital Phase-2 | C44: cwBOOKING/00155/22-23 | D44: cwFLAP/00329/22-23 | E44: Mr. SURESH CHAND | F44: 44900 | G44: BLOCK-01 | H44: FLOOR 2 | I44: Retail | J44: 369.21 | K44: 369.21 | L44: =K44-J44 -> 0 | M44: 160.38 | N44: 160.38 | O44: =N44-M44 -> 0 | P44: 12900 | Q44: 29697.026 | R44: 20000 | S44: 4762809 | T44: 571538 | U44: =T44/S44 -> 0.12000019 | V44: =L44*P44 -> 0 | W44: =V44*U44 -> 0 | Z44: =S44+V44+X44 -> 4762809 | AA44: 408680 | AB44: 49042 | AC44: =Z44-AA44 -> 4354129 | AD44: =AE44/M44 -> 300 | AE44: 48114 | AF44: 8660 | AG44: =(AD44*O44) -> 0 | AH44: =AG44*18% -> 0 | AI44: =AD44*N44 -> 48114 | AJ44: =ROUNDUP(AI44*18%,0) -> 8661 | AK44: 48114 | AL44: =N44*300 -> 48114 | AM44: =ROUND(AI44+AC44,0) -> 4402243 | AN44: =ROUNDUP(AJ44+W44+T44+Y44-AB44,0) -> 531157 | AO44: =AN44+AL44+AR44 -> 579271 | AP44: =AM44+AO44 -> 4981514 | AQ44: 4343191 | AR44: 0 | AS44: =ROUND(AP44-AQ44,0) -> 638323 | AT44: 0 | AU44: 8800 | AV44: =AU44*N44 -> 1411344 | AW44: =MAX(AM44,AT44,AV44) -> 4402243 | AX44: =CEILING((AW44),1000) -> 4403000 | AY44: 0.07 | AZ44: =AY44*AX44 -> 308210 | BA44: =CEILING(AZ44,100) -> 308300 | BB44: =BA44+AS44 -> 946623 | BC44: =L44/J44% -> 0 | BD44: =O44/M44% -> 0 | BE44: 34.3 | BF44: 14.9 | BG44: 46176 | BH44: =BG44+30 -> 46206 | BI44: 7 | BL44: =VLOOKUP(A44,[2]Sheet1!$D$2:$H$933,5,0) -> 0 | BM44: UBPL M3M CAPITAL PHASE 2 MASTER ACCOUNT | BN44: 777705551661 | BO44: ICIC0000399 | BP44: ICICI Bank | BQ44: Shop No - 19, 20, Vipul Orchid Plaza, Suncity, Sector 54, Gurgaon, Haryana -122002 | BR44: Union Buildmart Private Limited | BS44: AABCU4843M | BT44: 41st Floor, Tower-1, M3M International Financial center, sector- 66,Gurugram, Haryana, India 122101 | BU44: (……………..)Village Chauma, Sector – 113, Gurugram, Manesar Urban Complex, GURGAON, HARYANA, INDIA PIN Code: 122017 | BV44: Feedback@m3mindia.com | BW44: 8068970077 | BX44: 0 | BY44: Priya Anand | BZ44: Sabhyata Kapoor
A45: R1 209 | B45: M3M Capital Walk in M3M Capital Phase-2 | C45: cwBOOKING/00287/23-24 | D45: cwFLAP/00181/23-24 | E45: Ms. Anjana Yadav | F45: 45222 | G45: BLOCK-01 | H45: FLOOR 2 | I45: Retail | J45: 369.21 | K45: 369.21 | L45: =K45-J45 -> 0 | M45: 160.38 | N45: 160.38 | O45: =N45-M45 -> 0 | P45: 10500 | Q45: 24171.998 | R45: 20000 | S45: 3876705 | T45: 465206 | U45: =T45/S45 -> 0.12000036 | V45: =L45*P45 -> 0 | W45: =V45*U45 -> 0 | Z45: =S45+V45+X45 -> 3876705 | AC45: =Z45-AA45 -> 3876705 | AD45: =AE45/M45 -> 300 | AE45: 48114 | AF45: 8660 | AG45: =(AD45*O45) -> 0 | AH45: =AG45*18% -> 0 | AI45: =AD45*N45 -> 48114 | AJ45: =ROUNDUP(AI45*18%,0) -> 8661 | AK45: 48114 | AL45: =N45*300 -> 48114 | AM45: =ROUND(AI45+AC45,0) -> 3924819 | AN45: =ROUNDUP(AJ45+W45+T45+Y45-AB45,0) -> 473867 | AO45: =AN45+AL45+AR45 -> 521981 | AP45: =AM45+AO45 -> 4446800 | AQ45: 3094348 | AR45: 0 | AS45: =ROUND(AP45-AQ45,0) -> 1352452 | AT45: 0 | AU45: 8800 | AV45: =AU45*N45 -> 1411344 | AW45: =MAX(AM45,AT45,AV45) -> 3924819 | AX45: =CEILING((AW45),1000) -> 3925000 | AY45: 0.06 | AZ45: =AY45*AX45 -> 235500 | BA45: =CEILING(AZ45,100) -> 235500 | BB45: =BA45+AS45 -> 1587952 | BC45: =L45/J45% -> 0 | BD45: =O45/M45% -> 0 | BE45: 34.3 | BF45: 14.9 | BG45: 46176 | BH45: =BG45+30 -> 46206 | BI45: 6 | BL45: =VLOOKUP(A45,[2]Sheet1!$D$2:$H$933,5,0) -> 0 | BM45: UBPL M3M CAPITAL PHASE 2 MASTER ACCOUNT | BN45: 777705551661 | BO45: ICIC0000399 | BP45: ICICI Bank | BQ45: Shop No - 19, 20, Vipul Orchid Plaza, Suncity, Sector 54, Gurgaon, Haryana -122002 | BR45: Union Buildmart Private Limited | BS45: AABCU4843M | BT45: 41st Floor, Tower-1, M3M International Financial center, sector- 66,Gurugram, Haryana, India 122101 | BU45: (……………..)Village Chauma, Sector – 113, Gurugram, Manesar Urban Complex, GURGAON, HARYANA, INDIA PIN Code: 122017 | BV45: Feedback@m3mindia.com | BW45: 8068970077 | BX45: 0 | BY45: Darshan Lal | BZ45: Sabhyata Kapoor
A46: R1 210 | B46: M3M Capital Walk in M3M Capital Phase-2 | C46: cwBOOKING/00614/22-23 | D46: cwFLAP/00526/22-23 | E46: Ms. MANJU SHARMA | F46: 44996 | G46: BLOCK-01 | H46: FLOOR 2 | I46: Retail | J46: 369.21 | K46: 369.21 | L46: =K46-J46 -> 0 | M46: 160.38 | N46: 160.38 | O46: =N46-M46 -> 0 | P46: 9415.3788 | Q46: 21675.097 | R46: 20000 | S46: 3476252 | T46: 417152 | U46: =T46/S46 -> 0.12000051 | V46: =L46*P46 -> 0 | W46: =V46*U46 -> 0 | Z46: =S46+V46+X46 -> 3476252 | AC46: =Z46-AA46 -> 3476252 | AD46: =AE46/M46 -> 300 | AE46: 48114 | AF46: 8660 | AG46: =(AD46*O46) -> 0 | AH46: =AG46*18% -> 0 | AI46: =AD46*N46 -> 48114 | AJ46: =ROUNDUP(AI46*18%,0) -> 8661 | AK46: 48114 | AL46: =N46*300 -> 48114 | AM46: =ROUND(AI46+AC46,0) -> 3524366 | AN46: =ROUNDUP(AJ46+W46+T46+Y46-AB46,0) -> 425813 | AO46: =AN46+AL46+AR46 -> 473927 | AP46: =AM46+AO46 -> 3998293 | AQ46: 3504063 | AR46: 0 | AS46: =ROUND(AP46-AQ46,0) -> 494230 | AT46: 0 | AU46: 8800 | AV46: =AU46*N46 -> 1411344 | AW46: =MAX(AM46,AT46,AV46) -> 3524366 | AX46: =CEILING((AW46),1000) -> 3525000 | AY46: 0.05 | AZ46: =AY46*AX46 -> 176250 | BA46: =CEILING(AZ46,100) -> 176300 | BB46: =BA46+AS46 -> 670530 | BC46: =L46/J46% -> 0 | BD46: =O46/M46% -> 0 | BE46: 34.3 | BF46: 14.9 | BG46: 46176 | BH46: =BG46+30 -> 46206 | BI46: 5 | BL46: =VLOOKUP(A46,[2]Sheet1!$D$2:$H$933,5,0) -> 0 | BM46: UBPL M3M CAPITAL PHASE 2 MASTER ACCOUNT | BN46: 777705551661 | BO46: ICIC0000399 | BP46: ICICI Bank | BQ46: Shop No - 19, 20, Vipul Orchid Plaza, Suncity, Sector 54, Gurgaon, Haryana -122002 | BR46: Union Buildmart Private Limited | BS46: AABCU4843M | BT46: 41st Floor, Tower-1, M3M International Financial center, sector- 66,Gurugram, Haryana, India 122101 | BU46: (……………..)Village Chauma, Sector – 113, Gurugram, Manesar Urban Complex, GURGAON, HARYANA, INDIA PIN Code: 122017 | BV46: Feedback@m3mindia.com | BW46: 8068970077 | BX46: 0 | BY46: Deepak chaubey | BZ46: Sabhyata Kapoor
A47: R1 222 | B47: M3M Capital Walk in M3M Capital Phase-2 | C47: cwBOOKING/00333/22-23 | D47: cwFLAP/00269/22-23 | E47: Mr. KOMAL AHUJA | F47: 44926 | G47: BLOCK-01 | H47: FLOOR 2 | I47: Retail | J47: 529.59 | K47: 529.59 | L47: =K47-J47 -> 0 | M47: 242.19 | N47: 242.19 | O47: =N47-M47 -> 0 | P47: 11400 | Q47: 24928.056 | R47: 20000 | S47: 6037326 | T47: 724480 | U47: =T47/S47 -> 0.12000015 | V47: =L47*P47 -> 0 | W47: =V47*U47 -> 0 | Z47: =S47+V47+X47 -> 6037326 | AC47: =Z47-AA47 -> 6037326 | AD47: =AE47/M47 -> 300 | AE47: 72657 | AF47: 13078 | AG47: =(AD47*O47) -> 0 | AH47: =AG47*18% -> 0 | AI47: =AD47*N47 -> 72657 | AJ47: =ROUNDUP(AI47*18%,0) -> 13079 | AK47: 72657 | AL47: =N47*300 -> 72657 | AM47: =ROUND(AI47+AC47,0) -> 6109983 | AN47: =ROUNDUP(AJ47+W47+T47+Y47-AB47,0) -> 737559 | AO47: =AN47+AL47+AR47 -> 810216 | AP47: =AM47+AO47 -> 6920199 | AQ47: 6085626 | AR47: 0 | AS47: =ROUND(AP47-AQ47,0) -> 834573 | AT47: 0 | AU47: 8800 | AV47: =AU47*N47 -> 2131272 | AW47: =MAX(AM47,AT47,AV47) -> 6109983 | AX47: =CEILING((AW47),1000) -> 6110000 | AY47: 0.0634 | AZ47: =AY47*AX47 -> 387374 | BA47: =CEILING(AZ47,100) -> 387400 | BB47: =BA47+AS47 -> 1221973 | BC47: =L47/J47% -> 0 | BD47: =O47/M47% -> 0 | BE47: 49.2 | BF47: 22.5 | BG47: 46176 | BH47: =BG47+30 -> 46206 | BI47: 6.34 | BL47: =VLOOKUP(A47,[2]Sheet1!$D$2:$H$933,5,0) -> 0 | BM47: UBPL M3M CAPITAL PHASE 2 MASTER ACCOUNT | BN47: 777705551661 | BO47: ICIC0000399 | BP47: ICICI Bank | BQ47: Shop No - 19, 20, Vipul Orchid Plaza, Suncity, Sector 54, Gurgaon, Haryana -122002 | BR47: Union Buildmart Private Limited | BS47: AABCU4843M | BT47: 41st Floor, Tower-1, M3M International Financial center, sector- 66,Gurugram, Haryana, India 122101 | BU47: (……………..)Village Chauma, Sector – 113, Gurugram, Manesar Urban Complex, GURGAON, HARYANA, INDIA PIN Code: 122017 | BV47: Feedback@m3mindia.com | BW47: 8068970077 | BX47: 0 | BY47: Preeti Chauhan | BZ47: Sabhyata Kapoor
A48: R1 228 | B48: M3M Capital Walk in M3M Capital Phase-2 | C48: cwBOOKING/00390/22-23 | D48: cwFLAP/00383/22-23 | E48: Ms. SUMAN SHARMA | F48: 44945 | G48: BLOCK-01 | H48: FLOOR 2 | I48: Retail | J48: 574.37 | K48: 574.37 | L48: =K48-J48 -> 0 | M48: 266.95 | N48: 266.95 | O48: =N48-M48 -> 0 | P48: 8649.7502 | Q48: 18610.815 | R48: 20000 | S48: 4968157 | T48: 596180 | U48: =T48/S48 -> 0.12000023 | V48: =L48*P48 -> 0 | W48: =V48*U48 -> 0 | Z48: =S48+V48+X48 -> 4968157 | AC48: =Z48-AA48 -> 4968157 | AD48: =AE48/M48 -> 300 | AE48: 80085 | AF48: 14416 | AG48: =(AD48*O48) -> 0 | AH48: =AG48*18% -> 0 | AI48: =AD48*N48 -> 80085 | AJ48: =ROUNDUP(AI48*18%,0) -> 14416 | AK48: 80085 | AL48: =N48*300 -> 80085 | AM48: =ROUND(AI48+AC48,0) -> 5048242 | AN48: =ROUNDUP(AJ48+W48+T48+Y48-AB48,0) -> 610596 | AO48: =AN48+AL48+AR48 -> 690681 | AP48: =AM48+AO48 -> 5738923 | AQ48: 4854102 | AR48: 0 | AS48: =ROUND(AP48-AQ48,0) -> 884821 | AT48: 0 | AU48: 8800 | AV48: =AU48*N48 -> 2349160 | AW48: =MAX(AM48,AT48,AV48) -> 5048242 | AX48: =CEILING((AW48),1000) -> 5049000 | AY48: 0.05 | AZ48: =AY48*AX48 -> 252450 | BA48: =CEILING(AZ48,100) -> 252500 | BB48: =BA48+AS48 -> 1137321 | BC48: =L48/J48% -> 0 | BD48: =O48/M48% -> 0 | BE48: 53.36 | BF48: 24.8 | BG48: 46176 | BH48: =BG48+30 -> 46206 | BI48: 5 | BL48: =VLOOKUP(A48,[2]Sheet1!$D$2:$H$933,5,0) -> 0 | BM48: UBPL M3M CAPITAL PHASE 2 MASTER ACCOUNT | BN48: 777705551661 | BO48: ICIC0000399 | BP48: ICICI Bank | BQ48: Shop No - 19, 20, Vipul Orchid Plaza, Suncity, Sector 54, Gurgaon, Haryana -122002 | BR48: Union Buildmart Private Limited | BS48: AABCU4843M | BT48: 41st Floor, Tower-1, M3M International Financial center, sector- 66,Gurugram, Haryana, India 122101 | BU48: (……………..)Village Chauma, Sector – 113, Gurugram, Manesar Urban Complex, GURGAON, HARYANA, INDIA PIN Code: 122017 | BV48: Feedback@m3mindia.com | BW48: 8068970077 | BX48: 0 | BY48: Preeti Chauhan | BZ48: Sabhyata Kapoor
A49: R1 231 | B49: M3M Capital Walk in M3M Capital Phase-2 | C49: cwBOOKING/00075/22-23 | D49: cwFLAP/00178/22-23 | E49: Ms. GARIMA MOHAN | F49: 44882 | G49: BLOCK-01 | H49: FLOOR 2 | I49: Retail | J49: 564.46 | K49: 564.46 | L49: =K49-J49 -> 0 | M49: 248.65 | N49: 248.65 | O49: =N49-M49 -> 0 | P49: 14800 | Q49: 33597.458 | R49: 20000 | S49: 8354008 | T49: 1002482 | U49: =T49/S49 -> 0.12000012 | V49: =L49*P49 -> 0 | W49: =V49*U49 -> 0 | Z49: =S49+V49+X49 -> 8354008 | AA49: 1826626 | AB49: 219196 | AC49: =Z49-AA49 -> 6527382 | AD49: =AE49/M49 -> 300 | AE49: 74595 | AF49: 13428 | AG49: =(AD49*O49) -> 0 | AH49: =AG49*18% -> 0 | AI49: =AD49*N49 -> 74595 | AJ49: =ROUNDUP(AI49*18%,0) -> 13428 | AK49: 74595 | AL49: =N49*300 -> 74595 | AM49: =ROUND(AI49+AC49,0) -> 6601977 | AN49: =ROUNDUP(AJ49+W49+T49+Y49-AB49,0) -> 796714 | AO49: =AN49+AL49+AR49 -> 871309 | AP49: =AM49+AO49 -> 7473286 | AQ49: 6375020 | AR49: 0 | AS49: =ROUND(AP49-AQ49,0) -> 1098266 | AT49: 0 | AU49: 8800 | AV49: =AU49*N49 -> 2188120 | AW49: =MAX(AM49,AT49,AV49) -> 6601977 | AX49: =CEILING((AW49),1000) -> 6602000 | AY49: 0.06 | AZ49: =AY49*AX49 -> 396120 | BA49: =CEILING(AZ49,100) -> 396200 | BB49: =BA49+AS49 -> 1494466 | BC49: =L49/J49% -> 0 | BD49: =O49/M49% -> 0 | BE49: 52.44 | BF49: 23.1 | BG49: 46176 | BH49: =BG49+30 -> 46206 | BI49: 6 | BL49: =VLOOKUP(A49,[2]Sheet1!$D$2:$H$933,5,0) -> 0 | BM49: UBPL M3M CAPITAL PHASE 2 MASTER ACCOUNT | BN49: 777705551661 | BO49: ICIC0000399 | BP49: ICICI Bank | BQ49: Shop No - 19, 20, Vipul Orchid Plaza, Suncity, Sector 54, Gurgaon, Haryana -122002 | BR49: Union Buildmart Private Limited | BS49: AABCU4843M | BT49: 41st Floor, Tower-1, M3M International Financial center, sector- 66,Gurugram, Haryana, India 122101 | BU49: (……………..)Village Chauma, Sector – 113, Gurugram, Manesar Urban Complex, GURGAON, HARYANA, INDIA PIN Code: 122017 | BV49: Feedback@m3mindia.com | BW49: 8068970077 | BX49: 0 | BY49: Darshan Lal | BZ49: Sabhyata Kapoor
A50: R1 232 | B50: M3M Capital Walk in M3M Capital Phase-2 | C50: cwBOOKING/00257/22-23 | D50: cwFLAP/00281/22-23 | E50: Mr. PRAVEEN KUMAR | F50: 44903 | G50: BLOCK-01 | H50: FLOOR 2 | I50: Retail | J50: 742.07 | K50: 742.07 | L50: =K50-J50 -> 0 | M50: 340.14 | N50: 340.14 | O50: =N50-M50 -> 0 | P50: 7285.0001 | Q50: 15893.397 | R50: 20000 | S50: 5405980 | T50: 648720 | U50: =T50/S50 -> 0.12000044 | V50: =L50*P50 -> 0 | W50: =V50*U50 -> 0 | Z50: =S50+V50+X50 -> 5405980 | AA50: 1073875 | AB50: 128866 | AC50: =Z50-AA50 -> 4332105 | AD50: =AE50/M50 -> 300 | AE50: 102042 | AF50: 18368 | AG50: =(AD50*O50) -> 0 | AH50: =AG50*18% -> 0 | AI50: =AD50*N50 -> 102042 | AJ50: =ROUNDUP(AI50*18%,0) -> 18368 | AK50: 102042 | AL50: =N50*300 -> 102042 | AM50: =ROUND(AI50+AC50,0) -> 4434147 | AN50: =ROUNDUP(AJ50+W50+T50+Y50-AB50,0) -> 538222 | AO50: =AN50+AL50+AR50 -> 640264 | AP50: =AM50+AO50 -> 5074411 | AQ50: 4701609.6 | AR50: 0 | AS50: =ROUND(AP50-AQ50,0) -> 372801 | AT50: 5405980 | AU50: 8800 | AV50: =AU50*N50 -> 2993232 | AW50: =MAX(AM50,AT50,AV50) -> 5405980 | AX50: =CEILING((AW50),1000) -> 5406000 | AY50: 0.07 | AZ50: =AY50*AX50 -> 378420 | BA50: =CEILING(AZ50,100) -> 378500 | BB50: =BA50+AS50 -> 751301 | BC50: =L50/J50% -> 0 | BD50: =O50/M50% -> 0 | BE50: 68.94 | BF50: 31.6 | BG50: 46176 | BH50: =BG50+30 -> 46206 | BI50: 7 | BL50: =VLOOKUP(A50,[2]Sheet1!$D$2:$H$933,5,0) -> 0 | BM50: UBPL M3M CAPITAL PHASE 2 MASTER ACCOUNT | BN50: 777705551661 | BO50: ICIC0000399 | BP50: ICICI Bank | BQ50: Shop No - 19, 20, Vipul Orchid Plaza, Suncity, Sector 54, Gurgaon, Haryana -122002 | BR50: Union Buildmart Private Limited | BS50: AABCU4843M | BT50: 41st Floor, Tower-1, M3M International Financial center, sector- 66,Gurugram, Haryana, India 122101 | BU50: (……………..)Village Chauma, Sector – 113, Gurugram, Manesar Urban Complex, GURGAON, HARYANA, INDIA PIN Code: 122017 | BV50: Feedback@m3mindia.com | BW50: 8068970077 | BX50: 0 | BY50: Chandrima | BZ50: Sabhyata Kapoor
A51: R1 233 | B51: M3M Capital Walk in M3M Capital Phase-2 | C51: cwBOOKING/00278/22-23 | D51: cwFLAP/00362/22-23 | E51: Ms. NELLA MANOJ DAVIS | F51: 44907 | G51: BLOCK-01 | H51: FLOOR 2 | I51: Retail | J51: 617.85 | K51: 617.85 | L51: =K51-J51 -> 0 | M51: 286.32 | N51: 286.32 | O51: =N51-M51 -> 0 | P51: 12250.001 | Q51: 26434.28 | R51: 20000 | S51: 7568663 | T51: 908240 | U51: =T51/S51 -> 0.12000006 | V51: =L51*P51 -> 0 | W51: =V51*U51 -> 0 | Z51: =S51+V51+X51 -> 7568663 | AC51: =Z51-AA51 -> 7568663 | AD51: =AE51/M51 -> 300 | AE51: 85896 | AF51: 15462 | AG51: =(AD51*O51) -> 0 | AH51: =AG51*18% -> 0 | AI51: =AD51*N51 -> 85896 | AJ51: =ROUNDUP(AI51*18%,0) -> 15462 | AK51: 85896 | AL51: =N51*300 -> 85896 | AM51: =ROUND(AI51+AC51,0) -> 7654559 | AN51: =ROUNDUP(AJ51+W51+T51+Y51-AB51,0) -> 923702 | AO51: =AN51+AL51+AR51 -> 1009598 | AP51: =AM51+AO51 -> 8664157 | AQ51: 7629213 | AR51: 0 | AS51: =ROUND(AP51-AQ51,0) -> 1034944 | AT51: 0 | AU51: 8800 | AV51: =AU51*N51 -> 2519616 | AW51: =MAX(AM51,AT51,AV51) -> 7654559 | AX51: =CEILING((AW51),1000) -> 7655000 | AY51: 0.06 | AZ51: =AY51*AX51 -> 459300 | BA51: =CEILING(AZ51,100) -> 459300 | BB51: =BA51+AS51 -> 1494244 | BC51: =L51/J51% -> 0 | BD51: =O51/M51% -> 0 | BE51: 57.4 | BF51: 26.6 | BG51: 46176 | BH51: =BG51+30 -> 46206 | BI51: 6 | BL51: =VLOOKUP(A51,[2]Sheet1!$D$2:$H$933,5,0) -> 0 | BM51: UBPL M3M CAPITAL PHASE 2 MASTER ACCOUNT | BN51: 777705551661 | BO51: ICIC0000399 | BP51: ICICI Bank | BQ51: Shop No - 19, 20, Vipul Orchid Plaza, Suncity, Sector 54, Gurgaon, Haryana -122002 | BR51: Union Buildmart Private Limited | BS51: AABCU4843M | BT51: 41st Floor, Tower-1, M3M International Financial center, sector- 66,Gurugram, Haryana, India 122101 | BU51: (……………..)Village Chauma, Sector – 113, Gurugram, Manesar Urban Complex, GURGAON, HARYANA, INDIA PIN Code: 122017 | BV51: Feedback@m3mindia.com | BW51: 8068970077 | BX51: 0 | BY51: Preeti Chauhan | BZ51: Sabhyata Kapoor
A52: R1 238 | B52: M3M Capital Walk in M3M Capital Phase-2 | C52: cwBOOKING/00358/22-23 | D52: cwFLAP/00424/22-23 | E52: Ms. URMILA SINHA | F52: 44931 | G52: BLOCK-01 | H52: FLOOR 2 | I52: Retail | J52: 676.41 | K52: 676.41 | L52: =K52-J52 -> 0 | M52: 315.39 | N52: 315.39 | O52: =N52-M52 -> 0 | P52: 11850.001 | Q52: 25414.436 | R52: 20000 | S52: 8015459 | T52: 961856 | U52: =T52/S52 -> 0.12000011 | V52: =L52*P52 -> 0 | W52: =V52*U52 -> 0 | Z52: =S52+V52+X52 -> 8015459 | AC52: =Z52-AA52 -> 8015459 | AD52: =AE52/M52 -> 300 | AE52: 94617 | AF52: 17032 | AG52: =(AD52*O52) -> 0 | AH52: =AG52*18% -> 0 | AI52: =AD52*N52 -> 94617 | AJ52: =ROUNDUP(AI52*18%,0) -> 17032 | AK52: 94617 | AL52: =N52*300 -> 94617 | AM52: =ROUND(AI52+AC52,0) -> 8110076 | AN52: =ROUNDUP(AJ52+W52+T52+Y52-AB52,0) -> 978888 | AO52: =AN52+AL52+AR52 -> 1073505 | AP52: =AM52+AO52 -> 9183581 | AQ52: 8079581 | AR52: 0 | AS52: =ROUND(AP52-AQ52,0) -> 1104000 | AT52: 0 | AU52: 8800 | AV52: =AU52*N52 -> 2775432 | AW52: =MAX(AM52,AT52,AV52) -> 8110076 | AX52: =CEILING((AW52),1000) -> 8111000 | AY52: 0.05 | AZ52: =AY52*AX52 -> 405550 | BA52: =CEILING(AZ52,100) -> 405600 | BB52: =BA52+AS52 -> 1509600 | BC52: =L52/J52% -> 0 | BD52: =O52/M52% -> 0 | BE52: 62.84 | BF52: 29.3 | BG52: 46176 | BH52: =BG52+30 -> 46206 | BI52: 5 | BL52: =VLOOKUP(A52,[2]Sheet1!$D$2:$H$933,5,0) -> 0 | BM52: UBPL M3M CAPITAL PHASE 2 MASTER ACCOUNT | BN52: 777705551661 | BO52: ICIC0000399 | BP52: ICICI Bank | BQ52: Shop No - 19, 20, Vipul Orchid Plaza, Suncity, Sector 54, Gurgaon, Haryana -122002 | BR52: Union Buildmart Private Limited | BS52: AABCU4843M | BT52: 41st Floor, Tower-1, M3M International Financial center, sector- 66,Gurugram, Haryana, India 122101 | BU52: (……………..)Village Chauma, Sector – 113, Gurugram, Manesar Urban Complex, GURGAON, HARYANA, INDIA PIN Code: 122017 | BV52: Feedback@m3mindia.com | BW52: 8068970077 | BX52: 0 | BY52: Sonia Gupta | BZ52: Sabhyata Kapoor
A53: R1 239 | B53: M3M Capital Walk in M3M Capital Phase-2 | C53: cwBOOKING/00640/22-23 | D53: cwFLAP/00466/22-23 | E53: Mr. PARVEEN CHAWLA | F53: 44998 | G53: BLOCK-01 | H53: FLOOR 2 | I53: Retail | J53: 676.41 | K53: 676.41 | L53: =K53-J53 -> 0 | M53: 315.39 | N53: 315.39 | O53: =N53-M53 -> 0 | P53: 13669 | Q53: 29315.603 | R53: 20000 | S53: 9245848 | T53: 1109500 | U53: =T53/S53 -> 0.11999981 | V53: =L53*P53 -> 0 | W53: =V53*U53 -> 0 | Z53: =S53+V53+X53 -> 9245848 | AA53: 2744765 | AB53: 329372 | AC53: =Z53-AA53 -> 6501083 | AD53: =AE53/M53 -> 300 | AE53: 94617 | AF53: 17032 | AG53: =(AD53*O53) -> 0 | AH53: =AG53*18% -> 0 | AI53: =AD53*N53 -> 94617 | AJ53: =ROUNDUP(AI53*18%,0) -> 17032 | AK53: 94617 | AL53: =N53*300 -> 94617 | AM53: =ROUND(AI53+AC53,0) -> 6595700 | AN53: =ROUNDUP(AJ53+W53+T53+Y53-AB53,0) -> 797160 | AO53: =AN53+AL53+AR53 -> 891777 | AP53: =AM53+AO53 -> 7487477 | AQ53: 6720000 | AR53: 0 | AS53: =ROUND(AP53-AQ53,0) -> 767477 | AT53: 0 | AU53: 8800 | AV53: =AU53*N53 -> 2775432 | AW53: =MAX(AM53,AT53,AV53) -> 6595700 | AX53: =CEILING((AW53),1000) -> 6596000 | AY53: 0.07 | AZ53: =AY53*AX53 -> 461720 | BA53: =CEILING(AZ53,100) -> 461800 | BB53: =BA53+AS53 -> 1229277 | BC53: =L53/J53% -> 0 | BD53: =O53/M53% -> 0 | BE53: 62.84 | BF53: 29.3 | BG53: 46176 | BH53: =BG53+30 -> 46206 | BI53: 7 | BL53: =VLOOKUP(A53,[2]Sheet1!$D$2:$H$933,5,0) -> 0 | BM53: UBPL M3M CAPITAL PHASE 2 MASTER ACCOUNT | BN53: 777705551661 | BO53: ICIC0000399 | BP53: ICICI Bank | BQ53: Shop No - 19, 20, Vipul Orchid Plaza, Suncity, Sector 54, Gurgaon, Haryana -122002 | BR53: Union Buildmart Private Limited | BS53: AABCU4843M | BT53: 41st Floor, Tower-1, M3M International Financial center, sector- 66,Gurugram, Haryana, India 122101 | BU53: (……………..)Village Chauma, Sector – 113, Gurugram, Manesar Urban Complex, GURGAON, HARYANA, INDIA PIN Code: 122017 | BV53: Feedback@m3mindia.com | BW53: 8068970077 | BX53: 0 | BY53: Preeti Chauhan | BZ53: Sabhyata Kapoor
A54: R1 241 | B54: M3M Capital Walk in M3M Capital Phase-2 | C54: cwBOOKING/00411/22-23 | D54: cwFLAP/00169/22-23 | E54: Mr. ATUL KUMAR SETHI | F54: 44956 | G54: BLOCK-01 | H54: FLOOR 2 | I54: Retail | J54: 1044.97 | K54: 1020.9 | L54: =K54-J54 -> -24.07 | M54: 479 | N54: 468 | O54: =N54-M54 -> -11 | P54: 6736.69 | Q54: 14696.532 | R54: 20000 | S54: 7039639 | T54: 844756 | U54: =T54/S54 -> 0.1199999 | V54: =L54*P54 -> -162152.13 | W54: =V54*U54 -> -19458.24 | Z54: =S54+V54+X54 -> 6877486.9 | AC54: =Z54-AA54 -> 6877486.9 | AD54: =AE54/M54 -> 300 | AE54: 143700 | AF54: 25866 | AG54: =(AD54*O54) -> -3300 | AH54: =AG54*18% -> -594 | AI54: =AD54*N54 -> 140400 | AJ54: =ROUNDUP(AI54*18%,0) -> 25272 | AK54: 143700 | AL54: =N54*300 -> 140400 | AM54: =ROUND(AI54+AC54,0) -> 7017887 | AN54: =ROUNDUP(AJ54+W54+T54+Y54-AB54,0) -> 850570 | AO54: =AN54+AL54+AR54 -> 990970 | AP54: =AM54+AO54 -> 8008857 | AQ54: 7095957 | AR54: 0 | AS54: =ROUND(AP54-AQ54,0) -> 912900 | AT54: 0 | AU54: 8800 | AV54: =AU54*N54 -> 4118400 | AW54: =MAX(AM54,AT54,AV54) -> 7017887 | AX54: =CEILING((AW54),1000) -> 7018000 | AY54: 0.06 | AZ54: =AY54*AX54 -> 421080 | BA54: =CEILING(AZ54,100) -> 421100 | BB54: =BA54+AS54 -> 1334000 | BC54: =L54/J54% -> -2.3034154 | BD54: =O54/M54% -> -2.2964509 | BE54: 94.84 | BF54: 43.48 | BG54: 46176 | BH54: =BG54+30 -> 46206 | BI54: 6 | BL54: =VLOOKUP(A54,[2]Sheet1!$D$2:$H$933,5,0) -> 0 | BM54: UBPL M3M CAPITAL PHASE 2 MASTER ACCOUNT | BN54: 777705551661 | BO54: ICIC0000399 | BP54: ICICI Bank | BQ54: Shop No - 19, 20, Vipul Orchid Plaza, Suncity, Sector 54, Gurgaon, Haryana -122002 | BR54: Union Buildmart Private Limited | BS54: AABCU4843M | BT54: 41st Floor, Tower-1, M3M International Financial center, sector- 66,Gurugram, Haryana, India 122101 | BU54: (……………..)Village Chauma, Sector – 113, Gurugram, Manesar Urban Complex, GURGAON, HARYANA, INDIA PIN Code: 122017 | BV54: Feedback@m3mindia.com | BW54: 8068970077 | BX54: 0 | BY54: Vidhi Singh | BZ54: Sabhyata Kapoor
A55: R1 242 | B55: M3M Capital Walk in M3M Capital Phase-2 | C55: cwBOOKING/00139/22-23 | D55: cwFLAP/00057/22-23 | E55: Mr. ABINASH KUMAR | F55: 44895 | G55: BLOCK-01 | H55: FLOOR 2 | I55: Retail | J55: 999.33 | K55: 999.33 | L55: =K55-J55 -> 0 | M55: 457.47 | N55: 457.47 | O55: =N55-M55 -> 0 | P55: 6500 | Q55: 14199.062 | R55: 20000 | S55: 6495645 | T55: 779478 | U55: =T55/S55 -> 0.12000009 | V55: =L55*P55 -> 0 | W55: =V55*U55 -> 0 | Z55: =S55+V55+X55 -> 6495645 | AA55: 1856751 | AB55: 222810 | AC55: =Z55-AA55 -> 4638894 | AD55: =AE55/M55 -> 300 | AE55: 137241 | AF55: 24704 | AG55: =(AD55*O55) -> 0 | AH55: =AG55*18% -> 0 | AI55: =AD55*N55 -> 137241 | AJ55: =ROUNDUP(AI55*18%,0) -> 24704 | AK55: 137241 | AL55: =N55*300 -> 137241 | AM55: =ROUND(AI55+AC55,0) -> 4776135 | AN55: =ROUNDUP(AJ55+W55+T55+Y55-AB55,0) -> 581372 | AO55: =AN55+AL55+AR55 -> 718613 | AP55: =AM55+AO55 -> 5494748 | AQ55: 4468053 | AR55: 0 | AS55: =ROUND(AP55-AQ55,0) -> 1026695 | AT55: 0 | AU55: 8800 | AV55: =AU55*N55 -> 4025736 | AW55: =MAX(AM55,AT55,AV55) -> 4776135 | AX55: =CEILING((AW55),1000) -> 4777000 | AY55: 0.07 | AZ55: =AY55*AX55 -> 334390 | BA55: =CEILING(AZ55,100) -> 334400 | BB55: =BA55+AS55 -> 1361095 | BC55: =L55/J55% -> 0 | BD55: =O55/M55% -> 0 | BE55: 92.84 | BF55: 42.5 | BG55: 46176 | BH55: =BG55+30 -> 46206 | BI55: 7 | BL55: =VLOOKUP(A55,[2]Sheet1!$D$2:$H$933,5,0) -> 0 | BM55: UBPL M3M CAPITAL PHASE 2 MASTER ACCOUNT | BN55: 777705551661 | BO55: ICIC0000399 | BP55: ICICI Bank | BQ55: Shop No - 19, 20, Vipul Orchid Plaza, Suncity, Sector 54, Gurgaon, Haryana -122002 | BR55: Union Buildmart Private Limited | BS55: AABCU4843M | BT55: 41st Floor, Tower-1, M3M International Financial center, sector- 66,Gurugram, Haryana, India 122101 | BU55: (……………..)Village Chauma, Sector – 113, Gurugram, Manesar Urban Complex, GURGAON, HARYANA, INDIA PIN Code: 122017 | BV55: Feedback@m3mindia.com | BW55: 8068970077 | BX55: 0 | BY55: Preeti Chauhan | BZ55: Sabhyata Kapoor
A56: R1 244 | B56: M3M Capital Walk in M3M Capital Phase-2 | C56: cwBOOKING/00743/22-23 | D56: cwFLAP/00629/22-23 | E56: Ms. SOUNDRYA NIDHI SINGH | F56: 45005 | G56: BLOCK-01 | H56: FLOOR 2 | I56: Retail | J56: 929.15 | K56: 929.15 | L56: =K56-J56 -> 0 | M56: 428.41 | N56: 428.41 | O56: =N56-M56 -> 0 | P56: 8747.9998 | Q56: 18972.956 | R56: 20000 | S56: 8128204 | T56: 975384 | U56: =T56/S56 -> 0.11999994 | V56: =L56*P56 -> 0 | W56: =V56*U56 -> 0 | Z56: =S56+V56+X56 -> 8128204 | AA56: 1457139 | AB56: 174856 | AC56: =Z56-AA56 -> 6671065 | AD56: =AE56/M56 -> 300 | AE56: 128523 | AF56: 23134 | AG56: =(AD56*O56) -> 0 | AH56: =AG56*18% -> 0 | AI56: =AD56*N56 -> 128523 | AJ56: =ROUNDUP(AI56*18%,0) -> 23135 | AK56: 128523 | AL56: =N56*300 -> 128523 | AM56: =ROUND(AI56+AC56,0) -> 6799588 | AN56: =ROUNDUP(AJ56+W56+T56+Y56-AB56,0) -> 823663 | AO56: =AN56+AL56+AR56 -> 952186 | AP56: =AM56+AO56 -> 7751774 | AQ56: 6561234 | AR56: 0 | AS56: =ROUND(AP56-AQ56,0) -> 1190540 | AT56: 0 | AU56: 8800 | AV56: =AU56*N56 -> 3770008 | AW56: =MAX(AM56,AT56,AV56) -> 6799588 | AX56: =CEILING((AW56),1000) -> 6800000 | AY56: 0.05 | AZ56: =AY56*AX56 -> 340000 | BA56: =CEILING(AZ56,100) -> 340000 | BB56: =BA56+AS56 -> 1530540 | BC56: =L56/J56% -> 0 | BD56: =O56/M56% -> 0 | BE56: 86.32 | BF56: 39.8 | BG56: 46176 | BH56: =BG56+30 -> 46206 | BI56: 5 | BL56: =VLOOKUP(A56,[2]Sheet1!$D$2:$H$933,5,0) -> 0 | BM56: UBPL M3M CAPITAL PHASE 2 MASTER ACCOUNT | BN56: 777705551661 | BO56: ICIC0000399 | BP56: ICICI Bank | BQ56: Shop No - 19, 20, Vipul Orchid Plaza, Suncity, Sector 54, Gurgaon, Haryana -122002 | BR56: Union Buildmart Private Limited | BS56: AABCU4843M | BT56: 41st Floor, Tower-1, M3M International Financial center, sector- 66,Gurugram, Haryana, India 122101 | BU56: (……………..)Village Chauma, Sector – 113, Gurugram, Manesar Urban Complex, GURGAON, HARYANA, INDIA PIN Code: 122017 | BV56: Feedback@m3mindia.com | BW56: 8068970077 | BX56: 0 | BY56: Sonia Gupta | BZ56: Sabhyata Kapoor
A57: R1 256 | B57: M3M Capital Walk in M3M Capital Phase-2 | C57: cwBOOKING/00672/22-23 | D57: cwFLAP/00803/22-23 | E57: Ms. DIKSHA GUPTA | F57: 45000 | G57: BLOCK-01 | H57: FLOOR 2 | I57: Anchor Units | J57: 571.69 | K57: 571.69 | L57: =K57-J57 -> 0 | M57: 234.66 | N57: 234.66 | O57: =N57-M57 -> 0 | P57: 8385.9994 | Q57: 20430.376 | R57: 20000 | S57: 4794192 | T57: 575304 | U57: =T57/S57 -> 0.1200002 | V57: =L57*P57 -> 0 | W57: =V57*U57 -> 0 | Z57: =S57+V57+X57 -> 4794192 | AC57: =Z57-AA57 -> 4794192 | AD57: =AE57/M57 -> 300 | AE57: 70398 | AF57: 12672 | AG57: =(AD57*O57) -> 0 | AH57: =AG57*18% -> 0 | AI57: =AD57*N57 -> 70398 | AJ57: =ROUNDUP(AI57*18%,0) -> 12672 | AK57: 70398 | AL57: =N57*300 -> 70398 | AM57: =ROUND(AI57+AC57,0) -> 4864590 | AN57: =ROUNDUP(AJ57+W57+T57+Y57-AB57,0) -> 587976 | AO57: =AN57+AL57+AR57 -> 658374 | AP57: =AM57+AO57 -> 5522964 | AQ57: 4720433 | AR57: 0 | AS57: =ROUND(AP57-AQ57,0) -> 802531 | AT57: 0 | AU57: 8800 | AV57: =AU57*N57 -> 2065008 | AW57: =MAX(AM57,AT57,AV57) -> 4864590 | AX57: =CEILING((AW57),1000) -> 4865000 | AY57: 0.06 | AZ57: =AY57*AX57 -> 291900 | BA57: =CEILING(AZ57,100) -> 291900 | BB57: =BA57+AS57 -> 1094431 | BC57: =L57/J57% -> 0 | BD57: =O57/M57% -> 0 | BE57: 53.11 | BF57: 21.8 | BG57: 46176 | BH57: =BG57+30 -> 46206 | BI57: 6 | BL57: =VLOOKUP(A57,[2]Sheet1!$D$2:$H$933,5,0) -> 0 | BM57: UBPL M3M CAPITAL PHASE 2 MASTER ACCOUNT | BN57: 777705551661 | BO57: ICIC0000399 | BP57: ICICI Bank | BQ57: Shop No - 19, 20, Vipul Orchid Plaza, Suncity, Sector 54, Gurgaon, Haryana -122002 | BR57: Union Buildmart Private Limited | BS57: AABCU4843M | BT57: 41st Floor, Tower-1, M3M International Financial center, sector- 66,Gurugram, Haryana, India 122101 | BU57: (……………..)Village Chauma, Sector – 113, Gurugram, Manesar Urban Complex, GURGAON, HARYANA, INDIA PIN Code: 122017 | BV57: Feedback@m3mindia.com | BW57: 8068970077 | BX57: 0 | BY57: Deepak chaubey | BZ57: Sabhyata Kapoor
A58: R1 G 07 | B58: M3M Capital Walk in M3M Capital Phase-2 | C58: cwBOOKING/00375/22-23 | D58: cwFLAP/00456/22-23 | E58: Ms. SEJAL JAIN | F58: 44940 | G58: BLOCK-01 | H58: GROUND | I58: Retail | J58: 1241.09 | K58: 1241.09 | L58: =K58-J58 -> 0 | M58: 580.18 | N58: 580.18 | O58: =N58-M58 -> 0 | P58: 11719.514 | Q58: 25069.758 | R58: 60000 | S58: 14544972 | T58: 1745396 | U58: =T58/S58 -> 0.11999996 | V58: =L58*P58 -> 0 | W58: =V58*U58 -> 0 | Z58: =S58+V58+X58 -> 14544972 | AC58: =Z58-AA58 -> 14544972 | AD58: =AE58/M58 -> 300 | AE58: 174054 | AF58: 31330 | AG58: =(AD58*O58) -> 0 | AH58: =AG58*18% -> 0 | AI58: =AD58*N58 -> 174054 | AJ58: =ROUNDUP(AI58*18%,0) -> 31330 | AK58: 174054 | AL58: =N58*300 -> 174054 | AM58: =ROUND(AI58+AC58,0) -> 14719026 | AN58: =ROUNDUP(AJ58+W58+T58+Y58-AB58,0) -> 1776726 | AO58: =AN58+AL58+AR58 -> 1950780 | AP58: =AM58+AO58 -> 16669806 | AQ58: 2825000 | AR58: 0 | AS58: =ROUND(AP58-AQ58,0) -> 13844806 | AT58: 0 | AU58: 8800 | AV58: =AU58*N58 -> 5105584 | AW58: =MAX(AM58,AT58,AV58) -> 14719026 | AX58: =CEILING((AW58),1000) -> 14720000 | AY58: 0.05 | AZ58: =AY58*AX58 -> 736000 | BA58: =CEILING(AZ58,100) -> 736000 | BB58: =BA58+AS58 -> 14580806 | BC58: =L58/J58% -> 0 | BD58: =O58/M58% -> 0 | BE58: 115.3 | BF58: 53.9 | BG58: 46176 | BH58: =BG58+30 -> 46206 | BI58: 5 | BL58: =VLOOKUP(A58,[2]Sheet1!$D$2:$H$933,5,0) -> 0 | BM58: UBPL M3M CAPITAL PHASE 2 MASTER ACCOUNT | BN58: 777705551661 | BO58: ICIC0000399 | BP58: ICICI Bank | BQ58: Shop No - 19, 20, Vipul Orchid Plaza, Suncity, Sector 54, Gurgaon, Haryana -122002 | BR58: Union Buildmart Private Limited | BS58: AABCU4843M | BT58: 41st Floor, Tower-1, M3M International Financial center, sector- 66,Gurugram, Haryana, India 122101 | BU58: (……………..)Village Chauma, Sector – 113, Gurugram, Manesar Urban Complex, GURGAON, HARYANA, INDIA PIN Code: 122017 | BV58: Feedback@m3mindia.com | BW58: 8068970077 | BX58: 3808998.9 | BY58: Sudhanshu Gurjar | BZ58: Sabhyata Kapoor
A59: R1 LG 03 | B59: M3M Capital Walk in M3M Capital Phase-2 | C59: cwBOOKING/00031/23-24 | D59: cwFLAP/00996/22-23 | E59: Mr. SURYAVIR SINGH | F59: 45027 | G59: BLOCK-01 | H59: BASEMENT 2 | I59: Retail | J59: 668.44 | K59: 668.44 | L59: =K59-J59 -> 0 | M59: 306.24 | N59: 306.24 | O59: =N59-M59 -> 0 | P59: 35443 | Q59: 77362.588 | R59: 40000 | S59: 23691519 | T59: 2842982 | U59: =T59/S59 -> 0.11999999 | V59: =L59*P59 -> 0 | W59: =V59*U59 -> 0 | Z59: =S59+V59+X59 -> 23691519 | AC59: =Z59-AA59 -> 23691519 | AD59: =AE59/M59 -> 300 | AE59: 91872 | AF59: 16536 | AG59: =(AD59*O59) -> 0 | AH59: =AG59*18% -> 0 | AI59: =AD59*N59 -> 91872 | AJ59: =ROUNDUP(AI59*18%,0) -> 16537 | AK59: 91872 | AL59: =N59*300 -> 91872 | AM59: =ROUND(AI59+AC59,0) -> 23783391 | AN59: =ROUNDUP(AJ59+W59+T59+Y59-AB59,0) -> 2859519 | AO59: =AN59+AL59+AR59 -> 2951391 | AP59: =AM59+AO59 -> 26734782 | AQ59: 23881051 | AR59: 0 | AS59: =ROUND(AP59-AQ59,0) -> 2853731 | AT59: 0 | AU59: 8800 | AV59: =AU59*N59 -> 2694912 | AW59: =MAX(AM59,AT59,AV59) -> 23783391 | AX59: =CEILING((AW59),1000) -> 23784000 | AY59: 0.06 | AZ59: =AY59*AX59 -> 1427040 | BA59: =CEILING(AZ59,100) -> 1427100 | BB59: =BA59+AS59 -> 4280831 | BC59: =L59/J59% -> 0 | BD59: =O59/M59% -> 0 | BE59: 62.1 | BF59: 28.45 | BG59: 46176 | BH59: =BG59+30 -> 46206 | BI59: 6 | BL59: =VLOOKUP(A59,[2]Sheet1!$D$2:$H$933,5,0) -> 0 | BM59: UBPL M3M CAPITAL PHASE 2 MASTER ACCOUNT | BN59: 777705551661 | BO59: ICIC0000399 | BP59: ICICI Bank | BQ59: Shop No - 19, 20, Vipul Orchid Plaza, Suncity, Sector 54, Gurgaon, Haryana -122002 | BR59: Union Buildmart Private Limited | BS59: AABCU4843M | BT59: 41st Floor, Tower-1, M3M International Financial center, sector- 66,Gurugram, Haryana, India 122101 | BU59: (……………..)Village Chauma, Sector – 113, Gurugram, Manesar Urban Complex, GURGAON, HARYANA, INDIA PIN Code: 122017 | BV59: Feedback@m3mindia.com | BW59: 8068970077 | BX59: 0 | BY59: Vidhi Singh | BZ59: Sabhyata Kapoor
A60: R1 LG 04 | B60: M3M Capital Walk in M3M Capital Phase-2 | C60: cwBOOKING/00294/23-24 | D60: cwFLAP/00179/23-24 | E60: Mr. Nand Ram Saini | F60: 45247 | G60: BLOCK-01 | H60: BASEMENT 2 | I60: Retail | J60: 668.44 | K60: 668.44 | L60: =K60-J60 -> 0 | M60: 306.24 | N60: 306.24 | O60: =N60-M60 -> 0 | P60: 17999.997 | Q60: 39289.178 | R60: 40000 | S60: 12031918 | T60: 1443830 | U60: =T60/S60 -> 0.11999999 | V60: =L60*P60 -> 0 | W60: =V60*U60 -> 0 | Z60: =S60+V60+X60 -> 12031918 | AC60: =Z60-AA60 -> 12031918 | AD60: =AE60/M60 -> 300 | AE60: 91872 | AF60: 16536 | AG60: =(AD60*O60) -> 0 | AH60: =AG60*18% -> 0 | AI60: =AD60*N60 -> 91872 | AJ60: =ROUNDUP(AI60*18%,0) -> 16537 | AK60: 91872 | AL60: =N60*300 -> 91872 | AM60: =ROUND(AI60+AC60,0) -> 12123790 | AN60: =ROUNDUP(AJ60+W60+T60+Y60-AB60,0) -> 1460367 | AO60: =AN60+AL60+AR60 -> 1552239 | AP60: =AM60+AO60 -> 13676029 | AQ60: 12240476 | AR60: 0 | AS60: =ROUND(AP60-AQ60,0) -> 1435553 | AT60: 0 | AU60: 8800 | AV60: =AU60*N60 -> 2694912 | AW60: =MAX(AM60,AT60,AV60) -> 12123790 | AX60: =CEILING((AW60),1000) -> 12124000 | AY60: 0.07 | AZ60: =AY60*AX60 -> 848680 | BA60: =CEILING(AZ60,100) -> 848700 | BB60: =BA60+AS60 -> 2284253 | BC60: =L60/J60% -> 0 | BD60: =O60/M60% -> 0 | BE60: 62.1 | BF60: 28.45 | BG60: 46176 | BH60: =BG60+30 -> 46206 | BI60: 7 | BL60: =VLOOKUP(A60,[2]Sheet1!$D$2:$H$933,5,0) -> 0 | BM60: UBPL M3M CAPITAL PHASE 2 MASTER ACCOUNT | BN60: 777705551661 | BO60: ICIC0000399 | BP60: ICICI Bank | BQ60: Shop No - 19, 20, Vipul Orchid Plaza, Suncity, Sector 54, Gurgaon, Haryana -122002 | BR60: Union Buildmart Private Limited | BS60: AABCU4843M | BT60: 41st Floor, Tower-1, M3M International Financial center, sector- 66,Gurugram, Haryana, India 122101 | BU60: (……………..)Village Chauma, Sector – 113, Gurugram, Manesar Urban Complex, GURGAON, HARYANA, INDIA PIN Code: 122017 | BV60: Feedback@m3mindia.com | BW60: 8068970077 | BX60: 0 | BY60: Sudhanshu Gurjar | BZ60: Sabhyata Kapoor
A61: R1 LG 05 | B61: M3M Capital Walk in M3M Capital Phase-2 | C61: cwBOOKING/00281/23-24 | D61: cwFLAP/00159/23-24 | E61: Mr. Vikas Arora | F61: 45181 | G61: BLOCK-01 | H61: BASEMENT 2 | I61: Retail | J61: 668.44 | K61: 668.44 | L61: =K61-J61 -> 0 | M61: 306.24 | N61: 306.24 | O61: =N61-M61 -> 0 | P61: 14020 | Q61: 30601.91 | R61: 40000 | S61: 9371529 | T61: 1124584 | U61: =T61/S61 -> 0.12000006 | V61: =L61*P61 -> 0 | W61: =V61*U61 -> 0 | Z61: =S61+V61+X61 -> 9371529 | AC61: =Z61-AA61 -> 9371529 | AD61: =AE61/M61 -> 300 | AE61: 91872 | AF61: 16536 | AG61: =(AD61*O61) -> 0 | AH61: =AG61*18% -> 0 | AI61: =AD61*N61 -> 91872 | AJ61: =ROUNDUP(AI61*18%,0) -> 16537 | AK61: 91872 | AL61: =N61*300 -> 91872 | AM61: =ROUND(AI61+AC61,0) -> 9463401 | AN61: =ROUNDUP(AJ61+W61+T61+Y61-AB61,0) -> 1141121 | AO61: =AN61+AL61+AR61 -> 1232993 | AP61: =AM61+AO61 -> 10696394 | AQ61: 2099223.1 | AR61: 0 | AS61: =ROUND(AP61-AQ61,0) -> 8597171 | AT61: 0 | AU61: 8800 | AV61: =AU61*N61 -> 2694912 | AW61: =MAX(AM61,AT61,AV61) -> 9463401 | AX61: =CEILING((AW61),1000) -> 9464000 | AY61: 0.0567 | AZ61: =AY61*AX61 -> 536608.8 | BA61: =CEILING(AZ61,100) -> 536700 | BB61: =BA61+AS61 -> 9133871 | BC61: =L61/J61% -> 0 | BD61: =O61/M61% -> 0 | BE61: 62.1 | BF61: 28.45 | BG61: 46176 | BH61: =BG61+30 -> 46206 | BI61: 5.67 | BL61: =VLOOKUP(A61,[2]Sheet1!$D$2:$H$933,5,0) -> 0 | BM61: UBPL M3M CAPITAL PHASE 2 MASTER ACCOUNT | BN61: 777705551661 | BO61: ICIC0000399 | BP61: ICICI Bank | BQ61: Shop No - 19, 20, Vipul Orchid Plaza, Suncity, Sector 54, Gurgaon, Haryana -122002 | BR61: Union Buildmart Private Limited | BS61: AABCU4843M | BT61: 41st Floor, Tower-1, M3M International Financial center, sector- 66,Gurugram, Haryana, India 122101 | BU61: (……………..)Village Chauma, Sector – 113, Gurugram, Manesar Urban Complex, GURGAON, HARYANA, INDIA PIN Code: 122017 | BV61: Feedback@m3mindia.com | BW61: 8068970077 | BX61: 0 | BY61: Sudhanshu Gurjar | BZ61: Sabhyata Kapoor
A62: R1 LG 08 | B62: M3M Capital Walk in M3M Capital Phase-2 | C62: cwBOOKING/00298/23-24 | D62: cwFLAP/00164/23-24 | E62: Mr. Chhotu Ram Saini | F62: 45266 | G62: BLOCK-01 | H62: BASEMENT 2 | I62: Retail | J62: 668.44 | K62: 668.44 | L62: =K62-J62 -> 0 | M62: 306.24 | N62: 306.24 | O62: =N62-M62 -> 0 | P62: 10000.003 | Q62: 21827.332 | R62: 40000 | S62: 6684402 | T62: 802130 | U62: =T62/S62 -> 0.12000026 | V62: =L62*P62 -> 0 | W62: =V62*U62 -> 0 | Z62: =S62+V62+X62 -> 6684402 | AC62: =Z62-AA62 -> 6684402 | AD62: =AE62/M62 -> 300 | AE62: 91872 | AF62: 16536 | AG62: =(AD62*O62) -> 0 | AH62: =AG62*18% -> 0 | AI62: =AD62*N62 -> 91872 | AJ62: =ROUNDUP(AI62*18%,0) -> 16537 | AK62: 91872 | AL62: =N62*300 -> 91872 | AM62: =ROUND(AI62+AC62,0) -> 6776274 | AN62: =ROUNDUP(AJ62+W62+T62+Y62-AB62,0) -> 818667 | AO62: =AN62+AL62+AR62 -> 910539 | AP62: =AM62+AO62 -> 7686813 | AQ62: 6989222 | AR62: 0 | AS62: =ROUND(AP62-AQ62,0) -> 697591 | AT62: 0 | AU62: 8800 | AV62: =AU62*N62 -> 2694912 | AW62: =MAX(AM62,AT62,AV62) -> 6776274 | AX62: =CEILING((AW62),1000) -> 6777000 | AY62: 0.07 | AZ62: =AY62*AX62 -> 474390 | BA62: =CEILING(AZ62,100) -> 474400 | BB62: =BA62+AS62 -> 1171991 | BC62: =L62/J62% -> 0 | BD62: =O62/M62% -> 0 | BE62: 62.1 | BF62: 28.45 | BG62: 46176 | BH62: =BG62+30 -> 46206 | BI62: 7 | BL62: =VLOOKUP(A62,[2]Sheet1!$D$2:$H$933,5,0) -> 0 | BM62: UBPL M3M CAPITAL PHASE 2 MASTER ACCOUNT | BN62: 777705551661 | BO62: ICIC0000399 | BP62: ICICI Bank | BQ62: Shop No - 19, 20, Vipul Orchid Plaza, Suncity, Sector 54, Gurgaon, Haryana -122002 | BR62: Union Buildmart Private Limited | BS62: AABCU4843M | BT62: 41st Floor, Tower-1, M3M International Financial center, sector- 66,Gurugram, Haryana, India 122101 | BU62: (……………..)Village Chauma, Sector – 113, Gurugram, Manesar Urban Complex, GURGAON, HARYANA, INDIA PIN Code: 122017 | BV62: Feedback@m3mindia.com | BW62: 8068970077 | BX62: 0 | BY62: Vidhi Singh | BZ62: Sabhyata Kapoor
A63: R1 LG 09 | B63: M3M Capital Walk in M3M Capital Phase-2 | C63: cwBOOKING/00504/22-23 | D63: cwFLAP/00829/22-23 | E63: Ms. ABHA KALRA | F63: 44985 | G63: BLOCK-01 | H63: BASEMENT 2 | I63: Retail | J63: 668.44 | K63: 668.44 | L63: =K63-J63 -> 0 | M63: 306.24 | N63: 306.24 | O63: =N63-M63 -> 0 | P63: 26416.435 | Q63: 57660.012 | R63: 40000 | S63: 17657802 | T63: 2118938 | U63: =T63/S63 -> 0.1200001 | V63: =L63*P63 -> 0 | W63: =V63*U63 -> 0 | Z63: =S63+V63+X63 -> 17657802 | AA63: 1219680 | AB63: 146362 | AC63: =Z63-AA63 -> 16438122 | AD63: =AE63/M63 -> 300 | AE63: 91872 | AF63: 16536 | AG63: =(AD63*O63) -> 0 | AH63: =AG63*18% -> 0 | AI63: =AD63*N63 -> 91872 | AJ63: =ROUNDUP(AI63*18%,0) -> 16537 | AK63: 91872 | AL63: =N63*300 -> 91872 | AM63: =ROUND(AI63+AC63,0) -> 16529994 | AN63: =ROUNDUP(AJ63+W63+T63+Y63-AB63,0) -> 1989113 | AO63: =AN63+AL63+AR63 -> 2080985 | AP63: =AM63+AO63 -> 18610979 | AQ63: 15806141 | AR63: 0 | AS63: =ROUND(AP63-AQ63,0) -> 2804838 | AT63: 0 | AU63: 8800 | AV63: =AU63*N63 -> 2694912 | AW63: =MAX(AM63,AT63,AV63) -> 16529994 | AX63: =CEILING((AW63),1000) -> 16530000 | AY63: 0.05 | AZ63: =AY63*AX63 -> 826500 | BA63: =CEILING(AZ63,100) -> 826500 | BB63: =BA63+AS63 -> 3631338 | BC63: =L63/J63% -> 0 | BD63: =O63/M63% -> 0 | BE63: 62.1 | BF63: 28.45 | BG63: 46176 | BH63: =BG63+30 -> 46206 | BI63: 5 | BL63: =VLOOKUP(A63,[2]Sheet1!$D$2:$H$933,5,0) -> 0 | BM63: UBPL M3M CAPITAL PHASE 2 MASTER ACCOUNT | BN63: 777705551661 | BO63: ICIC0000399 | BP63: ICICI Bank | BQ63: Shop No - 19, 20, Vipul Orchid Plaza, Suncity, Sector 54, Gurgaon, Haryana -122002 | BR63: Union Buildmart Private Limited | BS63: AABCU4843M | BT63: 41st Floor, Tower-1, M3M International Financial center, sector- 66,Gurugram, Haryana, India 122101 | BU63: (……………..)Village Chauma, Sector – 113, Gurugram, Manesar Urban Complex, GURGAON, HARYANA, INDIA PIN Code: 122017 | BV63: Feedback@m3mindia.com | BW63: 8068970077 | BX63: 0 | BY63: Deepak chaubey | BZ63: Sabhyata Kapoor
A64: R1 LG 10 | B64: M3M Capital Walk in M3M Capital Phase-2 | C64: cwBOOKING/00772/22-23 | D64: cwFLAP/00660/22-23 | E64: Ms. ANITA TOKAS | F64: 45014 | G64: BLOCK-01 | H64: BASEMENT 2 | I64: Retail | J64: 1228.6 | K64: 1228.6 | L64: =K64-J64 -> 0 | M64: 567.8 | N64: 567.8 | O64: =N64-M64 -> 0 | P64: 15180 | Q64: 32846.333 | R64: 40000 | S64: 18650148 | T64: 2238018 | U64: =T64/S64 -> 0.12000001 | V64: =L64*P64 -> 0 | W64: =V64*U64 -> 0 | Z64: =S64+V64+X64 -> 18650148 | AA64: 1641643 | AB64: 196997 | AC64: =Z64-AA64 -> 17008505 | AD64: =AE64/M64 -> 300 | AE64: 170340 | AF64: 30662 | AG64: =(AD64*O64) -> 0 | AH64: =AG64*18% -> 0 | AI64: =AD64*N64 -> 170340 | AJ64: =ROUNDUP(AI64*18%,0) -> 30662 | AK64: 170340 | AL64: =N64*300 -> 170340 | AM64: =ROUND(AI64+AC64,0) -> 17178845 | AN64: =ROUNDUP(AJ64+W64+T64+Y64-AB64,0) -> 2071683 | AO64: =AN64+AL64+AR64 -> 2242023 | AP64: =AM64+AO64 -> 19420868 | AQ64: 18799348 | AR64: 0 | AS64: =ROUND(AP64-AQ64,0) -> 621520 | AT64: 0 | AU64: 8800 | AV64: =AU64*N64 -> 4996640 | AW64: =MAX(AM64,AT64,AV64) -> 17178845 | AX64: =CEILING((AW64),1000) -> 17179000 | AY64: 0.05 | AZ64: =AY64*AX64 -> 858950 | BA64: =CEILING(AZ64,100) -> 859000 | BB64: =BA64+AS64 -> 1480520 | BC64: =L64/J64% -> 0 | BD64: =O64/M64% -> 0 | BE64: 114.14 | BF64: 52.75 | BG64: 46176 | BH64: =BG64+30 -> 46206 | BI64: 5 | BJ64: Pre Payment | BL64: =VLOOKUP(A64,[2]Sheet1!$D$2:$H$933,5,0) -> 0 | BM64: UBPL M3M CAPITAL PHASE 2 MASTER ACCOUNT | BN64: 777705551661 | BO64: ICIC0000399 | BP64: ICICI Bank | BQ64: Shop No - 19, 20, Vipul Orchid Plaza, Suncity, Sector 54, Gurgaon, Haryana -122002 | BR64: Union Buildmart Private Limited | BS64: AABCU4843M | BT64: 41st Floor, Tower-1, M3M International Financial center, sector- 66,Gurugram, Haryana, India 122101 | BU64: (……………..)Village Chauma, Sector – 113, Gurugram, Manesar Urban Complex, GURGAON, HARYANA, INDIA PIN Code: 122017 | BV64: Feedback@m3mindia.com | BW64: 8068970077 | BY64: Sudhanshu Gurjar | BZ64: Sabhyata Kapoor
A65: R1 LG 23 | B65: M3M Capital Walk in M3M Capital Phase-2 | C65: cwBOOKING/00072/23-24 | D65: cwFLAP/01030/22-23 | E65: M/S. Praveensharma Infrabuild Private Limited | F65: 45046 | G65: BLOCK-01 | H65: BASEMENT 2 | I65: Retail | J65: 1472.52 | K65: 1472.52 | L65: =K65-J65 -> 0 | M65: 683.51 | N65: 683.51 | O65: =N65-M65 -> 0 | P65: 12500 | Q65: 26929.379 | R65: 40000 | S65: 18406500 | T65: 2208780 | U65: =T65/S65 -> 0.12 | V65: =L65*P65 -> 0 | W65: =V65*U65 -> 0 | Z65: =S65+V65+X65 -> 18406500 | AC65: =Z65-AA65 -> 18406500 | AD65: =AE65/M65 -> 300 | AE65: 205053 | AF65: 36910 | AG65: =(AD65*O65) -> 0 | AH65: =AG65*18% -> 0 | AI65: =AD65*N65 -> 205053 | AJ65: =ROUNDUP(AI65*18%,0) -> 36910 | AK65: 205053 | AL65: =N65*300 -> 205053 | AM65: =ROUND(AI65+AC65,0) -> 18611553 | AN65: =ROUNDUP(AJ65+W65+T65+Y65-AB65,0) -> 2245690 | AO65: =AN65+AL65+AR65 -> 2450743 | AP65: =AM65+AO65 -> 21062296 | AQ65: 18553752 | AR65: 0 | AS65: =ROUND(AP65-AQ65,0) -> 2508544 | AT65: 18406500 | AU65: 8800 | AV65: =AU65*N65 -> 6014888 | AW65: =MAX(AM65,AT65,AV65) -> 18611553 | AX65: =CEILING((AW65),1000) -> 18612000 | AY65: 0.07 | AZ65: =AY65*AX65 -> 1302840 | BA65: =CEILING(AZ65,100) -> 1302900 | BB65: =BA65+AS65 -> 3811444 | BC65: =L65/J65% -> 0 | BD65: =O65/M65% -> 0 | BE65: 136.8 | BF65: 63.5 | BG65: 46176 | BH65: =BG65+30 -> 46206 | BI65: 7 | BL65: =VLOOKUP(A65,[2]Sheet1!$D$2:$H$933,5,0) -> 0 | BM65: UBPL M3M CAPITAL PHASE 2 MASTER ACCOUNT | BN65: 777705551661 | BO65: ICIC0000399 | BP65: ICICI Bank | BQ65: Shop No - 19, 20, Vipul Orchid Plaza, Suncity, Sector 54, Gurgaon, Haryana -122002 | BR65: Union Buildmart Private Limited | BS65: AABCU4843M | BT65: 41st Floor, Tower-1, M3M International Financial center, sector- 66,Gurugram, Haryana, India 122101 | BU65: (……………..)Village Chauma, Sector – 113, Gurugram, Manesar Urban Complex, GURGAON, HARYANA, INDIA PIN Code: 122017 | BV65: Feedback@m3mindia.com | BW65: 8068970077 | BX65: 0 | BY65: Darshan Lal | BZ65: Sabhyata Kapoor
A66: R1 LG 28 | B66: M3M Capital Walk in M3M Capital Phase-2 | C66: cwBOOKING/00750/22-23 | D66: cwFLAP/00124/22-23 | E66: Mr. NEERAJ ARORA | F66: 45009 | G66: BLOCK-01 | H66: BASEMENT 2 | I66: Retail | J66: 729.8 | K66: 729.8 | L66: =K66-J66 -> 0 | M66: 322.92 | N66: 322.92 | O66: =N66-M66 -> 0 | P66: 24085 | Q66: 54432.16 | R66: 40000 | S66: 17577233 | T66: 2109268 | U66: =T66/S66 -> 0.12 | V66: =L66*P66 -> 0 | W66: =V66*U66 -> 0 | Z66: =S66+V66+X66 -> 17577233 | AA66: 1434758 | AB66: 172170 | AC66: =Z66-AA66 -> 16142475 | AD66: =AE66/M66 -> 300 | AE66: 96876 | AF66: 17438 | AG66: =(AD66*O66) -> 0 | AH66: =AG66*18% -> 0 | AI66: =AD66*N66 -> 96876 | AJ66: =ROUNDUP(AI66*18%,0) -> 17438 | AK66: 96876 | AL66: =N66*300 -> 96876 | AM66: =ROUND(AI66+AC66,0) -> 16239351 | AN66: =ROUNDUP(AJ66+W66+T66+Y66-AB66,0) -> 1954536 | AO66: =AN66+AL66+AR66 -> 2051412 | AP66: =AM66+AO66 -> 18290763 | AQ66: 16110924 | AR66: 0 | AS66: =ROUND(AP66-AQ66,0) -> 2179839 | AT66: 0 | AU66: 8800 | AV66: =AU66*N66 -> 2841696 | AW66: =MAX(AM66,AT66,AV66) -> 16239351 | AX66: =CEILING((AW66),1000) -> 16240000 | AY66: 0.07 | AZ66: =AY66*AX66 -> 1136800 | BA66: =CEILING(AZ66,100) -> 1136800 | BB66: =BA66+AS66 -> 3316639 | BC66: =L66/J66% -> 0 | BD66: =O66/M66% -> 0 | BE66: 67.8 | BF66: 30 | BG66: 46176 | BH66: =BG66+30 -> 46206 | BI66: 7 | BL66: =VLOOKUP(A66,[2]Sheet1!$D$2:$H$933,5,0) -> 0 | BM66: UBPL M3M CAPITAL PHASE 2 MASTER ACCOUNT | BN66: 777705551661 | BO66: ICIC0000399 | BP66: ICICI Bank | BQ66: Shop No - 19, 20, Vipul Orchid Plaza, Suncity, Sector 54, Gurgaon, Haryana -122002 | BR66: Union Buildmart Private Limited | BS66: AABCU4843M | BT66: 41st Floor, Tower-1, M3M International Financial center, sector- 66,Gurugram, Haryana, India 122101 | BU66: (……………..)Village Chauma, Sector – 113, Gurugram, Manesar Urban Complex, GURGAON, HARYANA, INDIA PIN Code: 122017 | BV66: Feedback@m3mindia.com | BW66: 8068970077 | BX66: 0 | BY66: Sudhanshu Gurjar | BZ66: Sabhyata Kapoor
A67: R1 UG 03 | B67: M3M Capital Walk in M3M Capital Phase-2 | C67: cwBOOKING/00712/22-23 | D67: cwFLAP/00954/22-23 | E67: Ms. SIMMI MAKKER | F67: 45006 | G67: BLOCK-01 | H67: BASEMENT 1 | I67: Retail | J67: 611.4 | K67: 611.4 | L67: =K67-J67 -> 0 | M67: 281.48 | N67: 281.48 | O67: =N67-M67 -> 0 | P67: 19903.291 | Q67: 43231.746 | R67: 28000 | S67: 12168872 | T67: 1460266 | U67: =T67/S67 -> 0.12000011 | V67: =L67*P67 -> 0 | W67: =V67*U67 -> 0 | Z67: =S67+V67+X67 -> 12168872 | AC67: =Z67-AA67 -> 12168872 | AD67: =AE67/M67 -> 300 | AE67: 84444 | AF67: 15200 | AG67: =(AD67*O67) -> 0 | AH67: =AG67*18% -> 0 | AI67: =AD67*N67 -> 84444 | AJ67: =ROUNDUP(AI67*18%,0) -> 15200 | AK67: 84444 | AL67: =N67*300 -> 84444 | AM67: =ROUND(AI67+AC67,0) -> 12253316 | AN67: =ROUNDUP(AJ67+W67+T67+Y67-AB67,0) -> 1475466 | AO67: =AN67+AL67+AR67 -> 1559910 | AP67: =AM67+AO67 -> 13813226 | AQ67: 11726328 | AR67: 0 | AS67: =ROUND(AP67-AQ67,0) -> 2086898 | AT67: 0 | AU67: 8800 | AV67: =AU67*N67 -> 2477024 | AW67: =MAX(AM67,AT67,AV67) -> 12253316 | AX67: =CEILING((AW67),1000) -> 12254000 | AY67: 0.05 | AZ67: =AY67*AX67 -> 612700 | BA67: =CEILING(AZ67,100) -> 612700 | BB67: =BA67+AS67 -> 2699598 | BC67: =L67/J67% -> 0 | BD67: =O67/M67% -> 0 | BE67: 56.8 | BF67: 26.15 | BG67: 46176 | BH67: =BG67+30 -> 46206 | BI67: 5 | BL67: =VLOOKUP(A67,[2]Sheet1!$D$2:$H$933,5,0) -> 0 | BM67: UBPL M3M CAPITAL PHASE 2 MASTER ACCOUNT | BN67: 777705551661 | BO67: ICIC0000399 | BP67: ICICI Bank | BQ67: Shop No - 19, 20, Vipul Orchid Plaza, Suncity, Sector 54, Gurgaon, Haryana -122002 | BR67: Union Buildmart Private Limited | BS67: AABCU4843M | BT67: 41st Floor, Tower-1, M3M International Financial center, sector- 66,Gurugram, Haryana, India 122101 | BU67: (……………..)Village Chauma, Sector – 113, Gurugram, Manesar Urban Complex, GURGAON, HARYANA, INDIA PIN Code: 122017 | BV67: Feedback@m3mindia.com | BW67: 8068970077 | BX67: 0 | BY67: Sonia Gupta | BZ67: Sabhyata Kapoor
A68: R1 UG 09 | B68: M3M Capital Walk in M3M Capital Phase-2 | C68: cwBOOKING/00708/22-23 | D68: cwFLAP/00943/22-23 | E68: Ms. KANCHANA CHAKRABORTY | F68: 45005 | G68: BLOCK-01 | H68: BASEMENT 1 | I68: Retail | J68: 611.4 | K68: 611.4 | L68: =K68-J68 -> 0 | M68: 281.48 | N68: 281.48 | O68: =N68-M68 -> 0 | P68: 20128.459 | Q68: 43720.833 | R68: 28000 | S68: 12306540 | T68: 1476784 | U68: =T68/S68 -> 0.11999993 | V68: =L68*P68 -> 0 | W68: =V68*U68 -> 0 | Z68: =S68+V68+X68 -> 12306540 | AA68: 1108011 | AB68: 132962 | AC68: =Z68-AA68 -> 11198529 | AD68: =AE68/M68 -> 300 | AE68: 84444 | AF68: 15200 | AG68: =(AD68*O68) -> 0 | AH68: =AG68*18% -> 0 | AI68: =AD68*N68 -> 84444 | AJ68: =ROUNDUP(AI68*18%,0) -> 15200 | AK68: 84444 | AL68: =N68*300 -> 84444 | AM68: =ROUND(AI68+AC68,0) -> 11282973 | AN68: =ROUNDUP(AJ68+W68+T68+Y68-AB68,0) -> 1359022 | AO68: =AN68+AL68+AR68 -> 1443466 | AP68: =AM68+AO68 -> 12726439 | AQ68: 11164019 | AR68: 0 | AS68: =ROUND(AP68-AQ68,0) -> 1562420 | AT68: 0 | AU68: 8800 | AV68: =AU68*N68 -> 2477024 | AW68: =MAX(AM68,AT68,AV68) -> 11282973 | AX68: =CEILING((AW68),1000) -> 11283000 | AY68: 0.06 | AZ68: =AY68*AX68 -> 676980 | BA68: =CEILING(AZ68,100) -> 677000 | BB68: =BA68+AS68 -> 2239420 | BC68: =L68/J68% -> 0 | BD68: =O68/M68% -> 0 | BE68: 56.8 | BF68: 26.15 | BG68: 46176 | BH68: =BG68+30 -> 46206 | BI68: 6 | BL68: =VLOOKUP(A68,[2]Sheet1!$D$2:$H$933,5,0) -> 0 | BM68: UBPL M3M CAPITAL PHASE 2 MASTER ACCOUNT | BN68: 777705551661 | BO68: ICIC0000399 | BP68: ICICI Bank | BQ68: Shop No - 19, 20, Vipul Orchid Plaza, Suncity, Sector 54, Gurgaon, Haryana -122002 | BR68: Union Buildmart Private Limited | BS68: AABCU4843M | BT68: 41st Floor, Tower-1, M3M International Financial center, sector- 66,Gurugram, Haryana, India 122101 | BU68: (……………..)Village Chauma, Sector – 113, Gurugram, Manesar Urban Complex, GURGAON, HARYANA, INDIA PIN Code: 122017 | BV68: Feedback@m3mindia.com | BW68: 8068970077 | BX68: 0 | BY68: Sudhanshu Gurjar | BZ68: Sabhyata Kapoor
A69: R1 UG 15 | B69: M3M Capital Walk in M3M Capital Phase-2 | C69: cwBOOKING/00529/22-23 | D69: cwFLAP/00547/22-23 | E69: Ms. MADHU SIKRI | F69: 44990 | G69: BLOCK-01 | H69: BASEMENT 1 | I69: Retail | J69: 585.56 | K69: 585.56 | L69: =K69-J69 -> 0 | M69: 272.33 | N69: 272.33 | O69: =N69-M69 -> 0 | P69: 14984 | Q69: 32218.378 | R69: 28000 | S69: 8774031 | T69: 1052882 | U69: =T69/S69 -> 0.1199998 | V69: =L69*P69 -> 0 | W69: =V69*U69 -> 0 | Z69: =S69+V69+X69 -> 8774031 | AC69: =Z69-AA69 -> 8774031 | AD69: =AE69/M69 -> 300 | AE69: 81699 | AF69: 14706 | AG69: =(AD69*O69) -> 0 | AH69: =AG69*18% -> 0 | AI69: =AD69*N69 -> 81699 | AJ69: =ROUNDUP(AI69*18%,0) -> 14706 | AK69: 81699 | AL69: =N69*300 -> 81699 | AM69: =ROUND(AI69+AC69,0) -> 8855730 | AN69: =ROUNDUP(AJ69+W69+T69+Y69-AB69,0) -> 1067588 | AO69: =AN69+AL69+AR69 -> 1149287 | AP69: =AM69+AO69 -> 10005017 | AQ69: 8844499 | AR69: 0 | AS69: =ROUND(AP69-AQ69,0) -> 1160518 | AT69: 0 | AU69: 8800 | AV69: =AU69*N69 -> 2396504 | AW69: =MAX(AM69,AT69,AV69) -> 8855730 | AX69: =CEILING((AW69),1000) -> 8856000 | AY69: 0.06 | AZ69: =AY69*AX69 -> 531360 | BA69: =CEILING(AZ69,100) -> 531400 | BB69: =BA69+AS69 -> 1691918 | BC69: =L69/J69% -> 0 | BD69: =O69/M69% -> 0 | BE69: 54.4 | BF69: 25.3 | BG69: 46176 | BH69: =BG69+30 -> 46206 | BI69: 6 | BL69: =VLOOKUP(A69,[2]Sheet1!$D$2:$H$933,5,0) -> 0 | BM69: UBPL M3M CAPITAL PHASE 2 MASTER ACCOUNT | BN69: 777705551661 | BO69: ICIC0000399 | BP69: ICICI Bank | BQ69: Shop No - 19, 20, Vipul Orchid Plaza, Suncity, Sector 54, Gurgaon, Haryana -122002 | BR69: Union Buildmart Private Limited | BS69: AABCU4843M | BT69: 41st Floor, Tower-1, M3M International Financial center, sector- 66,Gurugram, Haryana, India 122101 | BU69: (……………..)Village Chauma, Sector – 113, Gurugram, Manesar Urban Complex, GURGAON, HARYANA, INDIA PIN Code: 122017 | BV69: Feedback@m3mindia.com | BW69: 8068970077 | BX69: 0 | BY69: Deepak chaubey | BZ69: Sabhyata Kapoor
A70: R2 209 | B70: M3M Capital Walk in M3M Capital Phase-2 | C70: cwBOOKING/00184/23-24 | D70: cwFLAP/00067/23-24 | E70: Ms. HEMA PARESH DESAI | F70: 45111 | G70: BLOCK-02 | H70: FLOOR 2 | I70: Retail | J70: 1472.52 | K70: 1528 | L70: =K70-J70 -> 55.48 | M70: 666.29 | N70: 690 | O70: =N70-M70 -> 23.71 | P70: 6500.0014 | Q70: 14365.189 | R70: 20000 | S70: 9571382 | T70: 1148566 | U70: =T70/S70 -> 0.12000002 | V70: =L70*R70 -> 1109600 | W70: =V70*U70 -> 133152.02 | Z70: =S70+V70+X70 -> 10680982 | AA70: 3260693 | AB70: 391283 | AC70: =Z70-AA70 -> 7420289 | AD70: =AE70/M70 -> 300 | AE70: 199887 | AF70: 35980 | AG70: =(AD70*O70) -> 7113 | AH70: =AG70*18% -> 1280.34 | AI70: =AD70*N70 -> 207000 | AJ70: =ROUNDUP(AI70*18%,0) -> 37260 | AK70: 199887 | AL70: =N70*300 -> 207000 | AM70: =ROUND(AI70+AC70,0) -> 7627289 | AN70: =ROUNDUP(AJ70+W70+T70+Y70-AB70,0) -> 927696 | AO70: =AN70+AL70+AR70 -> 1134696 | AP70: =AM70+AO70 -> 8761985 | AQ70: 6538828.6 | AR70: 0 | AS70: =ROUND(AP70-AQ70,0) -> 2223156 | AT70: 0 | AU70: 8800 | AV70: =AU70*N70 -> 6072000 | AW70: =MAX(AM70,AT70,AV70) -> 7627289 | AX70: =CEILING((AW70),1000) -> 7628000 | AY70: 0.05 | AZ70: =AY70*AX70 -> 381400 | BA70: =CEILING(AZ70,100) -> 381400 | BB70: =BA70+AS70 -> 2604556 | BC70: =L70/J70% -> 3.7676908 | BD70: =O70/M70% -> 3.5585106 | BE70: 141.95 | BF70: 64.1 | BG70: 46176 | BH70: =BG70+30 -> 46206 | BI70: 5 | BJ70: Discount Manual | BL70: =VLOOKUP(A70,[2]Sheet1!$D$2:$H$933,5,0) -> 0 | BM70: UBPL M3M CAPITAL PHASE 2 MASTER ACCOUNT | BN70: 777705551661 | BO70: ICIC0000399 | BP70: ICICI Bank | BQ70: Shop No - 19, 20, Vipul Orchid Plaza, Suncity, Sector 54, Gurgaon, Haryana -122002 | BR70: Union Buildmart Private Limited | BS70: AABCU4843M | BT70: 41st Floor, Tower-1, M3M International Financial center, sector- 66,Gurugram, Haryana, India 122101 | BU70: (……………..)Village Chauma, Sector – 113, Gurugram, Manesar Urban Complex, GURGAON, HARYANA, INDIA PIN Code: 122017 | BV70: Feedback@m3mindia.com | BW70: 8068970077 | BX70: 0 | BY70: Manish Kumar | BZ70: Shubra
A71: R2 UG 01 | B71: M3M Capital Walk in M3M Capital Phase-2 | C71: cwBOOKING/00276/23-24 | D71: cwFLAP/00173/23-24 | E71: Mrs. DOLLY GOEL | F71: 45181 | G71: BLOCK-02 | H71: BASEMENT 1 | I71: Retail | J71: 946.16 | K71: 946.16 | L71: =K71-J71 -> 0 | M71: 441.97 | N71: 441.97 | O71: =N71-M71 -> 0 | P71: 12437.002 | Q71: 26624.87 | R71: 28000 | S71: 11767394 | T71: 1412086 | U71: =T71/S71 -> 0.11999989 | V71: =L71*P71 -> 0 | W71: =V71*U71 -> 0 | Z71: =S71+V71+X71 -> 11767394 | AC71: =Z71-AA71 -> 11767394 | AD71: =AE71/M71 -> 300 | AE71: 132591 | AF71: 23866 | AG71: =(AD71*O71) -> 0 | AH71: =AG71*18% -> 0 | AI71: =AD71*N71 -> 132591 | AJ71: =ROUNDUP(AI71*18%,0) -> 23867 | AK71: 132591 | AL71: =N71*300 -> 132591 | AM71: =ROUND(AI71+AC71,0) -> 11899985 | AN71: =ROUNDUP(AJ71+W71+T71+Y71-AB71,0) -> 1435953 | AO71: =AN71+AL71+AR71 -> 1568544 | AP71: =AM71+AO71 -> 13468529 | AQ71: 12520505 | AR71: 0 | AS71: =ROUND(AP71-AQ71,0) -> 948024 | AT71: 11992298 | AU71: 8800 | AV71: =AU71*N71 -> 3889336 | AW71: =MAX(AM71,AT71,AV71) -> 11992298 | AX71: =CEILING((AW71),1000) -> 11993000 | AY71: 0.05 | AZ71: =AY71*AX71 -> 599650 | BA71: =CEILING(AZ71,100) -> 599700 | BB71: =BA71+AS71 -> 1547724 | BC71: =L71/J71% -> 0 | BD71: =O71/M71% -> 0 | BE71: 87.9 | BF71: 41.06 | BG71: 46176 | BH71: =BG71+30 -> 46206 | BI71: 5 | BL71: =VLOOKUP(A71,[2]Sheet1!$D$2:$H$933,5,0) -> 0 | BM71: UBPL M3M CAPITAL PHASE 2 MASTER ACCOUNT | BN71: 777705551661 | BO71: ICIC0000399 | BP71: ICICI Bank | BQ71: Shop No - 19, 20, Vipul Orchid Plaza, Suncity, Sector 54, Gurgaon, Haryana -122002 | BR71: Union Buildmart Private Limited | BS71: AABCU4843M | BT71: 41st Floor, Tower-1, M3M International Financial center, sector- 66,Gurugram, Haryana, India 122101 | BU71: (……………..)Village Chauma, Sector – 113, Gurugram, Manesar Urban Complex, GURGAON, HARYANA, INDIA PIN Code: 122017 | BV71: Feedback@m3mindia.com | BW71: 8068970077 | BX71: 0 | BY71: Ritika Singh | BZ71: Shubra
A72: R2 UG 12 | B72: M3M Capital Walk in M3M Capital Phase-2 | C72: cwBOOKING/00175/22-23 | D72: cwFLAP/00283/22-23 | E72: Mrs. KAMLESH SOBTI | F72: 44901 | G72: BLOCK-02 | H72: BASEMENT 1 | I72: Retail | J72: 344.45 | K72: 344.45 | L72: =K72-J72 -> 0 | M72: 147.47 | N72: 147.47 | O72: =N72-M72 -> 0 | P72: 18535.999 | Q72: 43295.077 | R72: 28000 | S72: 6384725 | T72: 766166 | U72: =T72/S72 -> 0.11999984 | V72: =L72*P72 -> 0 | W72: =V72*U72 -> 0 | Z72: =S72+V72+X72 -> 6384725 | AA72: 861354 | AB72: 103362 | AC72: =Z72-AA72 -> 5523371 | AD72: =AE72/M72 -> 300 | AE72: 44241 | AF72: 7964 | AG72: =(AD72*O72) -> 0 | AH72: =AG72*18% -> 0 | AI72: =AD72*N72 -> 44241 | AJ72: =ROUNDUP(AI72*18%,0) -> 7964 | AK72: 44241 | AL72: =N72*300 -> 44241 | AM72: =ROUND(AI72+AC72,0) -> 5567612 | AN72: =ROUNDUP(AJ72+W72+T72+Y72-AB72,0) -> 670768 | AO72: =AN72+AL72+AR72 -> 715009 | AP72: =AM72+AO72 -> 6282621 | AQ72: 5503227.8 | AR72: 0 | AS72: =ROUND(AP72-AQ72,0) -> 779393 | AT72: 0 | AU72: 8800 | AV72: =AU72*N72 -> 1297736 | AW72: =MAX(AM72,AT72,AV72) -> 5567612 | AX72: =CEILING((AW72),1000) -> 5568000 | AY72: 0.05 | AZ72: =AY72*AX72 -> 278400 | BA72: =CEILING(AZ72,100) -> 278400 | BB72: =BA72+AS72 -> 1057793 | BC72: =L72/J72% -> 0 | BD72: =O72/M72% -> 0 | BE72: 32 | BF72: 13.7 | BG72: 46176 | BH72: =BG72+30 -> 46206 | BI72: 5 | BL72: =VLOOKUP(A72,[2]Sheet1!$D$2:$H$933,5,0) -> 0 | BM72: UBPL M3M CAPITAL PHASE 2 MASTER ACCOUNT | BN72: 777705551661 | BO72: ICIC0000399 | BP72: ICICI Bank | BQ72: Shop No - 19, 20, Vipul Orchid Plaza, Suncity, Sector 54, Gurgaon, Haryana -122002 | BR72: Union Buildmart Private Limited | BS72: AABCU4843M | BT72: 41st Floor, Tower-1, M3M International Financial center, sector- 66,Gurugram, Haryana, India 122101 | BU72: (……………..)Village Chauma, Sector – 113, Gurugram, Manesar Urban Complex, GURGAON, HARYANA, INDIA PIN Code: 122017 | BV72: Feedback@m3mindia.com | BW72: 8068970077 | BX72: 0 | BY72: Preeti Chauhan | BZ72: Shubra
A73: R3 LG 26 | B73: M3M Capital Walk in M3M Capital Phase-2 | C73: cwBOOKING/00470/22-23 | D73: cwFLAP/00442/22-23 | E73: Mr. MAHENDER SINGH | F73: 44970 | G73: BLOCK-03 | H73: BASEMENT 2 | I73: Anchor Units | J73: 201.17 | K73: 201.17 | L73: =K73-J73 -> 0 | M73: 75.89 | N73: 75.89 | O73: =N73-M73 -> 0 | P73: 12718 | Q73: 33713.006 | R73: 40000 | S73: 2558480 | T73: 307016 | U73: =T73/S73 -> 0.11999937 | V73: =L73*P73 -> 0 | W73: =V73*U73 -> 0 | Z73: =S73+V73+X73 -> 2558480 | AC73: =Z73-AA73 -> 2558480 | AD73: =AE73/M73 -> 300 | AE73: 22767 | AF73: 4098 | AG73: =(AD73*O73) -> 0 | AH73: =AG73*18% -> 0 | AI73: =AD73*N73 -> 22767 | AJ73: =ROUNDUP(AI73*18%,0) -> 4099 | AK73: 22767 | AL73: =N73*300 -> 22767 | AM73: =ROUND(AI73+AC73,0) -> 2581247 | AN73: =ROUNDUP(AJ73+W73+T73+Y73-AB73,0) -> 311115 | AO73: =AN73+AL73+AR73 -> 333882 | AP73: =AM73+AO73 -> 2915129 | AQ73: 2518917 | AR73: 0 | AS73: =ROUND(AP73-AQ73,0) -> 396212 | AT73: 0 | AU73: 8800 | AV73: =AU73*N73 -> 667832 | AW73: =MAX(AM73,AT73,AV73) -> 2581247 | AX73: =CEILING((AW73),1000) -> 2582000 | AY73: 0.07 | AZ73: =AY73*AX73 -> 180740 | BA73: =CEILING(AZ73,100) -> 180800 | BB73: =BA73+AS73 -> 577012 | BC73: =L73/J73% -> 0 | BD73: =O73/M73% -> 0 | BE73: 18.69 | BF73: 7.05 | BG73: 46176 | BH73: =BG73+30 -> 46206 | BI73: 7 | BL73: =VLOOKUP(A73,[2]Sheet1!$D$2:$H$933,5,0) -> 0 | BM73: UBPL M3M CAPITAL PHASE 2 MASTER ACCOUNT | BN73: 777705551661 | BO73: ICIC0000399 | BP73: ICICI Bank | BQ73: Shop No - 19, 20, Vipul Orchid Plaza, Suncity, Sector 54, Gurgaon, Haryana -122002 | BR73: Union Buildmart Private Limited | BS73: AABCU4843M | BT73: 41st Floor, Tower-1, M3M International Financial center, sector- 66,Gurugram, Haryana, India 122101 | BU73: (……………..)Village Chauma, Sector – 113, Gurugram, Manesar Urban Complex, GURGAON, HARYANA, INDIA PIN Code: 122017 | BV73: Feedback@m3mindia.com | BW73: 8068970077 | BX73: 0 | BY73: Deepak chaubey | BZ73: Sabhyata Kapoor
A74: R3 LG 33 | B74: M3M Capital Walk in M3M Capital Phase-2 | C74: cwBOOKING/00696/22-23 | D74: cwFLAP/00799/22-23 | E74: Ms. SANDEEP KAUR CHANNA | F74: 45002 | G74: BLOCK-03 | H74: BASEMENT 2 | I74: Anchor Units | J74: 220.06 | K74: 220.06 | L74: =K74-J74 -> 0 | M74: 88.26 | N74: 88.26 | O74: =N74-M74 -> 0 | P74: 17701.681 | Q74: 44135.871 | R74: 40000 | S74: 3895432 | T74: 467452 | U74: =T74/S74 -> 0.12000004 | V74: =L74*P74 -> 0 | W74: =V74*U74 -> 0 | Z74: =S74+V74+X74 -> 3895432 | AC74: =Z74-AA74 -> 3895432 | AD74: =AE74/M74 -> 300 | AE74: 26478 | AF74: 4766 | AG74: =(AD74*O74) -> 0 | AH74: =AG74*18% -> 0 | AI74: =AD74*N74 -> 26478 | AJ74: =ROUNDUP(AI74*18%,0) -> 4767 | AK74: 26478 | AL74: =N74*300 -> 26478 | AM74: =ROUND(AI74+AC74,0) -> 3921910 | AN74: =ROUNDUP(AJ74+W74+T74+Y74-AB74,0) -> 472219 | AO74: =AN74+AL74+AR74 -> 498697 | AP74: =AM74+AO74 -> 4420607 | AQ74: 3926595 | AR74: 0 | AS74: =ROUND(AP74-AQ74,0) -> 494012 | AT74: 0 | AU74: 8800 | AV74: =AU74*N74 -> 776688 | AW74: =MAX(AM74,AT74,AV74) -> 3921910 | AX74: =CEILING((AW74),1000) -> 3922000 | AY74: 0.05 | AZ74: =AY74*AX74 -> 196100 | BA74: =CEILING(AZ74,100) -> 196100 | BB74: =BA74+AS74 -> 690112 | BC74: =L74/J74% -> 0 | BD74: =O74/M74% -> 0 | BE74: 20.44 | BF74: 8.2 | BG74: 46176 | BH74: =BG74+30 -> 46206 | BI74: 5 | BL74: =VLOOKUP(A74,[2]Sheet1!$D$2:$H$933,5,0) -> 0 | BM74: UBPL M3M CAPITAL PHASE 2 MASTER ACCOUNT | BN74: 777705551661 | BO74: ICIC0000399 | BP74: ICICI Bank | BQ74: Shop No - 19, 20, Vipul Orchid Plaza, Suncity, Sector 54, Gurgaon, Haryana -122002 | BR74: Union Buildmart Private Limited | BS74: AABCU4843M | BT74: 41st Floor, Tower-1, M3M International Financial center, sector- 66,Gurugram, Haryana, India 122101 | BU74: (……………..)Village Chauma, Sector – 113, Gurugram, Manesar Urban Complex, GURGAON, HARYANA, INDIA PIN Code: 122017 | BV74: Feedback@m3mindia.com | BW74: 8068970077 | BX74: 0 | BY74: Sonia Gupta | BZ74: Sabhyata Kapoor
A75: R3 LG 43 | B75: M3M Capital Walk in M3M Capital Phase-2 | C75: cwBOOKING/00593/22-23 | D75: cwFLAP/00898/22-23 | E75: Mr. ANKUR JAIN | F75: 44995 | G75: BLOCK-03 | H75: BASEMENT 2 | I75: Anchor Units | J75: 220.06 | K75: 220.06 | L75: =K75-J75 -> 0 | M75: 88.26 | N75: 88.26 | O75: =N75-M75 -> 0 | P75: 10000 | Q75: 24933.152 | R75: 40000 | S75: 2200600 | T75: 264072 | U75: =T75/S75 -> 0.12 | V75: =L75*P75 -> 0 | W75: =V75*U75 -> 0 | Z75: =S75+V75+X75 -> 2200600 | AC75: =Z75-AA75 -> 2200600 | AD75: =AE75/M75 -> 300 | AE75: 26478 | AF75: 4766 | AG75: =(AD75*O75) -> 0 | AH75: =AG75*18% -> 0 | AI75: =AD75*N75 -> 26478 | AJ75: =ROUNDUP(AI75*18%,0) -> 4767 | AK75: 26478 | AL75: =N75*300 -> 26478 | AM75: =ROUND(AI75+AC75,0) -> 2227078 | AN75: =ROUNDUP(AJ75+W75+T75+Y75-AB75,0) -> 268839 | AO75: =AN75+AL75+AR75 -> 295317 | AP75: =AM75+AO75 -> 2522395 | AQ75: 2218204 | AR75: 0 | AS75: =ROUND(AP75-AQ75,0) -> 304191 | AT75: 0 | AU75: 8800 | AV75: =AU75*N75 -> 776688 | AW75: =MAX(AM75,AT75,AV75) -> 2227078 | AX75: =CEILING((AW75),1000) -> 2228000 | AY75: 0.07 | AZ75: =AY75*AX75 -> 155960 | BA75: =CEILING(AZ75,100) -> 156000 | BB75: =BA75+AS75 -> 460191 | BC75: =L75/J75% -> 0 | BD75: =O75/M75% -> 0 | BE75: 20.44 | BF75: 8.2 | BG75: 46176 | BH75: =BG75+30 -> 46206 | BI75: 7 | BL75: =VLOOKUP(A75,[2]Sheet1!$D$2:$H$933,5,0) -> 0 | BM75: UBPL M3M CAPITAL PHASE 2 MASTER ACCOUNT | BN75: 777705551661 | BO75: ICIC0000399 | BP75: ICICI Bank | BQ75: Shop No - 19, 20, Vipul Orchid Plaza, Suncity, Sector 54, Gurgaon, Haryana -122002 | BR75: Union Buildmart Private Limited | BS75: AABCU4843M | BT75: 41st Floor, Tower-1, M3M International Financial center, sector- 66,Gurugram, Haryana, India 122101 | BU75: (……………..)Village Chauma, Sector – 113, Gurugram, Manesar Urban Complex, GURGAON, HARYANA, INDIA PIN Code: 122017 | BV75: Feedback@m3mindia.com | BW75: 8068970077 | BX75: 0 | BY75: Deepak chaubey | BZ75: Sabhyata Kapoor
A76: R3 LG 57 | B76: M3M Capital Walk in M3M Capital Phase-2 | C76: cwBOOKING/00042/23-24 | D76: cwFLAP/01006/22-23 | E76: Mr. ISHWAR SINGH | F76: 45035 | G76: BLOCK-03 | H76: BASEMENT 2 | I76: Anchor Units | J76: 220.06 | K76: 220.06 | L76: =K76-J76 -> 0 | M76: 88.26 | N76: 88.26 | O76: =N76-M76 -> 0 | P76: 21700 | Q76: 54104.94 | R76: 40000 | S76: 4775302 | T76: 573036 | U76: =T76/S76 -> 0.11999995 | V76: =L76*P76 -> 0 | W76: =V76*U76 -> 0 | Z76: =S76+V76+X76 -> 4775302 | AC76: =Z76-AA76 -> 4775302 | AD76: =AE76/M76 -> 300 | AE76: 26478 | AF76: 4766 | AG76: =(AD76*O76) -> 0 | AH76: =AG76*18% -> 0 | AI76: =AD76*N76 -> 26478 | AJ76: =ROUNDUP(AI76*18%,0) -> 4767 | AK76: 26478 | AL76: =N76*300 -> 26478 | AM76: =ROUND(AI76+AC76,0) -> 4801780 | AN76: =ROUNDUP(AJ76+W76+T76+Y76-AB76,0) -> 577803 | AO76: =AN76+AL76+AR76 -> 604281 | AP76: =AM76+AO76 -> 5406061 | AQ76: 4813504 | AR76: 0 | AS76: =ROUND(AP76-AQ76,0) -> 592557 | AT76: 0 | AU76: 8800 | AV76: =AU76*N76 -> 776688 | AW76: =MAX(AM76,AT76,AV76) -> 4801780 | AX76: =CEILING((AW76),1000) -> 4802000 | AY76: 0.07 | AZ76: =AY76*AX76 -> 336140 | BA76: =CEILING(AZ76,100) -> 336200 | BB76: =BA76+AS76 -> 928757 | BC76: =L76/J76% -> 0 | BD76: =O76/M76% -> 0 | BE76: 20.44 | BF76: 8.2 | BG76: 46176 | BH76: =BG76+30 -> 46206 | BI76: 7 | BL76: =VLOOKUP(A76,[2]Sheet1!$D$2:$H$933,5,0) -> 0 | BM76: UBPL M3M CAPITAL PHASE 2 MASTER ACCOUNT | BN76: 777705551661 | BO76: ICIC0000399 | BP76: ICICI Bank | BQ76: Shop No - 19, 20, Vipul Orchid Plaza, Suncity, Sector 54, Gurgaon, Haryana -122002 | BR76: Union Buildmart Private Limited | BS76: AABCU4843M | BT76: 41st Floor, Tower-1, M3M International Financial center, sector- 66,Gurugram, Haryana, India 122101 | BU76: (……………..)Village Chauma, Sector – 113, Gurugram, Manesar Urban Complex, GURGAON, HARYANA, INDIA PIN Code: 122017 | BV76: Feedback@m3mindia.com | BW76: 8068970077 | BX76: 0 | BY76: Preeti Chauhan | BZ76: Sabhyata Kapoor
A77: R3 LG 73 | B77: M3M Capital Walk in M3M Capital Phase-2 | C77: cwBOOKING/00174/23-24 | D77: cwFLAP/00065/23-24 | E77: Mr. GAURAV DWIVEDI | F77: 45108 | G77: BLOCK-03 | H77: BASEMENT 2 | I77: Anchor Units | J77: 340.38 | K77: 340.38 | L77: =K77-J77 -> 0 | M77: 135.63 | N77: 135.63 | O77: =N77-M77 -> 0 | P77: 10000 | Q77: 25096.218 | R77: 40000 | S77: 3403800 | T77: 408456 | U77: =T77/S77 -> 0.12 | V77: =L77*P77 -> 0 | W77: =V77*U77 -> 0 | Z77: =S77+V77+X77 -> 3403800 | AC77: =Z77-AA77 -> 3403800 | AD77: =AE77/M77 -> 300 | AE77: 40689 | AF77: 7324 | AG77: =(AD77*O77) -> 0 | AH77: =AG77*18% -> 0 | AI77: =AD77*N77 -> 40689 | AJ77: =ROUNDUP(AI77*18%,0) -> 7325 | AK77: 40689 | AL77: =N77*300 -> 40689 | AM77: =ROUND(AI77+AC77,0) -> 3444489 | AN77: =ROUNDUP(AJ77+W77+T77+Y77-AB77,0) -> 415781 | AO77: =AN77+AL77+AR77 -> 456470 | AP77: =AM77+AO77 -> 3900959 | AQ77: 3431030 | AR77: 0 | AS77: =ROUND(AP77-AQ77,0) -> 469929 | AT77: 0 | AU77: 8800 | AV77: =AU77*N77 -> 1193544 | AW77: =MAX(AM77,AT77,AV77) -> 3444489 | AX77: =CEILING((AW77),1000) -> 3445000 | AY77: 0.07 | AZ77: =AY77*AX77 -> 241150 | BA77: =CEILING(AZ77,100) -> 241200 | BB77: =BA77+AS77 -> 711129 | BC77: =L77/J77% -> 0 | BD77: =O77/M77% -> 0 | BE77: 31.62 | BF77: 12.6 | BG77: 46176 | BH77: =BG77+30 -> 46206 | BI77: 7 | BL77: =VLOOKUP(A77,[2]Sheet1!$D$2:$H$933,5,0) -> 0 | BM77: UBPL M3M CAPITAL PHASE 2 MASTER ACCOUNT | BN77: 777705551661 | BO77: ICIC0000399 | BP77: ICICI Bank | BQ77: Shop No - 19, 20, Vipul Orchid Plaza, Suncity, Sector 54, Gurgaon, Haryana -122002 | BR77: Union Buildmart Private Limited | BS77: AABCU4843M | BT77: 41st Floor, Tower-1, M3M International Financial center, sector- 66,Gurugram, Haryana, India 122101 | BU77: (……………..)Village Chauma, Sector – 113, Gurugram, Manesar Urban Complex, GURGAON, HARYANA, INDIA PIN Code: 122017 | BV77: Feedback@m3mindia.com | BW77: 8068970077 | BX77: 0 | BY77: Chandrima | BZ77: Sabhyata Kapoor
A78: R3 UG 08 | B78: M3M Capital Walk in M3M Capital Phase-2 | C78: cwBOOKING/00244/23-24 | D78: cwFLAP/00115/23-24 | E78: M/S. Vishnu Kumar HUF | F78: 45149 | G78: BLOCK-03 | H78: BASEMENT 1 | I78: Retail | J78: 697.51 | K78: 697.51 | L78: =K78-J78 -> 0 | M78: 317.54 | N78: 317.54 | O78: =N78-M78 -> 0 | P78: 7000 | Q78: 15376.236 | R78: 28000 | S78: 4882570 | T78: 585908 | U78: =T78/S78 -> 0.11999992 | V78: =L78*P78 -> 0 | W78: =V78*U78 -> 0 | Z78: =S78+V78+X78 -> 4882570 | AC78: =Z78-AA78 -> 4882570 | AD78: =AE78/M78 -> 300 | AE78: 95262 | AF78: 17148 | AG78: =(AD78*O78) -> 0 | AH78: =AG78*18% -> 0 | AI78: =AD78*N78 -> 95262 | AJ78: =ROUNDUP(AI78*18%,0) -> 17148 | AK78: 95262 | AL78: =N78*300 -> 95262 | AM78: =ROUND(AI78+AC78,0) -> 4977832 | AN78: =ROUNDUP(AJ78+W78+T78+Y78-AB78,0) -> 603056 | AO78: =AN78+AL78+AR78 -> 698318 | AP78: =AM78+AO78 -> 5676150 | AQ78: 4921631 | AR78: 0 | AS78: =ROUND(AP78-AQ78,0) -> 754519 | AT78: 0 | AU78: 8800 | AV78: =AU78*N78 -> 2794352 | AW78: =MAX(AM78,AT78,AV78) -> 4977832 | AX78: =CEILING((AW78),1000) -> 4978000 | AY78: 0.07 | AZ78: =AY78*AX78 -> 348460 | BA78: =CEILING(AZ78,100) -> 348500 | BB78: =BA78+AS78 -> 1103019 | BC78: =L78/J78% -> 0 | BD78: =O78/M78% -> 0 | BE78: 64.8 | BF78: 29.5 | BG78: 46176 | BH78: =BG78+30 -> 46206 | BI78: 7 | BL78: =VLOOKUP(A78,[2]Sheet1!$D$2:$H$933,5,0) -> 0 | BM78: UBPL M3M CAPITAL PHASE 2 MASTER ACCOUNT | BN78: 777705551661 | BO78: ICIC0000399 | BP78: ICICI Bank | BQ78: Shop No - 19, 20, Vipul Orchid Plaza, Suncity, Sector 54, Gurgaon, Haryana -122002 | BR78: Union Buildmart Private Limited | BS78: AABCU4843M | BT78: 41st Floor, Tower-1, M3M International Financial center, sector- 66,Gurugram, Haryana, India 122101 | BU78: (……………..)Village Chauma, Sector – 113, Gurugram, Manesar Urban Complex, GURGAON, HARYANA, INDIA PIN Code: 122017 | BV78: Feedback@m3mindia.com | BW78: 8068970077 | BX78: 0 | BY78: Vidhi Singh | BZ78: Sabhyata Kapoor
A79: R3 UG 12A | B79: M3M Capital Walk in M3M Capital Phase-2 | C79: cwBOOKING/00732/22-23 | D79: cwFLAP/00823/22-23 | E79: Mr. JAI SHOKEEN | F79: 45008 | G79: BLOCK-03 | H79: BASEMENT 1 | I79: Retail | J79: 697.51 | K79: 697.51 | L79: =K79-J79 -> 0 | M79: 317.54 | N79: 317.54 | O79: =N79-M79 -> 0 | P79: 14700 | Q79: 32290.096 | R79: 28000 | S79: 10253397 | T79: 1230408 | U79: =T79/S79 -> 0.12000004 | V79: =L79*P79 -> 0 | W79: =V79*U79 -> 0 | Z79: =S79+V79+X79 -> 10253397 | AC79: =Z79-AA79 -> 10253397 | AD79: =AE79/M79 -> 300 | AE79: 95262 | AF79: 17148 | AG79: =(AD79*O79) -> 0 | AH79: =AG79*18% -> 0 | AI79: =AD79*N79 -> 95262 | AJ79: =ROUNDUP(AI79*18%,0) -> 17148 | AK79: 95262 | AL79: =N79*300 -> 95262 | AM79: =ROUND(AI79+AC79,0) -> 10348659 | AN79: =ROUNDUP(AJ79+W79+T79+Y79-AB79,0) -> 1247556 | AO79: =AN79+AL79+AR79 -> 1342818 | AP79: =AM79+AO79 -> 11691477 | AQ79: 10351292 | AR79: 0 | AS79: =ROUND(AP79-AQ79,0) -> 1340185 | AT79: 0 | AU79: 8800 | AV79: =AU79*N79 -> 2794352 | AW79: =MAX(AM79,AT79,AV79) -> 10348659 | AX79: =CEILING((AW79),1000) -> 10349000 | AY79: 0.07 | AZ79: =AY79*AX79 -> 724430 | BA79: =CEILING(AZ79,100) -> 724500 | BB79: =BA79+AS79 -> 2064685 | BC79: =L79/J79% -> 0 | BD79: =O79/M79% -> 0 | BE79: 64.8 | BF79: 29.5 | BG79: 46176 | BH79: =BG79+30 -> 46206 | BI79: 7 | BL79: =VLOOKUP(A79,[2]Sheet1!$D$2:$H$933,5,0) -> 0 | BM79: UBPL M3M CAPITAL PHASE 2 MASTER ACCOUNT | BN79: 777705551661 | BO79: ICIC0000399 | BP79: ICICI Bank | BQ79: Shop No - 19, 20, Vipul Orchid Plaza, Suncity, Sector 54, Gurgaon, Haryana -122002 | BR79: Union Buildmart Private Limited | BS79: AABCU4843M | BT79: 41st Floor, Tower-1, M3M International Financial center, sector- 66,Gurugram, Haryana, India 122101 | BU79: (……………..)Village Chauma, Sector – 113, Gurugram, Manesar Urban Complex, GURGAON, HARYANA, INDIA PIN Code: 122017 | BV79: Feedback@m3mindia.com | BW79: 8068970077 | BX79: 0 | BY79: Darshan Lal | BZ79: Sabhyata Kapoor
A80: R3 UG 28 | B80: M3M Capital Walk in M3M Capital Phase-2 | C80: cwBOOKING/00146/23-24 | D80: cwFLAP/00700/22-23 | E80: Ms. VEENA MALIK | F80: 45084 | G80: BLOCK-03 | H80: BASEMENT 1 | I80: Retail | J80: 697.51 | K80: 697.51 | L80: =K80-J80 -> 0 | M80: 317.54 | N80: 317.54 | O80: =N80-M80 -> 0 | P80: 20353.852 | Q80: 44709.375 | R80: 28000 | S80: 14197015 | T80: 1703642 | U80: =T80/S80 -> 0.12000001 | V80: =L80*P80 -> 0 | W80: =V80*U80 -> 0 | Z80: =S80+V80+X80 -> 14197015 | AA80: 737642 | AB80: 88518 | AC80: =Z80-AA80 -> 13459373 | AD80: =AE80/M80 -> 300 | AE80: 95262 | AF80: 17148 | AG80: =(AD80*O80) -> 0 | AH80: =AG80*18% -> 0 | AI80: =AD80*N80 -> 95262 | AJ80: =ROUNDUP(AI80*18%,0) -> 17148 | AK80: 95262 | AL80: =N80*300 -> 95262 | AM80: =ROUND(AI80+AC80,0) -> 13554635 | AN80: =ROUNDUP(AJ80+W80+T80+Y80-AB80,0) -> 1632272 | AO80: =AN80+AL80+AR80 -> 1727534 | AP80: =AM80+AO80 -> 15282169 | AQ80: 12798022 | AR80: 0 | AS80: =ROUND(AP80-AQ80,0) -> 2484147 | AT80: 0 | AU80: 8800 | AV80: =AU80*N80 -> 2794352 | AW80: =MAX(AM80,AT80,AV80) -> 13554635 | AX80: =CEILING((AW80),1000) -> 13555000 | AY80: 0.06 | AZ80: =AY80*AX80 -> 813300 | BA80: =CEILING(AZ80,100) -> 813300 | BB80: =BA80+AS80 -> 3297447 | BC80: =L80/J80% -> 0 | BD80: =O80/M80% -> 0 | BE80: 64.8 | BF80: 29.5 | BG80: 46176 | BH80: =BG80+30 -> 46206 | BI80: 6 | BL80: =VLOOKUP(A80,[2]Sheet1!$D$2:$H$933,5,0) -> 0 | BM80: UBPL M3M CAPITAL PHASE 2 MASTER ACCOUNT | BN80: 777705551661 | BO80: ICIC0000399 | BP80: ICICI Bank | BQ80: Shop No - 19, 20, Vipul Orchid Plaza, Suncity, Sector 54, Gurgaon, Haryana -122002 | BR80: Union Buildmart Private Limited | BS80: AABCU4843M | BT80: 41st Floor, Tower-1, M3M International Financial center, sector- 66,Gurugram, Haryana, India 122101 | BU80: (……………..)Village Chauma, Sector – 113, Gurugram, Manesar Urban Complex, GURGAON, HARYANA, INDIA PIN Code: 122017 | BV80: Feedback@m3mindia.com | BW80: 8068970077 | BX80: 0 | BY80: Ritika Singh | BZ80: Sabhyata Kapoor
A81: R3 UG 40 | B81: M3M Capital Walk in M3M Capital Phase-2 | C81: cwBOOKING/00024/22-23 | D81: cwFLAP/00045/22-23 | E81: Mr. MANDEEP YADAV | F81: 44863 | G81: BLOCK-03 | H81: BASEMENT 1 | I81: Retail | J81: 611.4 | K81: 611.4 | L81: =K81-J81 -> 0 | M81: 282.02 | N81: 282.02 | O81: =N81-M81 -> 0 | P81: 17815.851 | Q81: 38623.541 | R81: 28000 | S81: 10892611 | T81: 1307114 | U81: =T81/S81 -> 0.12000006 | V81: =L81*P81 -> 0 | W81: =V81*U81 -> 0 | Z81: =S81+V81+X81 -> 10892611 | AA81: 1880540 | AB81: 225665 | AC81: =Z81-AA81 -> 9012071 | AD81: =AE81/M81 -> 300 | AE81: 84606 | AF81: 15230 | AG81: =(AD81*O81) -> 0 | AH81: =AG81*18% -> 0 | AI81: =AD81*N81 -> 84606 | AJ81: =ROUNDUP(AI81*18%,0) -> 15230 | AK81: 84606 | AL81: =N81*300 -> 84606 | AM81: =ROUND(AI81+AC81,0) -> 9096677 | AN81: =ROUNDUP(AJ81+W81+T81+Y81-AB81,0) -> 1096679 | AO81: =AN81+AL81+AR81 -> 1181285 | AP81: =AM81+AO81 -> 10277962 | AQ81: 9000000 | AR81: 0 | AS81: =ROUND(AP81-AQ81,0) -> 1277962 | AT81: 0 | AU81: 8800 | AV81: =AU81*N81 -> 2481776 | AW81: =MAX(AM81,AT81,AV81) -> 9096677 | AX81: =CEILING((AW81),1000) -> 9097000 | AY81: 0.06 | AZ81: =AY81*AX81 -> 545820 | BA81: =CEILING(AZ81,100) -> 545900 | BB81: =BA81+AS81 -> 1823862 | BC81: =L81/J81% -> 0 | BD81: =O81/M81% -> 0 | BE81: 56.8 | BF81: 26.2 | BG81: 46176 | BH81: =BG81+30 -> 46206 | BI81: 6 | BJ81: Discount Manual | BL81: =VLOOKUP(A81,[2]Sheet1!$D$2:$H$933,5,0) -> 0 | BM81: UBPL M3M CAPITAL PHASE 2 MASTER ACCOUNT | BN81: 777705551661 | BO81: ICIC0000399 | BP81: ICICI Bank | BQ81: Shop No - 19, 20, Vipul Orchid Plaza, Suncity, Sector 54, Gurgaon, Haryana -122002 | BR81: Union Buildmart Private Limited | BS81: AABCU4843M | BT81: 41st Floor, Tower-1, M3M International Financial center, sector- 66,Gurugram, Haryana, India 122101 | BU81: (……………..)Village Chauma, Sector – 113, Gurugram, Manesar Urban Complex, GURGAON, HARYANA, INDIA PIN Code: 122017 | BV81: Feedback@m3mindia.com | BW81: 8068970077 | BX81: 0 | BY81: Darshan Lal | BZ81: Sabhyata Kapoor
A82: R3 UG 41 | B82: M3M Capital Walk in M3M Capital Phase-2 | C82: cwBOOKING/00477/22-23 | D82: cwFLAP/00777/22-23 | E82: Mr. ABHIJIT SINHA | F82: 44973 | G82: BLOCK-03 | H82: BASEMENT 1 | I82: Retail | J82: 542.94 | K82: 542.94 | L82: =K82-J82 -> 0 | M82: 240.04 | N82: 240.04 | O82: =N82-M82 -> 0 | P82: 25671 | Q82: 58064.543 | R82: 28000 | S82: 13937813 | T82: 1672538 | U82: =T82/S82 -> 0.12000003 | V82: =L82*P82 -> 0 | W82: =V82*U82 -> 0 | Z82: =S82+V82+X82 -> 13937813 | AA82: 903268 | AB82: 108392 | AC82: =Z82-AA82 -> 13034545 | AD82: =AE82/M82 -> 300 | AE82: 72012 | AF82: 12962 | AG82: =(AD82*O82) -> 0 | AH82: =AG82*18% -> 0 | AI82: =AD82*N82 -> 72012 | AJ82: =ROUNDUP(AI82*18%,0) -> 12963 | AK82: 72012 | AL82: =N82*300 -> 72012 | AM82: =ROUND(AI82+AC82,0) -> 13106557 | AN82: =ROUNDUP(AJ82+W82+T82+Y82-AB82,0) -> 1577109 | AO82: =AN82+AL82+AR82 -> 1649121 | AP82: =AM82+AO82 -> 14755678 | AQ82: 13037656 | AR82: 0 | AS82: =ROUND(AP82-AQ82,0) -> 1718022 | AT82: 0 | AU82: 8800 | AV82: =AU82*N82 -> 2112352 | AW82: =MAX(AM82,AT82,AV82) -> 13106557 | AX82: =CEILING((AW82),1000) -> 13107000 | AY82: 0.0634 | AZ82: =AY82*AX82 -> 830983.8 | BA82: =CEILING(AZ82,100) -> 831000 | BB82: =BA82+AS82 -> 2549022 | BC82: =L82/J82% -> 0 | BD82: =O82/M82% -> 0 | BE82: 50.44 | BF82: 22.3 | BG82: 46176 | BH82: =BG82+30 -> 46206 | BI82: 6.34 | BL82: =VLOOKUP(A82,[2]Sheet1!$D$2:$H$933,5,0) -> 0 | BM82: UBPL M3M CAPITAL PHASE 2 MASTER ACCOUNT | BN82: 777705551661 | BO82: ICIC0000399 | BP82: ICICI Bank | BQ82: Shop No - 19, 20, Vipul Orchid Plaza, Suncity, Sector 54, Gurgaon, Haryana -122002 | BR82: Union Buildmart Private Limited | BS82: AABCU4843M | BT82: 41st Floor, Tower-1, M3M International Financial center, sector- 66,Gurugram, Haryana, India 122101 | BU82: (……………..)Village Chauma, Sector – 113, Gurugram, Manesar Urban Complex, GURGAON, HARYANA, INDIA PIN Code: 122017 | BV82: Feedback@m3mindia.com | BW82: 8068970077 | BX82: 0 | BY82: Sudhanshu Gurjar | BZ82: Sabhyata Kapoor
A83: R4 104 | B83: M3M Capital Walk in M3M Capital Phase-2 | C83: cwBOOKING/00138/22-23 | D83: CCWFLAP/00010/22-23 | E83: Mr. MANOJ KUMAR SHARMA | F83: 44895 | G83: BLOCK-04 | H83: FLOOR 1 | I83: Retail | J83: 784.7 | K83: 784.7 | L83: =K83-J83 -> 0 | M83: 358.44 | N83: 358.44 | O83: =N83-M83 -> 0 | P83: 12000 | Q83: 26270.506 | R83: 22000 | S83: 9416400 | T83: 1129966 | U83: =T83/S83 -> 0.11999979 | V83: =L83*P83 -> 0 | W83: =V83*U83 -> 0 | Z83: =S83+V83+X83 -> 9416400 | AC83: =Z83-AA83 -> 9416400 | AD83: =AE83/M83 -> 300 | AE83: 107532 | AF83: 19356 | AG83: =(AD83*O83) -> 0 | AH83: =AG83*18% -> 0 | AI83: =AD83*N83 -> 107532 | AJ83: =ROUNDUP(AI83*18%,0) -> 19356 | AK83: 107532 | AL83: =N83*300 -> 107532 | AM83: =ROUND(AI83+AC83,0) -> 9523932 | AN83: =ROUNDUP(AJ83+W83+T83+Y83-AB83,0) -> 1149322 | AO83: =AN83+AL83+AR83 -> 1256854 | AP83: =AM83+AO83 -> 10780786 | AQ83: 7909774 | AR83: 0 | AS83: =ROUND(AP83-AQ83,0) -> 2871012 | AT83: 0 | AU83: 8800 | AV83: =AU83*N83 -> 3154272 | AW83: =MAX(AM83,AT83,AV83) -> 9523932 | AX83: =CEILING((AW83),1000) -> 9524000 | AY83: 0.07 | AZ83: =AY83*AX83 -> 666680 | BA83: =CEILING(AZ83,100) -> 666700 | BB83: =BA83+AS83 -> 3537712 | BC83: =L83/J83% -> 0 | BD83: =O83/M83% -> 0 | BE83: 72.9 | BF83: 33.3 | BG83: 46176 | BH83: =BG83+30 -> 46206 | BI83: 7 | BL83: =VLOOKUP(A83,[2]Sheet1!$D$2:$H$933,5,0) -> 0 | BM83: UBPL M3M CAPITAL PHASE 2 MASTER ACCOUNT | BN83: 777705551661 | BO83: ICIC0000399 | BP83: ICICI Bank | BQ83: Shop No - 19, 20, Vipul Orchid Plaza, Suncity, Sector 54, Gurgaon, Haryana -122002 | BR83: Union Buildmart Private Limited | BS83: AABCU4843M | BT83: 41st Floor, Tower-1, M3M International Financial center, sector- 66,Gurugram, Haryana, India 122101 | BU83: (……………..)Village Chauma, Sector – 113, Gurugram, Manesar Urban Complex, GURGAON, HARYANA, INDIA PIN Code: 122017 | BV83: Feedback@m3mindia.com | BW83: 8068970077 | BX83: 0 | BY83: Vidhi Singh | BZ83: Shubra
A84: R4 123 | B84: M3M Capital Walk in M3M Capital Phase-2 | C84: cwBOOKING/00646/22-23 | D84: cwFLAP/00627/22-23 | E84: Ms. Gurpreet Kaur Bhatia | F84: 44998 | G84: BLOCK-04 | H84: FLOOR 1 | I84: Retail | J84: 937.11 | K84: 937.11 | L84: =K84-J84 -> 0 | M84: 434.87 | N84: 434.87 | O84: =N84-M84 -> 0 | P84: 13252 | Q84: 28556.999 | R84: 22000 | S84: 12418582 | T84: 1490230 | U84: =T84/S84 -> 0.12000001 | V84: =L84*P84 -> 0 | W84: =V84*U84 -> 0 | Z84: =S84+V84+X84 -> 12418582 | AC84: =Z84-AA84 -> 12418582 | AD84: =AE84/M84 -> 300 | AE84: 130461 | AF84: 23482 | AG84: =(AD84*O84) -> 0 | AH84: =AG84*18% -> 0 | AI84: =AD84*N84 -> 130461 | AJ84: =ROUNDUP(AI84*18%,0) -> 23483 | AK84: 130461 | AL84: =N84*300 -> 130461 | AM84: =ROUND(AI84+AC84,0) -> 12549043 | AN84: =ROUNDUP(AJ84+W84+T84+Y84-AB84,0) -> 1513713 | AO84: =AN84+AL84+AR84 -> 1644174 | AP84: =AM84+AO84 -> 14193217 | AQ84: 12517932 | AR84: 0 | AS84: =ROUND(AP84-AQ84,0) -> 1675285 | AT84: 12418582 | AU84: 8800 | AV84: =AU84*N84 -> 3826856 | AW84: =MAX(AM84,AT84,AV84) -> 12549043 | AX84: =CEILING((AW84),1000) -> 12550000 | AY84: 0.05 | AZ84: =AY84*AX84 -> 627500 | BA84: =CEILING(AZ84,100) -> 627500 | BB84: =BA84+AS84 -> 2302785 | BC84: =L84/J84% -> 0 | BD84: =O84/M84% -> 0 | BE84: 87.06 | BF84: 40.4 | BG84: 46176 | BH84: =BG84+30 -> 46206 | BI84: 5 | BL84: =VLOOKUP(A84,[2]Sheet1!$D$2:$H$933,5,0) -> 0 | BM84: UBPL M3M CAPITAL PHASE 2 MASTER ACCOUNT | BN84: 777705551661 | BO84: ICIC0000399 | BP84: ICICI Bank | BQ84: Shop No - 19, 20, Vipul Orchid Plaza, Suncity, Sector 54, Gurgaon, Haryana -122002 | BR84: Union Buildmart Private Limited | BS84: AABCU4843M | BT84: 41st Floor, Tower-1, M3M International Financial center, sector- 66,Gurugram, Haryana, India 122101 | BU84: (……………..)Village Chauma, Sector – 113, Gurugram, Manesar Urban Complex, GURGAON, HARYANA, INDIA PIN Code: 122017 | BV84: Feedback@m3mindia.com | BW84: 8068970077 | BX84: 0 | BY84: Sonia Gupta | BZ84: Shubra
A85: R4 131 | B85: M3M Capital Walk in M3M Capital Phase-2 | C85: cwBOOKING/00297/22-23 | D85: cwFLAP/00377/22-23 | E85: Mr. PANKAJ SAINI | F85: 44907 | G85: BLOCK-04 | H85: FLOOR 1 | I85: Retail | J85: 815.91 | K85: 815.91 | L85: =K85-J85 -> 0 | M85: 375.66 | N85: 375.66 | O85: =N85-M85 -> 0 | P85: 12000 | Q85: 26063.249 | R85: 22000 | S85: 9790920 | T85: 1174914 | U85: =T85/S85 -> 0.12000037 | V85: =L85*P85 -> 0 | W85: =V85*U85 -> 0 | Z85: =S85+V85+X85 -> 9790920 | AC85: =Z85-AA85 -> 9790920 | AD85: =AE85/M85 -> 300 | AE85: 112698 | AF85: 20286 | AG85: =(AD85*O85) -> 0 | AH85: =AG85*18% -> 0 | AI85: =AD85*N85 -> 112698 | AJ85: =ROUNDUP(AI85*18%,0) -> 20286 | AK85: 112698 | AL85: =N85*300 -> 112698 | AM85: =ROUND(AI85+AC85,0) -> 9903618 | AN85: =ROUNDUP(AJ85+W85+T85+Y85-AB85,0) -> 1195200 | AO85: =AN85+AL85+AR85 -> 1307898 | AP85: =AM85+AO85 -> 11211516 | AQ85: 9869250 | AR85: 0 | AS85: =ROUND(AP85-AQ85,0) -> 1342266 | AT85: 0 | AU85: 8800 | AV85: =AU85*N85 -> 3305808 | AW85: =MAX(AM85,AT85,AV85) -> 9903618 | AX85: =CEILING((AW85),1000) -> 9904000 | AY85: 0.07 | AZ85: =AY85*AX85 -> 693280 | BA85: =CEILING(AZ85,100) -> 693300 | BB85: =BA85+AS85 -> 2035566 | BC85: =L85/J85% -> 0 | BD85: =O85/M85% -> 0 | BE85: 75.8 | BF85: 34.9 | BG85: 46176 | BH85: =BG85+30 -> 46206 | BI85: 7 | BL85: =VLOOKUP(A85,[2]Sheet1!$D$2:$H$933,5,0) -> 0 | BM85: UBPL M3M CAPITAL PHASE 2 MASTER ACCOUNT | BN85: 777705551661 | BO85: ICIC0000399 | BP85: ICICI Bank | BQ85: Shop No - 19, 20, Vipul Orchid Plaza, Suncity, Sector 54, Gurgaon, Haryana -122002 | BR85: Union Buildmart Private Limited | BS85: AABCU4843M | BT85: 41st Floor, Tower-1, M3M International Financial center, sector- 66,Gurugram, Haryana, India 122101 | BU85: (……………..)Village Chauma, Sector – 113, Gurugram, Manesar Urban Complex, GURGAON, HARYANA, INDIA PIN Code: 122017 | BV85: Feedback@m3mindia.com | BW85: 8068970077 | BX85: 0 | BY85: Sonia Gupta | BZ85: Shubra
A86: R4 137 | B86: M3M Capital Walk in M3M Capital Phase-2 | C86: cwBOOKING/00331/22-23 | D86: cwFLAP/00160/22-23 | E86: Mr. SURESH KUMAR ARORA | F86: 44925 | G86: BLOCK-04 | H86: FLOOR 1 | I86: Retail | J86: 504.83 | K86: 504.83 | L86: =K86-J86 -> 0 | M86: 234.12 | N86: 234.12 | O86: =N86-M86 -> 0 | P86: 12970 | Q86: 27967.047 | R86: 22000 | S86: 6547645 | T86: 785718 | U86: =T86/S86 -> 0.12000009 | V86: =L86*P86 -> 0 | W86: =V86*U86 -> 0 | Z86: =S86+V86+X86 -> 6547645 | AA86: 2142667 | AB86: 257120 | AC86: =Z86-AA86 -> 4404978 | AD86: =AE86/M86 -> 300 | AE86: 70236 | AF86: 12642 | AG86: =(AD86*O86) -> 0 | AH86: =AG86*18% -> 0 | AI86: =AD86*N86 -> 70236 | AJ86: =ROUNDUP(AI86*18%,0) -> 12643 | AK86: 70236 | AL86: =N86*300 -> 70236 | AM86: =ROUND(AI86+AC86,0) -> 4475214 | AN86: =ROUNDUP(AJ86+W86+T86+Y86-AB86,0) -> 541241 | AO86: =AN86+AL86+AR86 -> 611477 | AP86: =AM86+AO86 -> 5086691 | AQ86: 4200240 | AR86: 0 | AS86: =ROUND(AP86-AQ86,0) -> 886451 | AT86: 0 | AU86: 8800 | AV86: =AU86*N86 -> 2060256 | AW86: =MAX(AM86,AT86,AV86) -> 4475214 | AX86: =CEILING((AW86),1000) -> 4476000 | AY86: 0.07 | AZ86: =AY86*AX86 -> 313320 | BA86: =CEILING(AZ86,100) -> 313400 | BB86: =BA86+AS86 -> 1199851 | BC86: =L86/J86% -> 0 | BD86: =O86/M86% -> 0 | BE86: 46.9 | BF86: 21.75 | BG86: 46176 | BH86: =BG86+30 -> 46206 | BI86: 7 | BL86: =VLOOKUP(A86,[2]Sheet1!$D$2:$H$933,5,0) -> 0 | BM86: UBPL M3M CAPITAL PHASE 2 MASTER ACCOUNT | BN86: 777705551661 | BO86: ICIC0000399 | BP86: ICICI Bank | BQ86: Shop No - 19, 20, Vipul Orchid Plaza, Suncity, Sector 54, Gurgaon, Haryana -122002 | BR86: Union Buildmart Private Limited | BS86: AABCU4843M | BT86: 41st Floor, Tower-1, M3M International Financial center, sector- 66,Gurugram, Haryana, India 122101 | BU86: (……………..)Village Chauma, Sector – 113, Gurugram, Manesar Urban Complex, GURGAON, HARYANA, INDIA PIN Code: 122017 | BV86: Feedback@m3mindia.com | BW86: 8068970077 | BX86: 0 | BY86: Preeti Chauhan | BZ86: Shubra
A87: R4 144 | B87: M3M Capital Walk in M3M Capital Phase-2 | C87: cwBOOKING/00049/22-23 | D87: cwFLAP/00089/22-23 | E87: Mr. RAMESH KUMAR SINGH | F87: 44871 | G87: BLOCK-04 | H87: FLOOR 1 | I87: Retail | J87: 363.82 | K87: 363.82 | L87: =K87-J87 -> 0 | M87: 156.08 | N87: 156.08 | O87: =N87-M87 -> 0 | P87: 12000 | Q87: 27971.809 | R87: 22000 | S87: 4365840 | T87: 523902 | U87: =T87/S87 -> 0.12000027 | V87: =L87*P87 -> 0 | W87: =V87*U87 -> 0 | Z87: =S87+V87+X87 -> 4365840 | AA87: 731471 | AB87: 87776 | AC87: =Z87-AA87 -> 3634369 | AD87: =AE87/M87 -> 300 | AE87: 46824 | AF87: 8428 | AG87: =(AD87*O87) -> 0 | AH87: =AG87*18% -> 0 | AI87: =AD87*N87 -> 46824 | AJ87: =ROUNDUP(AI87*18%,0) -> 8429 | AK87: 46824 | AL87: =N87*300 -> 46824 | AM87: =ROUND(AI87+AC87,0) -> 3681193 | AN87: =ROUNDUP(AJ87+W87+T87+Y87-AB87,0) -> 444555 | AO87: =AN87+AL87+AR87 -> 491379 | AP87: =AM87+AO87 -> 4172572 | AQ87: 3581521 | AR87: 0 | AS87: =ROUND(AP87-AQ87,0) -> 591051 | AT87: 0 | AU87: 8800 | AV87: =AU87*N87 -> 1373504 | AW87: =MAX(AM87,AT87,AV87) -> 3681193 | AX87: =CEILING((AW87),1000) -> 3682000 | AY87: 0.07 | AZ87: =AY87*AX87 -> 257740 | BA87: =CEILING(AZ87,100) -> 257800 | BB87: =BA87+AS87 -> 848851 | BC87: =L87/J87% -> 0 | BD87: =O87/M87% -> 0 | BE87: 33.8 | BF87: 14.5 | BG87: 46176 | BH87: =BG87+30 -> 46206 | BI87: 7 | BL87: =VLOOKUP(A87,[2]Sheet1!$D$2:$H$933,5,0) -> 0 | BM87: UBPL M3M CAPITAL PHASE 2 MASTER ACCOUNT | BN87: 777705551661 | BO87: ICIC0000399 | BP87: ICICI Bank | BQ87: Shop No - 19, 20, Vipul Orchid Plaza, Suncity, Sector 54, Gurgaon, Haryana -122002 | BR87: Union Buildmart Private Limited | BS87: AABCU4843M | BT87: 41st Floor, Tower-1, M3M International Financial center, sector- 66,Gurugram, Haryana, India 122101 | BU87: (……………..)Village Chauma, Sector – 113, Gurugram, Manesar Urban Complex, GURGAON, HARYANA, INDIA PIN Code: 122017 | BV87: Feedback@m3mindia.com | BW87: 8068970077 | BX87: 0 | BY87: Darshan Lal | BZ87: Shubra
A88: R4 145 | B88: M3M Capital Walk in M3M Capital Phase-2 | C88: cwBOOKING/00048/22-23 | D88: cwFLAP/00088/22-23 | E88: Ms. SWETA KUMARI | F88: 44870 | G88: BLOCK-04 | H88: FLOOR 1 | I88: Retail | J88: 363.82 | K88: 363.82 | L88: =K88-J88 -> 0 | M88: 156.08 | N88: 156.08 | O88: =N88-M88 -> 0 | P88: 12000 | Q88: 27971.808 | R88: 22000 | S88: 4365839.9 | T88: 523902 | U88: =T88/S88 -> 0.12000028 | V88: =L88*P88 -> 0 | W88: =V88*U88 -> 0 | Z88: =S88+V88+X88 -> 4365839.9 | AA88: 732838 | AB88: 87940 | AC88: =Z88-AA88 -> 3633001.9 | AD88: =AE88/M88 -> 300 | AE88: 46824 | AF88: 8428 | AG88: =(AD88*O88) -> 0 | AH88: =AG88*18% -> 0 | AI88: =AD88*N88 -> 46824 | AJ88: =ROUNDUP(AI88*18%,0) -> 8429 | AK88: 46824 | AL88: =N88*300 -> 46824 | AM88: =ROUND(AI88+AC88,0) -> 3679826 | AN88: =ROUNDUP(AJ88+W88+T88+Y88-AB88,0) -> 444391 | AO88: =AN88+AL88+AR88 -> 491215 | AP88: =AM88+AO88 -> 4171041 | AQ88: 3579989 | AR88: 0 | AS88: =ROUND(AP88-AQ88,0) -> 591052 | AT88: 0 | AU88: 8800 | AV88: =AU88*N88 -> 1373504 | AW88: =MAX(AM88,AT88,AV88) -> 3679826 | AX88: =CEILING((AW88),1000) -> 3680000 | AY88: 0.05 | AZ88: =AY88*AX88 -> 184000 | BA88: =CEILING(AZ88,100) -> 184000 | BB88: =BA88+AS88 -> 775052 | BC88: =L88/J88% -> 0 | BD88: =O88/M88% -> 0 | BE88: 33.8 | BF88: 14.5 | BG88: 46176 | BH88: =BG88+30 -> 46206 | BI88: 5 | BL88: =VLOOKUP(A88,[2]Sheet1!$D$2:$H$933,5,0) -> 0 | BM88: UBPL M3M CAPITAL PHASE 2 MASTER ACCOUNT | BN88: 777705551661 | BO88: ICIC0000399 | BP88: ICICI Bank | BQ88: Shop No - 19, 20, Vipul Orchid Plaza, Suncity, Sector 54, Gurgaon, Haryana -122002 | BR88: Union Buildmart Private Limited | BS88: AABCU4843M | BT88: 41st Floor, Tower-1, M3M International Financial center, sector- 66,Gurugram, Haryana, India 122101 | BU88: (……………..)Village Chauma, Sector – 113, Gurugram, Manesar Urban Complex, GURGAON, HARYANA, INDIA PIN Code: 122017 | BV88: Feedback@m3mindia.com | BW88: 8068970077 | BX88: 0 | BY88: Darshan Lal | BZ88: Shubra
A89: R4 212A | B89: M3M Capital Walk in M3M Capital Phase-2 | C89: cwBOOKING/00326/22-23 | D89: cwFLAP/00166/22-23 | E89: Mrs. SUMAN JAIN | F89: 44924 | G89: BLOCK-04 | H89: FLOOR 2 | I89: Retail | J89: 945.08 | K89: 945.08 | L89: =K89-J89 -> 0 | M89: 425.18 | N89: 425.18 | O89: =N89-M89 -> 0 | P89: 9092.9995 | Q89: 20211.703 | R89: 20000 | S89: 8593612 | T89: 1031236 | U89: =T89/S89 -> 0.1200003 | V89: =L89*P89 -> 0 | W89: =V89*U89 -> 0 | Z89: =S89+V89+X89 -> 8593612 | AC89: =Z89-AA89 -> 8593612 | AD89: =AE89/M89 -> 300 | AE89: 127554 | AF89: 22960 | AG89: =(AD89*O89) -> 0 | AH89: =AG89*18% -> 0 | AI89: =AD89*N89 -> 127554 | AJ89: =ROUNDUP(AI89*18%,0) -> 22960 | AK89: 127554 | AL89: =N89*300 -> 127554 | AM89: =ROUND(AI89+AC89,0) -> 8721166 | AN89: =ROUNDUP(AJ89+W89+T89+Y89-AB89,0) -> 1054196 | AO89: =AN89+AL89+AR89 -> 1181750 | AP89: =AM89+AO89 -> 9902916 | AQ89: 8662363 | AR89: 0 | AS89: =ROUND(AP89-AQ89,0) -> 1240553 | AT89: 8593612 | AU89: 8800 | AV89: =AU89*N89 -> 3741584 | AW89: =MAX(AM89,AT89,AV89) -> 8721166 | AX89: =CEILING((AW89),1000) -> 8722000 | AY89: 0.0567 | AZ89: =AY89*AX89 -> 494537.4 | BA89: =CEILING(AZ89,100) -> 494600 | BB89: =BA89+AS89 -> 1735153 | BC89: =L89/J89% -> 0 | BD89: =O89/M89% -> 0 | BE89: 87.8 | BF89: 39.5 | BG89: 46176 | BH89: =BG89+30 -> 46206 | BI89: 5.67 | BL89: =VLOOKUP(A89,[2]Sheet1!$D$2:$H$933,5,0) -> 0 | BM89: UBPL M3M CAPITAL PHASE 2 MASTER ACCOUNT | BN89: 777705551661 | BO89: ICIC0000399 | BP89: ICICI Bank | BQ89: Shop No - 19, 20, Vipul Orchid Plaza, Suncity, Sector 54, Gurgaon, Haryana -122002 | BR89: Union Buildmart Private Limited | BS89: AABCU4843M | BT89: 41st Floor, Tower-1, M3M International Financial center, sector- 66,Gurugram, Haryana, India 122101 | BU89: (……………..)Village Chauma, Sector – 113, Gurugram, Manesar Urban Complex, GURGAON, HARYANA, INDIA PIN Code: 122017 | BV89: Feedback@m3mindia.com | BW89: 8068970077 | BX89: 0 | BY89: Sonia Gupta | BZ89: Shubra
A90: R4 219 | B90: M3M Capital Walk in M3M Capital Phase-2 | C90: cwBOOKING/00643/22-23 | D90: cwFLAP/00912/22-23 | E90: Ms. Madhu Saini | F90: 44998 | G90: BLOCK-04 | H90: FLOOR 2 | I90: Retail | J90: 652.3 | K90: 652.3 | L90: =K90-J90 -> 0 | M90: 293.86 | N90: 293.86 | O90: =N90-M90 -> 0 | P90: 7600.9995 | Q90: 16872.429 | R90: 20000 | S90: 4958132 | T90: 594978 | U90: =T90/S90 -> 0.12000044 | V90: =L90*P90 -> 0 | W90: =V90*U90 -> 0 | Z90: =S90+V90+X90 -> 4958132 | AC90: =Z90-AA90 -> 4958132 | AD90: =AE90/M90 -> 300 | AE90: 88158 | AF90: 15868 | AG90: =(AD90*O90) -> 0 | AH90: =AG90*18% -> 0 | AI90: =AD90*N90 -> 88158 | AJ90: =ROUNDUP(AI90*18%,0) -> 15869 | AK90: 88158 | AL90: =N90*300 -> 88158 | AM90: =ROUND(AI90+AC90,0) -> 5046290 | AN90: =ROUNDUP(AJ90+W90+T90+Y90-AB90,0) -> 610847 | AO90: =AN90+AL90+AR90 -> 699005 | AP90: =AM90+AO90 -> 5745295 | AQ90: 4997893 | AR90: 0 | AS90: =ROUND(AP90-AQ90,0) -> 747402 | AT90: 6261842 | AU90: 8800 | AV90: =AU90*N90 -> 2585968 | AW90: =MAX(AM90,AT90,AV90) -> 6261842 | AX90: =CEILING((AW90),1000) -> 6262000 | AY90: 0.05 | AZ90: =AY90*AX90 -> 313100 | BA90: =CEILING(AZ90,100) -> 313100 | BB90: =BA90+AS90 -> 1060502 | BC90: =L90/J90% -> 0 | BD90: =O90/M90% -> 0 | BE90: 60.6 | BF90: 27.3 | BG90: 46176 | BH90: =BG90+30 -> 46206 | BI90: 5 | BL90: =VLOOKUP(A90,[2]Sheet1!$D$2:$H$933,5,0) -> 0 | BM90: UBPL M3M CAPITAL PHASE 2 MASTER ACCOUNT | BN90: 777705551661 | BO90: ICIC0000399 | BP90: ICICI Bank | BQ90: Shop No - 19, 20, Vipul Orchid Plaza, Suncity, Sector 54, Gurgaon, Haryana -122002 | BR90: Union Buildmart Private Limited | BS90: AABCU4843M | BT90: 41st Floor, Tower-1, M3M International Financial center, sector- 66,Gurugram, Haryana, India 122101 | BU90: (……………..)Village Chauma, Sector – 113, Gurugram, Manesar Urban Complex, GURGAON, HARYANA, INDIA PIN Code: 122017 | BV90: Feedback@m3mindia.com | BW90: 8068970077 | BX90: 0 | BY90: Priya Anand | BZ90: Shubra
A91: R4 224 | B91: M3M Capital Walk in M3M Capital Phase-2 | C91: cwBOOKING/00084/22-23 | D91: cwFLAP/00219/22-23 | E91: Mr. SUSHIL MALIK | F91: 44886 | G91: BLOCK-04 | H91: FLOOR 2 | I91: Retail | J91: 556.5 | K91: 556.5 | L91: =K91-J91 -> 0 | M91: 257.26 | N91: 257.26 | O91: =N91-M91 -> 0 | P91: 8722.6307 | Q91: 18868.631 | R91: 20000 | S91: 4854144 | T91: 582498 | U91: =T91/S91 -> 0.12000015 | V91: =L91*P91 -> 0 | W91: =V91*U91 -> 0 | Z91: =S91+V91+X91 -> 4854144 | AA91: 6377 | AB91: 766 | AC91: =Z91-AA91 -> 4847767 | AD91: =AE91/M91 -> 300 | AE91: 77178 | AF91: 13892 | AG91: =(AD91*O91) -> 0 | AH91: =AG91*18% -> 0 | AI91: =AD91*N91 -> 77178 | AJ91: =ROUNDUP(AI91*18%,0) -> 13893 | AK91: 77178 | AL91: =N91*300 -> 77178 | AM91: =ROUND(AI91+AC91,0) -> 4924945 | AN91: =ROUNDUP(AJ91+W91+T91+Y91-AB91,0) -> 595625 | AO91: =AN91+AL91+AR91 -> 672803 | AP91: =AM91+AO91 -> 5597748 | AQ91: 4885836 | AR91: 0 | AS91: =ROUND(AP91-AQ91,0) -> 711912 | AT91: 0 | AU91: 8800 | AV91: =AU91*N91 -> 2263888 | AW91: =MAX(AM91,AT91,AV91) -> 4924945 | AX91: =CEILING((AW91),1000) -> 4925000 | AY91: 0.0567 | AZ91: =AY91*AX91 -> 279247.5 | BA91: =CEILING(AZ91,100) -> 279300 | BB91: =BA91+AS91 -> 991212 | BC91: =L91/J91% -> 0 | BD91: =O91/M91% -> 0 | BE91: 51.7 | BF91: 23.9 | BG91: 46176 | BH91: =BG91+30 -> 46206 | BI91: 5.67 | BL91: =VLOOKUP(A91,[2]Sheet1!$D$2:$H$933,5,0) -> 0 | BM91: UBPL M3M CAPITAL PHASE 2 MASTER ACCOUNT | BN91: 777705551661 | BO91: ICIC0000399 | BP91: ICICI Bank | BQ91: Shop No - 19, 20, Vipul Orchid Plaza, Suncity, Sector 54, Gurgaon, Haryana -122002 | BR91: Union Buildmart Private Limited | BS91: AABCU4843M | BT91: 41st Floor, Tower-1, M3M International Financial center, sector- 66,Gurugram, Haryana, India 122101 | BU91: (……………..)Village Chauma, Sector – 113, Gurugram, Manesar Urban Complex, GURGAON, HARYANA, INDIA PIN Code: 122017 | BV91: Feedback@m3mindia.com | BW91: 8068970077 | BX91: 0 | BY91: Priya Anand | BZ91: Shubra
A92: R4 228 | B92: M3M Capital Walk in M3M Capital Phase-2 | C92: cwBOOKING/00025/22-23 | D92: cwFLAP/00047/22-23 | E92: Ms. SAVITA SINGHAL | F92: 44863 | G92: BLOCK-04 | H92: FLOOR 2 | I92: Retail | J92: 541.21 | K92: 541.21 | L92: =K92-J92 -> 0 | M92: 241.11 | N92: 241.11 | O92: =N92-M92 -> 0 | P92: 6500 | Q92: 14590.291 | R92: 20000 | S92: 3517865 | T92: 422142 | U92: =T92/S92 -> 0.11999949 | V92: =L92*P92 -> 0 | W92: =V92*U92 -> 0 | Z92: =S92+V92+X92 -> 3517865 | AA92: 1008293 | AB92: 120996 | AC92: =Z92-AA92 -> 2509572 | AD92: =AE92/M92 -> 300 | AE92: 72333 | AF92: 13020 | AG92: =(AD92*O92) -> 0 | AH92: =AG92*18% -> 0 | AI92: =AD92*N92 -> 72333 | AJ92: =ROUNDUP(AI92*18%,0) -> 13020 | AK92: 72333 | AL92: =N92*300 -> 72333 | AM92: =ROUND(AI92+AC92,0) -> 2581905 | AN92: =ROUNDUP(AJ92+W92+T92+Y92-AB92,0) -> 314166 | AO92: =AN92+AL92+AR92 -> 386499 | AP92: =AM92+AO92 -> 2968404 | AQ92: 2416717 | AR92: 0 | AS92: =ROUND(AP92-AQ92,0) -> 551687 | AT92: 0 | AU92: 8800 | AV92: =AU92*N92 -> 2121768 | AW92: =MAX(AM92,AT92,AV92) -> 2581905 | AX92: =CEILING((AW92),1000) -> 2582000 | AY92: 0.05 | AZ92: =AY92*AX92 -> 129100 | BA92: =CEILING(AZ92,100) -> 129100 | BB92: =BA92+AS92 -> 680787 | BC92: =L92/J92% -> 0 | BD92: =O92/M92% -> 0 | BE92: 50.28 | BF92: 22.4 | BG92: 46176 | BH92: =BG92+30 -> 46206 | BI92: 5 | BL92: =VLOOKUP(A92,[2]Sheet1!$D$2:$H$933,5,0) -> 0 | BM92: UBPL M3M CAPITAL PHASE 2 MASTER ACCOUNT | BN92: 777705551661 | BO92: ICIC0000399 | BP92: ICICI Bank | BQ92: Shop No - 19, 20, Vipul Orchid Plaza, Suncity, Sector 54, Gurgaon, Haryana -122002 | BR92: Union Buildmart Private Limited | BS92: AABCU4843M | BT92: 41st Floor, Tower-1, M3M International Financial center, sector- 66,Gurugram, Haryana, India 122101 | BU92: (……………..)Village Chauma, Sector – 113, Gurugram, Manesar Urban Complex, GURGAON, HARYANA, INDIA PIN Code: 122017 | BV92: Feedback@m3mindia.com | BW92: 8068970077 | BX92: 0 | BY92: Preeti Chauhan | BZ92: Shubra
A93: R4 230 | B93: M3M Capital Walk in M3M Capital Phase-2 | C93: cwBOOKING/00130/22-23 | D93: cwFLAP/00153/22-23 | E93: Ms. ISHITA SINGHAL | F93: 44895 | G93: BLOCK-04 | H93: FLOOR 2 | I93: Retail | J93: 682.44 | K93: 682.44 | L93: =K93-J93 -> 0 | M93: 312.16 | N93: 312.16 | O93: =N93-M93 -> 0 | P93: 6889.2606 | Q93: 15061.209 | R93: 20000 | S93: 4701507 | T93: 564180 | U93: =T93/S93 -> 0.11999982 | V93: =L93*P93 -> 0 | W93: =V93*U93 -> 0 | Z93: =S93+V93+X93 -> 4701507 | AA93: 599581 | AB93: 71950 | AC93: =Z93-AA93 -> 4101926 | AD93: =AE93/M93 -> 300 | AE93: 93648 | AF93: 16856 | AG93: =(AD93*O93) -> 0 | AH93: =AG93*18% -> 0 | AI93: =AD93*N93 -> 93648 | AJ93: =ROUNDUP(AI93*18%,0) -> 16857 | AK93: 93648 | AL93: =N93*300 -> 93648 | AM93: =ROUND(AI93+AC93,0) -> 4195574 | AN93: =ROUNDUP(AJ93+W93+T93+Y93-AB93,0) -> 509087 | AO93: =AN93+AL93+AR93 -> 602735 | AP93: =AM93+AO93 -> 4798309 | AQ93: 3601289 | AR93: 0 | AS93: =ROUND(AP93-AQ93,0) -> 1197020 | AT93: 0 | AU93: 8800 | AV93: =AU93*N93 -> 2747008 | AW93: =MAX(AM93,AT93,AV93) -> 4195574 | AX93: =CEILING((AW93),1000) -> 4196000 | AY93: 0.06 | AZ93: =AY93*AX93 -> 251760 | BA93: =CEILING(AZ93,100) -> 251800 | BB93: =BA93+AS93 -> 1448820 | BC93: =L93/J93% -> 0 | BD93: =O93/M93% -> 0 | BE93: 63.4 | BF93: 29 | BG93: 46176 | BH93: =BG93+30 -> 46206 | BI93: 6 | BL93: =VLOOKUP(A93,[2]Sheet1!$D$2:$H$933,5,0) -> 0 | BM93: UBPL M3M CAPITAL PHASE 2 MASTER ACCOUNT | BN93: 777705551661 | BO93: ICIC0000399 | BP93: ICICI Bank | BQ93: Shop No - 19, 20, Vipul Orchid Plaza, Suncity, Sector 54, Gurgaon, Haryana -122002 | BR93: Union Buildmart Private Limited | BS93: AABCU4843M | BT93: 41st Floor, Tower-1, M3M International Financial center, sector- 66,Gurugram, Haryana, India 122101 | BU93: (……………..)Village Chauma, Sector – 113, Gurugram, Manesar Urban Complex, GURGAON, HARYANA, INDIA PIN Code: 122017 | BV93: Feedback@m3mindia.com | BW93: 8068970077 | BX93: 0 | BY93: Priya Anand | BZ93: Shubra
A94: R4 233 | B94: M3M Capital Walk in M3M Capital Phase-2 | C94: cwBOOKING/00202/22-23 | D94: cwFLAP/00358/22-23 | E94: Ms. PRABHATI VARMA | F94: 44896 | G94: BLOCK-04 | H94: FLOOR 2 | I94: Retail | J94: 556.5 | K94: 556.5 | L94: =K94-J94 -> 0 | M94: 257.26 | N94: 257.26 | O94: =N94-M94 -> 0 | P94: 15750 | Q94: 34070.104 | R94: 20000 | S94: 8764875 | T94: 1051784 | U94: =T94/S94 -> 0.11999989 | V94: =L94*P94 -> 0 | W94: =V94*U94 -> 0 | Z94: =S94+V94+X94 -> 8764875 | AC94: =Z94-AA94 -> 8764875 | AD94: =AE94/M94 -> 300 | AE94: 77178 | AF94: 13892 | AG94: =(AD94*O94) -> 0 | AH94: =AG94*18% -> 0 | AI94: =AD94*N94 -> 77178 | AJ94: =ROUNDUP(AI94*18%,0) -> 13893 | AK94: 77178 | AL94: =N94*300 -> 77178 | AM94: =ROUND(AI94+AC94,0) -> 8842053 | AN94: =ROUNDUP(AJ94+W94+T94+Y94-AB94,0) -> 1065677 | AO94: =AN94+AL94+AR94 -> 1142855 | AP94: =AM94+AO94 -> 9984908 | AQ94: 8834995 | AR94: 0 | AS94: =ROUND(AP94-AQ94,0) -> 1149913 | AT94: 0 | AU94: 8800 | AV94: =AU94*N94 -> 2263888 | AW94: =MAX(AM94,AT94,AV94) -> 8842053 | AX94: =CEILING((AW94),1000) -> 8843000 | AY94: 0.06 | AZ94: =AY94*AX94 -> 530580 | BA94: =CEILING(AZ94,100) -> 530600 | BB94: =BA94+AS94 -> 1680513 | BC94: =L94/J94% -> 0 | BD94: =O94/M94% -> 0 | BE94: 51.7 | BF94: 23.9 | BG94: 46176 | BH94: =BG94+30 -> 46206 | BI94: 6 | BL94: =VLOOKUP(A94,[2]Sheet1!$D$2:$H$933,5,0) -> 0 | BM94: UBPL M3M CAPITAL PHASE 2 MASTER ACCOUNT | BN94: 777705551661 | BO94: ICIC0000399 | BP94: ICICI Bank | BQ94: Shop No - 19, 20, Vipul Orchid Plaza, Suncity, Sector 54, Gurgaon, Haryana -122002 | BR94: Union Buildmart Private Limited | BS94: AABCU4843M | BT94: 41st Floor, Tower-1, M3M International Financial center, sector- 66,Gurugram, Haryana, India 122101 | BU94: (……………..)Village Chauma, Sector – 113, Gurugram, Manesar Urban Complex, GURGAON, HARYANA, INDIA PIN Code: 122017 | BV94: Feedback@m3mindia.com | BW94: 8068970077 | BX94: 0 | BY94: Sudhanshu Gurjar | BZ94: Shubra
A95: R4 235 | B95: M3M Capital Walk in M3M Capital Phase-2 | C95: cwBOOKING/00011/23-24 | D95: cwFLAP/00521/22-23 | E95: Mr. SATISH CHANDER SAROHA | F95: 45020 | G95: BLOCK-04 | H95: FLOOR 2 | I95: Retail | J95: 556.5 | K95: 556.5 | L95: =K95-J95 -> 0 | M95: 257.26 | N95: 257.26 | O95: =N95-M95 -> 0 | P95: 9980.4798 | Q95: 21589.586 | R95: 20000 | S95: 5554137 | T95: 666496 | U95: =T95/S95 -> 0.11999992 | V95: =L95*P95 -> 0 | W95: =V95*U95 -> 0 | Z95: =S95+V95+X95 -> 5554137 | AA95: 1106828 | AB95: 132820 | AC95: =Z95-AA95 -> 4447309 | AD95: =AE95/M95 -> 300 | AE95: 77178 | AF95: 13892 | AG95: =(AD95*O95) -> 0 | AH95: =AG95*18% -> 0 | AI95: =AD95*N95 -> 77178 | AJ95: =ROUNDUP(AI95*18%,0) -> 13893 | AK95: 77178 | AL95: =N95*300 -> 77178 | AM95: =ROUND(AI95+AC95,0) -> 4524487 | AN95: =ROUNDUP(AJ95+W95+T95+Y95-AB95,0) -> 547569 | AO95: =AN95+AL95+AR95 -> 624747 | AP95: =AM95+AO95 -> 5149234 | AQ95: 4072868 | AR95: 0 | AS95: =ROUND(AP95-AQ95,0) -> 1076366 | AT95: 0 | AU95: 8800 | AV95: =AU95*N95 -> 2263888 | AW95: =MAX(AM95,AT95,AV95) -> 4524487 | AX95: =CEILING((AW95),1000) -> 4525000 | AY95: 0.07 | AZ95: =AY95*AX95 -> 316750 | BA95: =CEILING(AZ95,100) -> 316800 | BB95: =BA95+AS95 -> 1393166 | BC95: =L95/J95% -> 0 | BD95: =O95/M95% -> 0 | BE95: 51.7 | BF95: 23.9 | BG95: 46176 | BH95: =BG95+30 -> 46206 | BI95: 7 | BL95: =VLOOKUP(A95,[2]Sheet1!$D$2:$H$933,5,0) -> 0 | BM95: UBPL M3M CAPITAL PHASE 2 MASTER ACCOUNT | BN95: 777705551661 | BO95: ICIC0000399 | BP95: ICICI Bank | BQ95: Shop No - 19, 20, Vipul Orchid Plaza, Suncity, Sector 54, Gurgaon, Haryana -122002 | BR95: Union Buildmart Private Limited | BS95: AABCU4843M | BT95: 41st Floor, Tower-1, M3M International Financial center, sector- 66,Gurugram, Haryana, India 122101 | BU95: (……………..)Village Chauma, Sector – 113, Gurugram, Manesar Urban Complex, GURGAON, HARYANA, INDIA PIN Code: 122017 | BV95: Feedback@m3mindia.com | BW95: 8068970077 | BX95: 0 | BY95: Darshan Lal | BZ95: Shubra
A96: R4 236 | B96: M3M Capital Walk in M3M Capital Phase-2 | C96: cwBOOKING/00127/22-23 | D96: cwFLAP/00287/22-23 | E96: Mr. MUKESH KUMAR | F96: 44895 | G96: BLOCK-04 | H96: FLOOR 2 | I96: Retail | J96: 556.5 | K96: 556.5 | L96: =K96-J96 -> 0 | M96: 257.26 | N96: 257.26 | O96: =N96-M96 -> 0 | P96: 9000 | Q96: 19468.631 | R96: 20000 | S96: 5008500 | T96: 601020 | U96: =T96/S96 -> 0.12 | V96: =L96*P96 -> 0 | W96: =V96*U96 -> 0 | Z96: =S96+V96+X96 -> 5008500 | AA96: 603703 | AB96: 72444 | AC96: =Z96-AA96 -> 4404797 | AD96: =AE96/M96 -> 300 | AE96: 77178 | AF96: 13892 | AG96: =(AD96*O96) -> 0 | AH96: =AG96*18% -> 0 | AI96: =AD96*N96 -> 77178 | AJ96: =ROUNDUP(AI96*18%,0) -> 13893 | AK96: 77178 | AL96: =N96*300 -> 77178 | AM96: =ROUND(AI96+AC96,0) -> 4481975 | AN96: =ROUNDUP(AJ96+W96+T96+Y96-AB96,0) -> 542469 | AO96: =AN96+AL96+AR96 -> 619647 | AP96: =AM96+AO96 -> 5101622 | AQ96: 4532447 | AR96: 0 | AS96: =ROUND(AP96-AQ96,0) -> 569175 | AT96: 0 | AU96: 8800 | AV96: =AU96*N96 -> 2263888 | AW96: =MAX(AM96,AT96,AV96) -> 4481975 | AX96: =CEILING((AW96),1000) -> 4482000 | AY96: 0.07 | AZ96: =AY96*AX96 -> 313740 | BA96: =CEILING(AZ96,100) -> 313800 | BB96: =BA96+AS96 -> 882975 | BC96: =L96/J96% -> 0 | BD96: =O96/M96% -> 0 | BE96: 51.7 | BF96: 23.9 | BG96: 46176 | BH96: =BG96+30 -> 46206 | BI96: 7 | BL96: =VLOOKUP(A96,[2]Sheet1!$D$2:$H$933,5,0) -> 0 | BM96: UBPL M3M CAPITAL PHASE 2 MASTER ACCOUNT | BN96: 777705551661 | BO96: ICIC0000399 | BP96: ICICI Bank | BQ96: Shop No - 19, 20, Vipul Orchid Plaza, Suncity, Sector 54, Gurgaon, Haryana -122002 | BR96: Union Buildmart Private Limited | BS96: AABCU4843M | BT96: 41st Floor, Tower-1, M3M International Financial center, sector- 66,Gurugram, Haryana, India 122101 | BU96: (……………..)Village Chauma, Sector – 113, Gurugram, Manesar Urban Complex, GURGAON, HARYANA, INDIA PIN Code: 122017 | BV96: Feedback@m3mindia.com | BW96: 8068970077 | BX96: 0 | BY96: Preeti Chauhan | BZ96: Shubra
A97: R4 238 | B97: M3M Capital Walk in M3M Capital Phase-2 | C97: cwBOOKING/00196/22-23 | D97: cwFLAP/00071/22-23 | E97: Mr. SEELAM SINGH TYAGI | F97: 44896 | G97: BLOCK-04 | H97: FLOOR 2 | I97: Retail | J97: 424.1 | K97: 424.1 | L97: =K97-J97 -> 0 | M97: 186.76 | N97: 186.76 | O97: =N97-M97 -> 0 | P97: 9000 | Q97: 20437.46 | R97: 20000 | S97: 3816900 | T97: 458028 | U97: =T97/S97 -> 0.12 | V97: =L97*P97 -> 0 | W97: =V97*U97 -> 0 | Z97: =S97+V97+X97 -> 3816900 | AA97: 436883 | AB97: 52426 | AC97: =Z97-AA97 -> 3380017 | AD97: =AE97/M97 -> 300 | AE97: 56028 | AF97: 10086 | AG97: =(AD97*O97) -> 0 | AH97: =AG97*18% -> 0 | AI97: =AD97*N97 -> 56028 | AJ97: =ROUNDUP(AI97*18%,0) -> 10086 | AK97: 56028 | AL97: =N97*300 -> 56028 | AM97: =ROUND(AI97+AC97,0) -> 3436045 | AN97: =ROUNDUP(AJ97+W97+T97+Y97-AB97,0) -> 415688 | AO97: =AN97+AL97+AR97 -> 471716 | AP97: =AM97+AO97 -> 3907761 | AQ97: 3506696 | AR97: 0 | AS97: =ROUND(AP97-AQ97,0) -> 401065 | AT97: 0 | AU97: 8800 | AV97: =AU97*N97 -> 1643488 | AW97: =MAX(AM97,AT97,AV97) -> 3436045 | AX97: =CEILING((AW97),1000) -> 3437000 | AY97: 0.06 | AZ97: =AY97*AX97 -> 206220 | BA97: =CEILING(AZ97,100) -> 206300 | BB97: =BA97+AS97 -> 607365 | BC97: =L97/J97% -> 0 | BD97: =O97/M97% -> 0 | BE97: 39.4 | BF97: 17.35 | BG97: 46176 | BH97: =BG97+30 -> 46206 | BI97: 6 | BL97: =VLOOKUP(A97,[2]Sheet1!$D$2:$H$933,5,0) -> 0 | BM97: UBPL M3M CAPITAL PHASE 2 MASTER ACCOUNT | BN97: 777705551661 | BO97: ICIC0000399 | BP97: ICICI Bank | BQ97: Shop No - 19, 20, Vipul Orchid Plaza, Suncity, Sector 54, Gurgaon, Haryana -122002 | BR97: Union Buildmart Private Limited | BS97: AABCU4843M | BT97: 41st Floor, Tower-1, M3M International Financial center, sector- 66,Gurugram, Haryana, India 122101 | BU97: (……………..)Village Chauma, Sector – 113, Gurugram, Manesar Urban Complex, GURGAON, HARYANA, INDIA PIN Code: 122017 | BV97: Feedback@m3mindia.com | BW97: 8068970077 | BX97: 0 | BY97: Sonia Gupta | BZ97: Shubra
A98: R4 242 | B98: M3M Capital Walk in M3M Capital Phase-2 | C98: cwBOOKING/00285/23-24 | D98: cwFLAP/00183/23-24 | E98: Mr. Sunil Kumanna Chougule | F98: 45216 | G98: BLOCK-04 | H98: FLOOR 2 | I98: Retail | J98: 991.58 | K98: 991.58 | L98: =K98-J98 -> 0 | M98: 453.06 | N98: 453.06 | O98: =N98-M98 -> 0 | P98: 9999.998 | Q98: 21886.28 | R98: 20000 | S98: 9915798 | T98: 1189896 | U98: =T98/S98 -> 0.12000002 | V98: =L98*P98 -> 0 | W98: =V98*U98 -> 0 | Z98: =S98+V98+X98 -> 9915798 | AC98: =Z98-AA98 -> 9915798 | AD98: =AE98/M98 -> 300 | AE98: 135918 | AF98: 24466 | AG98: =(AD98*O98) -> 0 | AH98: =AG98*18% -> 0 | AI98: =AD98*N98 -> 135918 | AJ98: =ROUNDUP(AI98*18%,0) -> 24466 | AK98: 135918 | AL98: =N98*300 -> 135918 | AM98: =ROUND(AI98+AC98,0) -> 10051716 | AN98: =ROUNDUP(AJ98+W98+T98+Y98-AB98,0) -> 1214362 | AO98: =AN98+AL98+AR98 -> 1350280 | AP98: =AM98+AO98 -> 11401996 | AQ98: 9995126 | AR98: 0 | AS98: =ROUND(AP98-AQ98,0) -> 1406870 | AT98: 0 | AU98: 8800 | AV98: =AU98*N98 -> 3986928 | AW98: =MAX(AM98,AT98,AV98) -> 10051716 | AX98: =CEILING((AW98),1000) -> 10052000 | AY98: 0.0634 | AZ98: =AY98*AX98 -> 637296.8 | BA98: =CEILING(AZ98,100) -> 637300 | BB98: =BA98+AS98 -> 2044170 | BC98: =L98/J98% -> 0 | BD98: =O98/M98% -> 0 | BE98: 92.12 | BF98: 42.09 | BG98: 46176 | BH98: =BG98+30 -> 46206 | BI98: 6.34 | BL98: =VLOOKUP(A98,[2]Sheet1!$D$2:$H$933,5,0) -> 0 | BM98: UBPL M3M CAPITAL PHASE 2 MASTER ACCOUNT | BN98: 777705551661 | BO98: ICIC0000399 | BP98: ICICI Bank | BQ98: Shop No - 19, 20, Vipul Orchid Plaza, Suncity, Sector 54, Gurgaon, Haryana -122002 | BR98: Union Buildmart Private Limited | BS98: AABCU4843M | BT98: 41st Floor, Tower-1, M3M International Financial center, sector- 66,Gurugram, Haryana, India 122101 | BU98: (……………..)Village Chauma, Sector – 113, Gurugram, Manesar Urban Complex, GURGAON, HARYANA, INDIA PIN Code: 122017 | BV98: Feedback@m3mindia.com | BW98: 8068970077 | BX98: 0 | BY98: Ritika Singh | BZ98: Shubra
A99: R4 245 | B99: M3M Capital Walk in M3M Capital Phase-2 | C99: cwBOOKING/00070/22-23 | D99: cwFLAP/00125/22-23 | E99: Ms. Riya Ganotra | F99: 44875 | G99: BLOCK-04 | H99: FLOOR 2 | I99: Retail | J99: 365.98 | K99: 365.98 | L99: =K99-J99 -> 0 | M99: 156.08 | N99: 156.08 | O99: =N99-M99 -> 0 | P99: 11871.001 | Q99: 27835.399 | R99: 20000 | S99: 4344549 | T99: 521346 | U99: =T99/S99 -> 0.12000003 | V99: =L99*P99 -> 0 | W99: =V99*U99 -> 0 | Z99: =S99+V99+X99 -> 4344549 | AA99: 427214 | AB99: 51266 | AC99: =Z99-AA99 -> 3917335 | AD99: =AE99/M99 -> 300 | AE99: 46824 | AF99: 8428 | AG99: =(AD99*O99) -> 0 | AH99: =AG99*18% -> 0 | AI99: =AD99*N99 -> 46824 | AJ99: =ROUNDUP(AI99*18%,0) -> 8429 | AK99: 46824 | AL99: =N99*300 -> 46824 | AM99: =ROUND(AI99+AC99,0) -> 3964159 | AN99: =ROUNDUP(AJ99+W99+T99+Y99-AB99,0) -> 478509 | AO99: =AN99+AL99+AR99 -> 525333 | AP99: =AM99+AO99 -> 4489492 | AQ99: 3900827 | AR99: 0 | AS99: =ROUND(AP99-AQ99,0) -> 588665 | AT99: 4978654 | AU99: 8800 | AV99: =AU99*N99 -> 1373504 | AW99: =MAX(AM99,AT99,AV99) -> 4978654 | AX99: =CEILING((AW99),1000) -> 4979000 | AY99: 0.05 | AZ99: =AY99*AX99 -> 248950 | BA99: =CEILING(AZ99,100) -> 249000 | BB99: =BA99+AS99 -> 837665 | BC99: =L99/J99% -> 0 | BD99: =O99/M99% -> 0 | BE99: 34 | BF99: 14.5 | BG99: 46176 | BH99: =BG99+30 -> 46206 | BI99: 5 | BL99: =VLOOKUP(A99,[2]Sheet1!$D$2:$H$933,5,0) -> 0 | BM99: UBPL M3M CAPITAL PHASE 2 MASTER ACCOUNT | BN99: 777705551661 | BO99: ICIC0000399 | BP99: ICICI Bank | BQ99: Shop No - 19, 20, Vipul Orchid Plaza, Suncity, Sector 54, Gurgaon, Haryana -122002 | BR99: Union Buildmart Private Limited | BS99: AABCU4843M | BT99: 41st Floor, Tower-1, M3M International Financial center, sector- 66,Gurugram, Haryana, India 122101 | BU99: (……………..)Village Chauma, Sector – 113, Gurugram, Manesar Urban Complex, GURGAON, HARYANA, INDIA PIN Code: 122017 | BV99: Feedback@m3mindia.com | BW99: 8068970077 | BX99: 0 | BY99: Darshan Lal | BZ99: Shubra
A100: R4 246 | B100: M3M Capital Walk in M3M Capital Phase-2 | C100: cwBOOKING/00173/22-23 | D100: cwFLAP/00072/22-23 | E100: Mr. OM KAILASH | F100: 44896 | G100: BLOCK-04 | H100: FLOOR 2 | I100: Retail | J100: 537.12 | K100: 537.12 | L100: =K100-J100 -> 0 | M100: 242.19 | N100: 242.19 | O100: =N100-M100 -> 0 | P100: 9000 | Q100: 19959.866 | R100: 20000 | S100: 4834080 | T100: 580090 | U100: =T100/S100 -> 0.12000008 | V100: =L100*P100 -> 0 | W100: =V100*U100 -> 0 | Z100: =S100+V100+X100 -> 4834080 | AA100: 582679 | AB100: 69922 | AC100: =Z100-AA100 -> 4251401 | AD100: =AE100/M100 -> 300 | AE100: 72657 | AF100: 13078 | AG100: =(AD100*O100) -> 0 | AH100: =AG100*18% -> 0 | AI100: =AD100*N100 -> 72657 | AJ100: =ROUNDUP(AI100*18%,0) -> 13079 | AK100: 72657 | AL100: =N100*300 -> 72657 | AM100: =ROUND(AI100+AC100,0) -> 4324058 | AN100: =ROUNDUP(AJ100+W100+T100+Y100-AB100,0) -> 523247 | AO100: =AN100+AL100+AR100 -> 595904 | AP100: =AM100+AO100 -> 4919962 | AQ100: 3987645 | AR100: 0 | AS100: =ROUND(AP100-AQ100,0) -> 932317 | AT100: 0 | AU100: 8800 | AV100: =AU100*N100 -> 2131272 | AW100: =MAX(AM100,AT100,AV100) -> 4324058 | AX100: =CEILING((AW100),1000) -> 4325000 | AY100: 0.06 | AZ100: =AY100*AX100 -> 259500 | BA100: =CEILING(AZ100,100) -> 259500 | BB100: =BA100+AS100 -> 1191817 | BC100: =L100/J100% -> 0 | BD100: =O100/M100% -> 0 | BE100: 49.9 | BF100: 22.5 | BG100: 46176 | BH100: =BG100+30 -> 46206 | BI100: 6 | BL100: =VLOOKUP(A100,[2]Sheet1!$D$2:$H$933,5,0) -> 0 | BM100: UBPL M3M CAPITAL PHASE 2 MASTER ACCOUNT | BN100: 777705551661 | BO100: ICIC0000399 | BP100: ICICI Bank | BQ100: Shop No - 19, 20, Vipul Orchid Plaza, Suncity, Sector 54, Gurgaon, Haryana -122002 | BR100: Union Buildmart Private Limited | BS100: AABCU4843M | BT100: 41st Floor, Tower-1, M3M International Financial center, sector- 66,Gurugram, Haryana, India 122101 | BU100: (……………..)Village Chauma, Sector – 113, Gurugram, Manesar Urban Complex, GURGAON, HARYANA, INDIA PIN Code: 122017 | BV100: Feedback@m3mindia.com | BW100: 8068970077 | BX100: 0 | BY100: Preeti Chauhan | BZ100: Shubra
...

Sheet Excess Amount Cases
A1: Unit No | B1: Business Unit | C1: Booking No | D1: Application No | E1: Customer Name | F1: Booking Date | G1: Block | H1: Floor | I1: Hierarchy Level 4 | J1: Suer Area (Sq. ft.) | K1: New Super Area (Sq. ft.) | L1: Diff in Super Area | M1: Carpet Area (Sq. ft.) | N1: New Carpet Area (Sq. ft.) | O1: Diff in Carpet Area Area | P1: Super Area Rate (Booking Rate) | Q1: Carpet Area Rate (Booking Rate) | R1: Current Rate | S1: BSP | T1: GST on BSP as per Old Area | U1: GST%age | V1: Increase/Decrease Area cost | W1: GST% on Increase/Decrease Area cost | X1: Increased Unit Cost due to Excess Discount_Basic | Y1: Increased Unit Cost due to Excess Discount_Tax | Z1: BASIC after Increase or Decrease Area | AA1: Discount/Credit Note (Already applied) | AB1: GST on Credit Note | AC1: Basic Sale Price after discount & Adjustment | AD1: PBIC Rate Carpet Area | AE1: PBIC | AF1: Tax on PBIC | AG1: PBIC on Increase or Decrease Area | AH1: Tax on Diff PBIC | AI1: PBIC after Increase or Decrease Area | AJ1: Tax on PBIC after Increase or Decrease Area | AK1: IFMS Amount | AL1: IFMS Amount after Change Area | AM1: Total BSP & PBIC | AN1: Total GST on BSP/ PBIC | AO1: Total GST+IFMS and Interest | AP1: Grand Total | AQ1: Total Received Till Date | AR1: Interest | AS1: Net Payable with Interest | AT1: ATS Value | AU1: Circle Rate | AV1: Value as per Circle rate | AW1: Stamp Duty Calculation on | AX1: Ceiling up to 1000 of Stamp Duty Calculation Value | AY1: Stamp Duty Percentage | AZ1: stamp duty | BA1: actual stamp duty Ceiling up to Rs. 100 | BB1: Final Total Payable | BC1: Area Variation Super % | BD1: Area Variation Carpet % | BE1: Final Super Area (in sq. mt.) | BF1: Final Carpet Area (in sq. mt.) | BG1: Invocie Date | BH1: Due Date | BI1: Stampduty % for mail merge | BJ1: Payment in Favour of | BK1: Account Number | BL1: IFSC Code | BM1: Name of Bank | BN1: Address of Bank Branch | BO1: Name of Builder | BP1: PAN of the Builder | BQ1: Address of the builder | BR1: Address of the Unit/Apartment | BS1: Email ID | BT1: Mobile Number | BU1: Accumulation Amount
A2: R1 134 | B2: M3M Capital Walk in M3M Capital Phase-2 | C2: cwBOOKING/00691/22-23 | D2: cwFLAP/00586/22-23 | E2: Mr. VIKASH KUMAR | F2: 45002 | G2: BLOCK-01 | H2: FLOOR 1 | I2: Retail | J2: 660.91 | K2: 660.91 | L2: 0 | M2: 294.4 | N2: 294.4 | O2: 0 | P2: 10037.76 | Q2: 22534.158 | R2: 22000 | S2: 6634056 | T2: 796086 | U2: 0.11999989 | V2: 0 | W2: 0 | Z2: 6634056 | AA2: 2321919 | AB2: 278630 | AC2: 4312137 | AD2: 300 | AE2: 88320 | AF2: 15898 | AG2: 0 | AH2: 0 | AI2: 88320 | AJ2: 15898 | AK2: 88320 | AL2: 88320 | AM2: 4400457 | AN2: 533354 | AO2: 621674 | AP2: 5022131 | AQ2: 4600998 | AR2: 0 | AS2: 421133 | AT2: 0 | AU2: 8800 | AV2: 2590720 | AW2: 4400457 | AX2: 4401000 | AY2: 0.06 | AZ2: 264060 | BA2: 264100 | BB2: 685233 | BC2: 0 | BD2: 0 | BE2: 61.4 | BF2: 27.35 | BG2: 46176 | BH2: 46206 | BI2: 6 | BJ2: UBPL M3M CAPITAL PHASE 2 MASTER ACCOUNT | BK2: 777705551661 | BL2: ICIC0000399 | BM2: ICICI Bank | BN2: Shop No - 19, 20, Vipul Orchid Plaza, Suncity, Sector 54, Gurgaon, Haryana -122002 | BO2: Union Buildmart Private Limited | BP2: AABCU4843M | BQ2: 41st Floor, Tower-1, M3M International Financial center, sector- 66,Gurugram, Haryana, India 122101 | BR2: (……………..)Village Chauma, Sector – 113, Gurugram, Manesar Urban Complex, GURGAON, HARYANA, INDIA PIN Code: 122017 | BS2: Feedback@m3mindia.com | BT2: 8068970077 | BU2: 771833.33
